Workbook
Name ReceiveType: Cus!#REF!
Name ReceiveType: OtherMaster!$A$2:$A$7
Name User: Cus!#REF!
Name User: OtherMaster!$C$2:$C$5

Sheet Data_CN
A1: Date | B1: Invoice no. | C1: Customer | D1: UPC | E1: SKU | F1: Model Name | G1: Description | H1: Qty | I1: PriceBook | J1: Vat 7% | K1: Total Price (Exclude Vat) | L1: Discount | M1: Payment | N1: Staff | O1: Kerry | P1: Remark | Q1: No.# | R1: =ROUND(SUM(K:K)+SUM(K:K)*7%,2)-R3 -> 17058 | T1: =SUM(T2:T62)-T3 -> 0
A2: 45296 | B2: 105028 | C2: A041 | D2: 4892210204080 | E2: =IFERROR(VLOOKUP(D2,ProductMaster!$A:$B,2,FALSE),"") -> 018472009 | F2: =IFERROR(VLOOKUP(D2,ProductMaster!$A:$C,3,FALSE),"") -> M18 FHX-0X0 | G2: =IFERROR(VLOOKUP($D2,ProductMaster!$A:$O,4,FALSE),"") -> สว่านโรตารี่ไร้สาย 18 โวลต์ 26 มม. SDS PLUS 3 ระบบ (เครื่องเปล่า) | H2: 1 | I2: =IFERROR(VLOOKUP(E2,ProductMaster!B:G,6,FALSE),0) -> 11951.402 | J2: =ROUND(SUM(I2*7%),2) -> 836.6 | K2: =ROUND(SUM(H2*I2),2) -> 11951.4 | M2: Transfer | N2: Cat | O2: 0 | P2: No Tax Invoice | Q2: =IF(B2=B1,Q1+1,1) -> 1 | R2: =SUMIF(B2:K500,S2,K2:K500) -> 0 | S2: 505001 | T2: =R2*1.07 -> 0
A3: 45296 | B3: 105028 | C3: A041 | D3: 4892210139313-BF | E3: =IFERROR(VLOOKUP(D3,ProductMaster!$A:$B,2,FALSE),"") -> 001997014-(BF) | F3: =IFERROR(VLOOKUP(D3,ProductMaster!$A:$C,3,FALSE),"") -> M12-18FCSA-(BF) | G3: =IFERROR(VLOOKUP($D3,ProductMaster!$A:$O,4,FALSE),"") -> แท่นชาร์จแบตเตอรี่ 12-18 โวลต์ แบบชาร์จเร็ว | H3: 1 | I3: =IFERROR(VLOOKUP(E3,ProductMaster!B:G,6,FALSE),0) -> 1766.3551 | J3: =ROUND(SUM(I3*7%),2) -> 123.64 | K3: =ROUND(SUM(H3*I3),2) -> 1766.36 | M3: Transfer | N3: Cat | O3: 0 | P3: No Tax Invoice | Q3: =IF(B3=B2,Q2+1,1) -> 2 | R3: =SUMIF(B3:K501,S3,K3:K501) -> 0 | S3: 505002 | T3: =R3*1.07 -> 0 | U3: บิล 0505002 เปิดบิลใหม่แทนบิล 0105028(ยกเลิกทั้งบิลออกใหม่) เนื่องจากลูกค้าได้แบตไปผิดรุ่น ลูกค้าเพิ่มเงิน 2,200 บาท
A4: 45296 | B4: 105028 | C4: A041 | D4: 4892210220677-BF | E4: =IFERROR(VLOOKUP(D4,ProductMaster!$A:$B,2,FALSE),"") -> 001997033-(BF) | F4: =IFERROR(VLOOKUP(D4,ProductMaster!$A:$C,3,FALSE),"") -> M12HB5-(BF) | G4: =IFERROR(VLOOKUP($D4,ProductMaster!$A:$O,4,FALSE),"") -> แบตเตอรี่ 12 โวลต์ 5.0 แอมป์อาว HIGH OUTPUT | H4: 1 | I4: =IFERROR(VLOOKUP(E4,ProductMaster!B:G,6,FALSE),0) -> 1485.9813 | J4: =ROUND(SUM(I4*7%),2) -> 104.02 | K4: =ROUND(SUM(H4*I4),2) -> 1485.98 | M4: Transfer | N4: Cat | O4: 0 | P4: No Tax Invoice | Q4: =IF(B4=B3,Q3+1,1) -> 3 | R4: =SUMIF(B4:K502,S4,K4:K502) -> 0 | S4: 505003 | T4: =R4*1.07 -> 0
A5: 45416 | B5: 405004 | C5: A091 | D5: 4892210130266-BF | E5: =IFERROR(VLOOKUP(D5,ProductMaster!$A:$B,2,FALSE),"") -> 001998232-(BF) | F5: =IFERROR(VLOOKUP(D5,ProductMaster!$A:$C,3,FALSE),"") -> M12B2ASIA-(BF) | G5: =IFERROR(VLOOKUP($D5,ProductMaster!$A:$O,4,FALSE),"") -> แบตเตอรี่ 12 โวลต์ 2.0 แอมป์อาว | H5: 1 | I5: =IFERROR(VLOOKUP(E5,ProductMaster!B:G,6,FALSE),0) -> 738.31776 | J5: =ROUND(SUM(I5*7%),2) -> 51.68 | K5: =ROUND(SUM(H5*I5),2) -> 738.32 | M5: Transfer | N5: Cat | O5: 0 | P5: No Tax Invoice | Q5: =IF(B5=B4,Q4+1,1) -> 1 | R5: =SUMIF(B5:K503,S5,K5:K503) -> 0 | S5: 505004 | T5: =R5*1.07 -> 0
E6: =IFERROR(VLOOKUP(D6,ProductMaster!$A:$B,2,FALSE),"") | F6: =IFERROR(VLOOKUP(D6,ProductMaster!$A:$C,3,FALSE),"") | G6: =IFERROR(VLOOKUP($D6,ProductMaster!$A:$O,4,FALSE),"") | I6: =IFERROR(VLOOKUP(E6,ProductMaster!B:G,6,FALSE),0) -> 0 | J6: =ROUND(SUM(I6*7%),2) -> 0 | K6: =ROUND(SUM(H6*I6),2) -> 0 | M6: Transfer | N6: Cat | O6: 0 | P6: No Tax Invoice | Q6: =IF(B6=B5,Q5+1,1) -> 1 | R6: =SUMIF(B6:K504,S6,K6:K504) -> 0 | S6: 505005 | T6: =R6*1.07 -> 0
E7: =IFERROR(VLOOKUP(D7,ProductMaster!$A:$B,2,FALSE),"") | F7: =IFERROR(VLOOKUP(D7,ProductMaster!$A:$C,3,FALSE),"") | G7: =IFERROR(VLOOKUP($D7,ProductMaster!$A:$O,4,FALSE),"") | I7: =IFERROR(VLOOKUP(E7,ProductMaster!B:G,6,FALSE),0) -> 0 | J7: =ROUND(SUM(I7*7%),2) -> 0 | K7: =ROUND(SUM(H7*I7),2) -> 0 | M7: Credit Card | N7: Cat | O7: 0 | P7: Tax Invoice | Q7: =IF(B7=B6,Q6+1,1) -> 2 | R7: =SUMIF(B7:K505,S7,K7:K505) -> 0 | S7: 505006 | T7: =R7*1.07 -> 0
E8: =IFERROR(VLOOKUP(D8,ProductMaster!$A:$B,2,FALSE),"") | F8: =IFERROR(VLOOKUP(D8,ProductMaster!$A:$C,3,FALSE),"") | G8: =IFERROR(VLOOKUP($D8,ProductMaster!$A:$O,4,FALSE),"") | I8: =IFERROR(VLOOKUP(E8,ProductMaster!B:G,6,FALSE),0) -> 0 | J8: =ROUND(SUM(I8*7%),2) -> 0 | K8: =ROUND(SUM(H8*I8),2) -> 0 | M8: Credit Card | N8: Cat | O8: 0 | P8: Tax Invoice | Q8: =IF(B8=B7,Q7+1,1) -> 3 | R8: =SUMIF(B8:K506,S8,K8:K506) -> 0 | S8: 505007 | T8: =R8*1.07 -> 0
E9: =IFERROR(VLOOKUP(D9,ProductMaster!$A:$B,2,FALSE),"") | F9: =IFERROR(VLOOKUP(D9,ProductMaster!$A:$C,3,FALSE),"") | G9: =IFERROR(VLOOKUP($D9,ProductMaster!$A:$O,4,FALSE),"") | I9: =IFERROR(VLOOKUP(E9,ProductMaster!B:G,6,FALSE),0) -> 0 | J9: =ROUND(SUM(I9*7%),2) -> 0 | K9: =ROUND(SUM(H9*I9),2) -> 0 | M9: Credit Card | N9: Cat | O9: 0 | P9: Tax Invoice | Q9: =IF(B9=B8,Q8+1,1) -> 4 | R9: =SUMIF(B9:K507,S9,K9:K507) -> 0 | S9: 505008 | T9: =R9*1.07 -> 0
E10: =IFERROR(VLOOKUP(D10,ProductMaster!$A:$B,2,FALSE),"") | F10: =IFERROR(VLOOKUP(D10,ProductMaster!$A:$C,3,FALSE),"") | G10: =IFERROR(VLOOKUP($D10,ProductMaster!$A:$O,4,FALSE),"") | I10: =IFERROR(VLOOKUP(E10,ProductMaster!B:G,6,FALSE),0) -> 0 | J10: =ROUND(SUM(I10*7%),2) -> 0 | K10: =ROUND(SUM(H10*I10),2) -> 0 | M10: Credit Card | N10: Cat | O10: 0 | P10: Tax Invoice | Q10: =IF(B10=B9,Q9+1,1) -> 5 | R10: =SUMIF(B10:K508,S10,K10:K508) -> 0 | S10: 505009 | T10: =R10*1.07 -> 0
E11: =IFERROR(VLOOKUP(D11,ProductMaster!$A:$B,2,FALSE),"") | F11: =IFERROR(VLOOKUP(D11,ProductMaster!$A:$C,3,FALSE),"") | G11: =IFERROR(VLOOKUP($D11,ProductMaster!$A:$O,4,FALSE),"") | I11: =IFERROR(VLOOKUP(E11,ProductMaster!B:G,6,FALSE),0) -> 0 | J11: =ROUND(SUM(I11*7%),2) -> 0 | K11: =ROUND(SUM(H11*I11),2) -> 0 | M11: Credit Card | N11: Cat | O11: 0 | P11: Tax Invoice | Q11: =IF(B11=B10,Q10+1,1) -> 6 | R11: =SUMIF(B11:K509,S11,K11:K509) -> 0 | S11: 505010 | T11: =R11*1.07 -> 0
E12: =IFERROR(VLOOKUP(D12,ProductMaster!$A:$B,2,FALSE),"") | F12: =IFERROR(VLOOKUP(D12,ProductMaster!$A:$C,3,FALSE),"") | G12: =IFERROR(VLOOKUP($D12,ProductMaster!$A:$O,4,FALSE),"") | I12: =IFERROR(VLOOKUP(E12,ProductMaster!B:G,6,FALSE),0) -> 0 | J12: =ROUND(SUM(I12*7%),2) -> 0 | K12: =ROUND(SUM(H12*I12),2) -> 0 | M12: Cash | N12: Cat | O12: 0 | P12: No Tax Invoice | Q12: =IF(B12=B11,Q11+1,1) -> 7 | R12: =SUMIF(B12:K510,S12,K12:K510) -> 0 | S12: 505011 | T12: =R12*1.07 -> 0
E13: =IFERROR(VLOOKUP(D13,ProductMaster!$A:$B,2,FALSE),"") | F13: =IFERROR(VLOOKUP(D13,ProductMaster!$A:$C,3,FALSE),"") | G13: =IFERROR(VLOOKUP($D13,ProductMaster!$A:$O,4,FALSE),"") | I13: =IFERROR(VLOOKUP(E13,ProductMaster!B:G,6,FALSE),0) -> 0 | J13: =ROUND(SUM(I13*7%),2) -> 0 | K13: =ROUND(SUM(H13*I13),2) -> 0 | M13: Cash | N13: Cat | O13: 0 | P13: No Tax Invoice | Q13: =IF(B13=B12,Q12+1,1) -> 8 | R13: =SUMIF(B13:K511,S13,K13:K511) -> 0 | S13: 505012 | T13: =R13*1.07 -> 0
E14: =IFERROR(VLOOKUP(D14,ProductMaster!$A:$B,2,FALSE),"") | F14: =IFERROR(VLOOKUP(D14,ProductMaster!$A:$C,3,FALSE),"") | G14: =IFERROR(VLOOKUP($D14,ProductMaster!$A:$O,4,FALSE),"") | I14: =IFERROR(VLOOKUP(E14,ProductMaster!B:G,6,FALSE),0) -> 0 | J14: =ROUND(SUM(I14*7%),2) -> 0 | K14: =ROUND(SUM(H14*I14),2) -> 0 | M14: Cash | N14: Cat | O14: 0 | P14: No Tax Invoice | Q14: =IF(B14=B13,Q13+1,1) -> 9 | R14: =SUMIF(B14:K512,S14,K14:K512) -> 0 | S14: 505013 | T14: =R14*1.07 -> 0
E15: =IFERROR(VLOOKUP(D15,ProductMaster!$A:$B,2,FALSE),"") | F15: =IFERROR(VLOOKUP(D15,ProductMaster!$A:$C,3,FALSE),"") | G15: =IFERROR(VLOOKUP($D15,ProductMaster!$A:$O,4,FALSE),"") | I15: =IFERROR(VLOOKUP(E15,ProductMaster!B:G,6,FALSE),0) -> 0 | J15: =ROUND(SUM(I15*7%),2) -> 0 | K15: =ROUND(SUM(H15*I15),2) -> 0 | M15: Cash | N15: Cat | O15: 0 | P15: No Tax Invoice | Q15: =IF(B15=B14,Q14+1,1) -> 10 | R15: =SUMIF(B15:K513,S15,K15:K513) -> 0 | S15: 505014 | T15: =R15*1.07 -> 0
E16: =IFERROR(VLOOKUP(D16,ProductMaster!$A:$B,2,FALSE),"") | F16: =IFERROR(VLOOKUP(D16,ProductMaster!$A:$C,3,FALSE),"") | G16: =IFERROR(VLOOKUP($D16,ProductMaster!$A:$O,4,FALSE),"") | I16: =IFERROR(VLOOKUP(E16,ProductMaster!B:G,6,FALSE),0) -> 0 | J16: =ROUND(SUM(I16*7%),2) -> 0 | K16: =ROUND(SUM(H16*I16),2) -> 0 | M16: Transfer | N16: Cat | O16: 0 | P16: No Tax Invoice | Q16: =IF(B16=B15,Q15+1,1) -> 11 | R16: =SUMIF(B16:K514,S16,K16:K514) -> 0 | S16: 505015 | T16: =R16*1.07 -> 0
E17: =IFERROR(VLOOKUP(D17,ProductMaster!$A:$B,2,FALSE),"") | F17: =IFERROR(VLOOKUP(D17,ProductMaster!$A:$C,3,FALSE),"") | G17: =IFERROR(VLOOKUP($D17,ProductMaster!$A:$O,4,FALSE),"") | I17: =IFERROR(VLOOKUP(E17,ProductMaster!B:G,6,FALSE),0) -> 0 | J17: =ROUND(SUM(I17*7%),2) -> 0 | K17: =ROUND(SUM(H17*I17),2) -> 0 | M17: Transfer | N17: Cat | O17: 0 | P17: No Tax Invoice | Q17: =IF(B17=B16,Q16+1,1) -> 12 | R17: =SUMIF(B17:K515,S17,K17:K515) -> 0 | S17: 505016 | T17: =R17*1.07 -> 0
... E20: =IFERROR(VLOOKUP(D20,ProductMaster!$A:$B,2,FALSE),"") | F20: =IFERROR(VLOOKUP(D20,ProductMaster!$A:$C,3,FALSE),"") | G20: =IFERROR(VLOOKUP($D20,ProductMaster!$A:$O,4,FALSE),"") | I20: =IFERROR(VLOOKUP(E20,ProductMaster!B:G,6,FALSE),0) -> 0 | J20: =ROUND(SUM(I20*7%),2) -> 0 | K20: =ROUND(SUM(H20*I20),2) -> 0 | M20: Transfer | N20: Cat | O20: 0 | P20: No Tax Invoice | Q20: =IF(B20=B19,Q19+1,1) -> 15 | R20: =SUMIF(B20:K518,S20,K20:K518) -> 0 | S20: 505019 | T20: =R20*1.07 -> 0
E21: =IFERROR(VLOOKUP(D21,ProductMaster!$A:$B,2,FALSE),"") | F21: =IFERROR(VLOOKUP(D21,ProductMaster!$A:$C,3,FALSE),"") | G21: =IFERROR(VLOOKUP($D21,ProductMaster!$A:$O,4,FALSE),"") | I21: =IFERROR(VLOOKUP(E21,ProductMaster!B:G,6,FALSE),0) -> 0 | J21: =ROUND(SUM(I21*7%),2) -> 0 | K21: =ROUND(SUM(H21*I21),2) -> 0 | M21: Transfer | N21: Cat | O21: 0 | P21: No Tax Invoice | Q21: =IF(B21=B20,Q20+1,1) -> 16 | R21: =SUMIF(B21:K519,S21,K21:K519) -> 0 | S21: 505020 | T21: =R21*1.07 -> 0 | U21: โอนรวมกับบิล 0505002 ยอด 2,288
E22: =IFERROR(VLOOKUP(D22,ProductMaster!$A:$B,2,FALSE),"") | F22: =IFERROR(VLOOKUP(D22,ProductMaster!$A:$C,3,FALSE),"") | G22: =IFERROR(VLOOKUP($D22,ProductMaster!$A:$O,4,FALSE),"") | I22: =IFERROR(VLOOKUP(E22,ProductMaster!B:G,6,FALSE),0) -> 0 | J22: =ROUND(SUM(I22*7%),2) -> 0 | K22: =ROUND(SUM(H22*I22),2) -> 0 | M22: Transfer | N22: Cat | O22: 0 | P22: No Tax Invoice | Q22: =IF(B22=B21,Q21+1,1) -> 17 | R22: =SUMIF(B22:K520,S22,K22:K520) -> 0 | S22: 505021 | T22: =R22*1.07 -> 0
E23: =IFERROR(VLOOKUP(D23,ProductMaster!$A:$B,2,FALSE),"") | F23: =IFERROR(VLOOKUP(D23,ProductMaster!$A:$C,3,FALSE),"") | G23: =IFERROR(VLOOKUP($D23,ProductMaster!$A:$O,4,FALSE),"") | I23: =IFERROR(VLOOKUP(E23,ProductMaster!B:G,6,FALSE),0) -> 0 | J23: =ROUND(SUM(I23*7%),2) -> 0 | K23: =ROUND(SUM(H23*I23),2) -> 0 | M23: Transfer | N23: Cat | O23: 0 | P23: No Tax Invoice | Q23: =IF(B23=B22,Q22+1,1) -> 18 | R23: =SUMIF(B23:K521,S23,K23:K521) -> 0 | S23: 505022 | T23: =R23*1.07 -> 0
E24: =IFERROR(VLOOKUP(D24,ProductMaster!$A:$B,2,FALSE),"") | F24: =IFERROR(VLOOKUP(D24,ProductMaster!$A:$C,3,FALSE),"") | G24: =IFERROR(VLOOKUP($D24,ProductMaster!$A:$O,4,FALSE),"") | I24: =IFERROR(VLOOKUP(E24,ProductMaster!B:G,6,FALSE),0) -> 0 | J24: =ROUND(SUM(I24*7%),2) -> 0 | K24: =ROUND(SUM(H24*I24),2) -> 0 | M24: Transfer | N24: Cat | O24: 0 | P24: No Tax Invoice | Q24: =IF(B24=B23,Q23+1,1) -> 19 | R24: =SUMIF(B24:K522,S24,K24:K522) -> 0 | S24: 505023 | T24: =R24*1.07 -> 0
E25: =IFERROR(VLOOKUP(D25,ProductMaster!$A:$B,2,FALSE),"") | F25: =IFERROR(VLOOKUP(D25,ProductMaster!$A:$C,3,FALSE),"") | G25: =IFERROR(VLOOKUP($D25,ProductMaster!$A:$O,4,FALSE),"") | I25: =IFERROR(VLOOKUP(E25,ProductMaster!B:G,6,FALSE),0) -> 0 | J25: =ROUND(SUM(I25*7%),2) -> 0 | K25: =ROUND(SUM(H25*I25),2) -> 0 | M25: Transfer | N25: Cat | O25: 0 | P25: No Tax Invoice | Q25: =IF(B25=B24,Q24+1,1) -> 20 | R25: =SUMIF(B25:K523,S25,K25:K523) -> 0 | S25: 505024 | T25: =R25*1.07 -> 0
E26: =IFERROR(VLOOKUP(D26,ProductMaster!$A:$B,2,FALSE),"") | F26: =IFERROR(VLOOKUP(D26,ProductMaster!$A:$C,3,FALSE),"") | G26: =IFERROR(VLOOKUP($D26,ProductMaster!$A:$O,4,FALSE),"") | I26: =IFERROR(VLOOKUP(E26,ProductMaster!B:G,6,FALSE),0) -> 0 | J26: =ROUND(SUM(I26*7%),2) -> 0 | K26: =ROUND(SUM(H26*I26),2) -> 0 | M26: Transfer | N26: Cat | O26: 0 | P26: No Tax Invoice | Q26: =IF(B26=B25,Q25+1,1) -> 21 | R26: =SUMIF(B26:K524,S26,K26:K524) -> 0 | S26: 505025 | T26: =R26*1.07 -> 0
E27: =IFERROR(VLOOKUP(D27,ProductMaster!$A:$B,2,FALSE),"") | F27: =IFERROR(VLOOKUP(D27,ProductMaster!$A:$C,3,FALSE),"") | G27: =IFERROR(VLOOKUP($D27,ProductMaster!$A:$O,4,FALSE),"") | I27: =IFERROR(VLOOKUP(E27,ProductMaster!B:G,6,FALSE),0) -> 0 | J27: =ROUND(SUM(I27*7%),2) -> 0 | K27: =ROUND(SUM(H27*I27),2) -> 0 | M27: Transfer | N27: Cat | O27: 0 | P27: No Tax Invoice | Q27: =IF(B27=B26,Q26+1,1) -> 22 | R27: =SUMIF(B27:K525,S27,K27:K525) -> 0 | S27: 505026 | T27: =R27*1.07 -> 0
E28: =IFERROR(VLOOKUP(D28,ProductMaster!$A:$B,2,FALSE),"") | F28: =IFERROR(VLOOKUP(D28,ProductMaster!$A:$C,3,FALSE),"") | G28: =IFERROR(VLOOKUP($D28,ProductMaster!$A:$O,4,FALSE),"") | I28: =IFERROR(VLOOKUP(E28,ProductMaster!B:G,6,FALSE),0) -> 0 | J28: =ROUND(SUM(I28*7%),2) -> 0 | K28: =ROUND(SUM(H28*I28),2) -> 0 | M28: Transfer | N28: Cat | O28: 0 | P28: No Tax Invoice | Q28: =IF(B28=B27,Q27+1,1) -> 23 | R28: =SUMIF(B28:K526,S28,K28:K526) -> 0 | S28: 505027 | T28: =R28*1.07 -> 0
E29: =IFERROR(VLOOKUP(D29,ProductMaster!$A:$B,2,FALSE),"") | F29: =IFERROR(VLOOKUP(D29,ProductMaster!$A:$C,3,FALSE),"") | G29: =IFERROR(VLOOKUP($D29,ProductMaster!$A:$O,4,FALSE),"") | I29: =IFERROR(VLOOKUP(E29,ProductMaster!B:G,6,FALSE),0) -> 0 | J29: =ROUND(SUM(I29*7%),2) -> 0 | K29: =ROUND(SUM(H29*I29),2) -> 0 | M29: Transfer | N29: Cat | O29: 0 | P29: No Tax Invoice | Q29: =IF(B29=B28,Q28+1,1) -> 24 | R29: =SUMIF(B29:K527,S29,K29:K527) -> 0 | S29: 505028 | T29: =R29*1.07 -> 0
E30: =IFERROR(VLOOKUP(D30,ProductMaster!$A:$B,2,FALSE),"") | F30: =IFERROR(VLOOKUP(D30,ProductMaster!$A:$C,3,FALSE),"") | G30: =IFERROR(VLOOKUP($D30,ProductMaster!$A:$O,4,FALSE),"") | I30: =IFERROR(VLOOKUP(E30,ProductMaster!B:G,6,FALSE),0) -> 0 | J30: =ROUND(SUM(I30*7%),2) -> 0 | K30: =ROUND(SUM(H30*I30),2) -> 0 | M30: Transfer | N30: Cat | O30: 0 | P30: No Tax Invoice | Q30: =IF(B30=B29,Q29+1,1) -> 25 | R30: =SUMIF(B30:K528,S30,K30:K528) -> 0 | S30: 505029 | T30: =R30*1.07 -> 0
E31: =IFERROR(VLOOKUP(D31,ProductMaster!$A:$B,2,FALSE),"") | F31: =IFERROR(VLOOKUP(D31,ProductMaster!$A:$C,3,FALSE),"") | G31: =IFERROR(VLOOKUP($D31,ProductMaster!$A:$O,4,FALSE),"") | I31: =IFERROR(VLOOKUP(E31,ProductMaster!B:G,6,FALSE),0) -> 0 | J31: =ROUND(SUM(I31*7%),2) -> 0 | K31: =ROUND(SUM(H31*I31),2) -> 0 | M31: Transfer | N31: Cat | O31: 0 | P31: No Tax Invoice | Q31: =IF(B31=B30,Q30+1,1) -> 26 | R31: =SUMIF(B31:K529,S31,K31:K529) -> 0 | S31: 505030 | T31: =R31*1.07 -> 0
E32: =IFERROR(VLOOKUP(D32,ProductMaster!$A:$B,2,FALSE),"") | F32: =IFERROR(VLOOKUP(D32,ProductMaster!$A:$C,3,FALSE),"") | G32: =IFERROR(VLOOKUP($D32,ProductMaster!$A:$O,4,FALSE),"") | I32: =IFERROR(VLOOKUP(E32,ProductMaster!B:G,6,FALSE),0) -> 0 | J32: =ROUND(SUM(I32*7%),2) -> 0 | K32: =ROUND(SUM(H32*I32),2) -> 0 | M32: Transfer | N32: Cat | O32: 0 | P32: No Tax Invoice | Q32: =IF(B32=B31,Q31+1,1) -> 27 | R32: =SUMIF(B32:K530,S32,K32:K530) -> 0 | S32: 505031 | T32: =R32*1.07 -> 0
E33: =IFERROR(VLOOKUP(D33,ProductMaster!$A:$B,2,FALSE),"") | F33: =IFERROR(VLOOKUP(D33,ProductMaster!$A:$C,3,FALSE),"") | G33: =IFERROR(VLOOKUP($D33,ProductMaster!$A:$O,4,FALSE),"") | I33: =IFERROR(VLOOKUP(E33,ProductMaster!B:G,6,FALSE),0) -> 0 | J33: =ROUND(SUM(I33*7%),2) -> 0 | K33: =ROUND(SUM(H33*I33),2) -> 0 | M33: Transfer | N33: Cat | O33: 0 | P33: No Tax Invoice | Q33: =IF(B33=B32,Q32+1,1) -> 28 | R33: =SUMIF(B33:K531,S33,K33:K531) -> 0 | S33: 505032 | T33: =R33*1.07 -> 0
... E45: =IFERROR(VLOOKUP(D45,ProductMaster!$A:$B,2,FALSE),"") | F45: =IFERROR(VLOOKUP(D45,ProductMaster!$A:$C,3,FALSE),"") | G45: =IFERROR(VLOOKUP($D45,ProductMaster!$A:$O,4,FALSE),"") | I45: =IFERROR(VLOOKUP(E45,ProductMaster!B:G,6,FALSE),0) -> 0 | J45: =ROUND(SUM(I45*7%),2) -> 0 | K45: =ROUND(SUM(H45*I45),2) -> 0 | M45: Transfer | N45: Cat | O45: 0 | P45: No Tax Invoice | Q45: =IF(B45=B44,Q44+1,1) -> 40 | R45: =SUMIF(B45:K543,S45,K45:K543) -> 0 | S45: 505044 | T45: =R45*1.07 -> 0
E46: =IFERROR(VLOOKUP(D46,ProductMaster!$A:$B,2,FALSE),"") | F46: =IFERROR(VLOOKUP(D46,ProductMaster!$A:$C,3,FALSE),"") | G46: =IFERROR(VLOOKUP($D46,ProductMaster!$A:$O,4,FALSE),"") | I46: =IFERROR(VLOOKUP(E46,ProductMaster!B:G,6,FALSE),0) -> 0 | J46: =ROUND(SUM(I46*7%),2) -> 0 | K46: =ROUND(SUM(H46*I46),2) -> 0 | M46: Transfer | N46: Cat | O46: 0 | P46: No Tax Invoice | Q46: =IF(B46=B45,Q45+1,1) -> 41 | R46: =SUMIF(B46:K544,S46,K46:K544) -> 0 | S46: 505045 | T46: =R46*1.07 -> 0 | W46: =+V46-V45 -> 0
E47: =IFERROR(VLOOKUP(D47,ProductMaster!$A:$B,2,FALSE),"") | F47: =IFERROR(VLOOKUP(D47,ProductMaster!$A:$C,3,FALSE),"") | G47: =IFERROR(VLOOKUP($D47,ProductMaster!$A:$O,4,FALSE),"") | I47: =IFERROR(VLOOKUP(E47,ProductMaster!B:G,6,FALSE),0) -> 0 | J47: =ROUND(SUM(I47*7%),2) -> 0 | K47: =ROUND(SUM(H47*I47),2) -> 0 | M47: Transfer | N47: Cat | O47: 0 | P47: No Tax Invoice | Q47: =IF(B47=B46,Q46+1,1) -> 42 | R47: =SUMIF(B47:K545,S47,K47:K545) -> 0 | S47: 505046 | T47: =R47*1.07 -> 0
E48: =IFERROR(VLOOKUP(D48,ProductMaster!$A:$B,2,FALSE),"") | F48: =IFERROR(VLOOKUP(D48,ProductMaster!$A:$C,3,FALSE),"") | G48: =IFERROR(VLOOKUP($D48,ProductMaster!$A:$O,4,FALSE),"") | I48: =IFERROR(VLOOKUP(E48,ProductMaster!B:G,6,FALSE),0) -> 0 | J48: =ROUND(SUM(I48*7%),2) -> 0 | K48: =ROUND(SUM(H48*I48),2) -> 0 | M48: Transfer | N48: Cat | O48: 0 | P48: No Tax Invoice | Q48: =IF(B48=B47,Q47+1,1) -> 43 | R48: =SUMIF(B48:K546,S48,K48:K546) -> 0 | S48: 505047 | T48: =R48*1.07 -> 0
E49: =IFERROR(VLOOKUP(D49,ProductMaster!$A:$B,2,FALSE),"") | F49: =IFERROR(VLOOKUP(D49,ProductMaster!$A:$C,3,FALSE),"") | G49: =IFERROR(VLOOKUP($D49,ProductMaster!$A:$O,4,FALSE),"") | I49: =IFERROR(VLOOKUP(E49,ProductMaster!B:G,6,FALSE),0) -> 0 | J49: =ROUND(SUM(I49*7%),2) -> 0 | K49: =ROUND(SUM(H49*I49),2) -> 0 | M49: Transfer | N49: Cat | O49: 0 | P49: No Tax Invoice | Q49: =IF(B49=B48,Q48+1,1) -> 44 | R49: =SUMIF(B49:K547,S49,K49:K547) -> 0 | S49: 505048 | T49: =R49*1.07 -> 0
E50: =IFERROR(VLOOKUP(D50,ProductMaster!$A:$B,2,FALSE),"") | F50: =IFERROR(VLOOKUP(D50,ProductMaster!$A:$C,3,FALSE),"") | G50: =IFERROR(VLOOKUP($D50,ProductMaster!$A:$O,4,FALSE),"") | I50: =IFERROR(VLOOKUP(E50,ProductMaster!B:G,6,FALSE),0) -> 0 | J50: =ROUND(SUM(I50*7%),2) -> 0 | K50: =ROUND(SUM(H50*I50),2) -> 0 | M50: Transfer | N50: Cat | O50: 0 | P50: No Tax Invoice | Q50: =IF(B50=B49,Q49+1,1) -> 45 | R50: =SUMIF(B50:K548,S50,K50:K548) -> 0 | S50: 505049 | T50: =R50*1.07 -> 0
E51: =IFERROR(VLOOKUP(D51,ProductMaster!$A:$B,2,FALSE),"") | F51: =IFERROR(VLOOKUP(D51,ProductMaster!$A:$C,3,FALSE),"") | G51: =IFERROR(VLOOKUP($D51,ProductMaster!$A:$O,4,FALSE),"") | I51: =IFERROR(VLOOKUP(E51,ProductMaster!B:G,6,FALSE),0) -> 0 | J51: =ROUND(SUM(I51*7%),2) -> 0 | K51: =ROUND(SUM(H51*I51),2) -> 0 | M51: Transfer | N51: Cat | O51: 0 | P51: No Tax Invoice | Q51: =IF(B51=B50,Q50+1,1) -> 46 | R51: =SUMIF(B51:K549,S51,K51:K549) -> 0 | S51: 505050 | T51: =R51*1.07 -> 0
E52: =IFERROR(VLOOKUP(D52,ProductMaster!$A:$B,2,FALSE),"") | F52: =IFERROR(VLOOKUP(D52,ProductMaster!$A:$C,3,FALSE),"") | G52: =IFERROR(VLOOKUP($D52,ProductMaster!$A:$O,4,FALSE),"") | I52: =IFERROR(VLOOKUP(E52,ProductMaster!B:G,6,FALSE),0) -> 0 | J52: =ROUND(SUM(I52*7%),2) -> 0 | K52: =ROUND(SUM(H52*I52),2) -> 0 | M52: Transfer | N52: Cat | O52: 0 | P52: No Tax Invoice | Q52: =IF(B52=B51,Q51+1,1) -> 47 | R52: =SUMIF(B52:K550,S52,K52:K550) -> 0 | S52: 505051 | T52: =R52*1.07 -> 0
E53: =IFERROR(VLOOKUP(D53,ProductMaster!$A:$B,2,FALSE),"") | F53: =IFERROR(VLOOKUP(D53,ProductMaster!$A:$C,3,FALSE),"") | G53: =IFERROR(VLOOKUP($D53,ProductMaster!$A:$O,4,FALSE),"") | I53: =IFERROR(VLOOKUP(E53,ProductMaster!B:G,6,FALSE),0) -> 0 | J53: =ROUND(SUM(I53*7%),2) -> 0 | K53: =ROUND(SUM(H53*I53),2) -> 0 | M53: Transfer | N53: Cat | O53: 0 | P53: No Tax Invoice | Q53: =IF(B53=B52,Q52+1,1) -> 48 | R53: =SUMIF(B53:K551,S53,K53:K551) -> 0 | S53: 505052 | T53: =R53*1.07 -> 0
E54: =IFERROR(VLOOKUP(D54,ProductMaster!$A:$B,2,FALSE),"") | F54: =IFERROR(VLOOKUP(D54,ProductMaster!$A:$C,3,FALSE),"") | G54: =IFERROR(VLOOKUP($D54,ProductMaster!$A:$O,4,FALSE),"") | I54: =IFERROR(VLOOKUP(E54,ProductMaster!B:G,6,FALSE),0) -> 0 | J54: =ROUND(SUM(I54*7%),2) -> 0 | K54: =ROUND(SUM(H54*I54),2) -> 0 | M54: Transfer | N54: Cat | O54: 0 | P54: No Tax Invoice | Q54: =IF(B54=B53,Q53+1,1) -> 49 | R54: =SUMIF(B54:K552,S54,K54:K552) -> 0 | S54: 505053 | T54: =R54*1.07 -> 0
E55: =IFERROR(VLOOKUP(D55,ProductMaster!$A:$B,2,FALSE),"") | F55: =IFERROR(VLOOKUP(D55,ProductMaster!$A:$C,3,FALSE),"") | G55: =IFERROR(VLOOKUP($D55,ProductMaster!$A:$O,4,FALSE),"") | I55: =IFERROR(VLOOKUP(E55,ProductMaster!B:G,6,FALSE),0) -> 0 | J55: =ROUND(SUM(I55*7%),2) -> 0 | K55: =ROUND(SUM(H55*I55),2) -> 0 | M55: Transfer | N55: Cat | O55: 0 | P55: No Tax Invoice | Q55: =IF(B55=B54,Q54+1,1) -> 50 | R55: =SUMIF(B55:K553,S55,K55:K553) -> 0 | S55: 505054 | T55: =R55*1.07 -> 0
E56: =IFERROR(VLOOKUP(D56,ProductMaster!$A:$B,2,FALSE),"") | F56: =IFERROR(VLOOKUP(D56,ProductMaster!$A:$C,3,FALSE),"") | G56: =IFERROR(VLOOKUP($D56,ProductMaster!$A:$O,4,FALSE),"") | I56: =IFERROR(VLOOKUP(E56,ProductMaster!B:G,6,FALSE),0) -> 0 | J56: =ROUND(SUM(I56*7%),2) -> 0 | K56: =ROUND(SUM(H56*I56),2) -> 0 | M56: Transfer | N56: Cat | O56: 0 | P56: No Tax Invoice | Q56: =IF(B56=B55,Q55+1,1) -> 51 | R56: =SUMIF(B56:K554,S56,K56:K554) -> 0 | S56: 505055 | T56: =R56*1.07 -> 0
E57: =IFERROR(VLOOKUP(D57,ProductMaster!$A:$B,2,FALSE),"") | F57: =IFERROR(VLOOKUP(D57,ProductMaster!$A:$C,3,FALSE),"") | G57: =IFERROR(VLOOKUP($D57,ProductMaster!$A:$O,4,FALSE),"") | I57: =IFERROR(VLOOKUP(E57,ProductMaster!B:G,6,FALSE),0) -> 0 | J57: =ROUND(SUM(I57*7%),2) -> 0 | K57: =ROUND(SUM(H57*I57),2) -> 0 | M57: Transfer | N57: Cat | O57: 0 | P57: No Tax Invoice | Q57: =IF(B57=B56,Q56+1,1) -> 52 | R57: =SUMIF(B57:K555,S57,K57:K555) -> 0 | S57: 505056 | T57: =R57*1.07 -> 0
E58: =IFERROR(VLOOKUP(D58,ProductMaster!$A:$B,2,FALSE),"") | F58: =IFERROR(VLOOKUP(D58,ProductMaster!$A:$C,3,FALSE),"") | G58: =IFERROR(VLOOKUP($D58,ProductMaster!$A:$O,4,FALSE),"") | I58: =IFERROR(VLOOKUP(E58,ProductMaster!B:G,6,FALSE),0) -> 0 | J58: =ROUND(SUM(I58*7%),2) -> 0 | K58: =ROUND(SUM(H58*I58),2) -> 0 | M58: Transfer | N58: Cat | O58: 0 | P58: No Tax Invoice | Q58: =IF(B58=B57,Q57+1,1) -> 53 | R58: =SUMIF(B58:K556,S58,K58:K556) -> 0 | S58: 505057 | T58: =R58*1.07 -> 0
... E62: =IFERROR(VLOOKUP(D62,ProductMaster!$A:$B,2,FALSE),"") | F62: =IFERROR(VLOOKUP(D62,ProductMaster!$A:$C,3,FALSE),"") | G62: =IFERROR(VLOOKUP($D62,ProductMaster!$A:$O,4,FALSE),"") | I62: =IFERROR(VLOOKUP(E62,ProductMaster!B:G,6,FALSE),0) -> 0 | J62: =ROUND(SUM(I62*7%),2) -> 0 | K62: =ROUND(SUM(H62*I62),2) -> 0 | M62: Transfer | N62: Cat | O62: 0 | P62: No Tax Invoice | Q62: =IF(B62=B61,Q61+1,1) -> 57 | R62: =SUMIF(B62:K560,S62,K62:K560) -> 0 | S62: 505061 | T62: =R62*1.07 -> 0
E63: =IFERROR(VLOOKUP(D63,ProductMaster!$A:$B,2,FALSE),"") | F63: =IFERROR(VLOOKUP(D63,ProductMaster!$A:$C,3,FALSE),"") | G63: =IFERROR(VLOOKUP($D63,ProductMaster!$A:$O,4,FALSE),"") | I63: =IFERROR(VLOOKUP(E63,ProductMaster!B:G,6,FALSE),0) -> 0 | J63: =ROUND(SUM(I63*7%),2) -> 0 | K63: =ROUND(SUM(H63*I63),2) -> 0 | M63: Transfer | N63: Cat | P63: No Tax Invoice | Q63: =IF(B63=B62,Q62+1,1) -> 58
E64: =IFERROR(VLOOKUP(D64,ProductMaster!$A:$B,2,FALSE),"") | F64: =IFERROR(VLOOKUP(D64,ProductMaster!$A:$C,3,FALSE),"") | G64: =IFERROR(VLOOKUP($D64,ProductMaster!$A:$O,4,FALSE),"") | I64: =IFERROR(VLOOKUP(E64,ProductMaster!B:G,6,FALSE),0) -> 0 | J64: =ROUND(SUM(I64*7%),2) -> 0 | K64: =ROUND(SUM(H64*I64),2) -> 0 | M64: Transfer | N64: Cat | O64: 0 | P64: No Tax Invoice | Q64: =IF(B64=B63,Q63+1,1) -> 59
E65: =IFERROR(VLOOKUP(D65,ProductMaster!$A:$B,2,FALSE),"") | F65: =IFERROR(VLOOKUP(D65,ProductMaster!$A:$C,3,FALSE),"") | G65: =IFERROR(VLOOKUP($D65,ProductMaster!$A:$O,4,FALSE),"") | I65: =IFERROR(VLOOKUP(E65,ProductMaster!B:G,6,FALSE),0) -> 0 | J65: =ROUND(SUM(I65*7%),2) -> 0 | K65: =ROUND(SUM(H65*I65),2) -> 0 | M65: Transfer | N65: Cat | O65: 0 | P65: No Tax Invoice | Q65: =IF(B65=B64,Q64+1,1) -> 60
E66: =IFERROR(VLOOKUP(D66,ProductMaster!$A:$B,2,FALSE),"") | F66: =IFERROR(VLOOKUP(D66,ProductMaster!$A:$C,3,FALSE),"") | G66: =IFERROR(VLOOKUP($D66,ProductMaster!$A:$O,4,FALSE),"") | I66: =IFERROR(VLOOKUP(E66,ProductMaster!B:G,6,FALSE),0) -> 0 | J66: =ROUND(SUM(I66*7%),2) -> 0 | K66: =ROUND(SUM(H66*I66),2) -> 0 | M66: Transfer | N66: Cat | O66: 0 | P66: No Tax Invoice | Q66: =IF(B66=B65,Q65+1,1) -> 61
E67: =IFERROR(VLOOKUP(D67,ProductMaster!$A:$B,2,FALSE),"") | F67: =IFERROR(VLOOKUP(D67,ProductMaster!$A:$C,3,FALSE),"") | G67: =IFERROR(VLOOKUP($D67,ProductMaster!$A:$O,4,FALSE),"") | I67: =IFERROR(VLOOKUP(E67,ProductMaster!B:G,6,FALSE),0) -> 0 | J67: =ROUND(SUM(I67*7%),2) -> 0 | K67: =ROUND(SUM(H67*I67),2) -> 0 | M67: Transfer | N67: Cat | O67: 0 | P67: No Tax Invoice | Q67: =IF(B67=B66,Q66+1,1) -> 62
E68: =IFERROR(VLOOKUP(D68,ProductMaster!$A:$B,2,FALSE),"") | F68: =IFERROR(VLOOKUP(D68,ProductMaster!$A:$C,3,FALSE),"") | G68: =IFERROR(VLOOKUP($D68,ProductMaster!$A:$O,4,FALSE),"") | I68: =IFERROR(VLOOKUP(E68,ProductMaster!B:G,6,FALSE),0) -> 0 | J68: =ROUND(SUM(I68*7%),2) -> 0 | K68: =ROUND(SUM(H68*I68),2) -> 0 | M68: Transfer | N68: Cat | O68: 0 | P68: No Tax Invoice | Q68: =IF(B68=B67,Q67+1,1) -> 63
E69: =IFERROR(VLOOKUP(D69,ProductMaster!$A:$B,2,FALSE),"") | F69: =IFERROR(VLOOKUP(D69,ProductMaster!$A:$C,3,FALSE),"") | G69: =IFERROR(VLOOKUP($D69,ProductMaster!$A:$O,4,FALSE),"") | I69: =IFERROR(VLOOKUP(E69,ProductMaster!B:G,6,FALSE),0) -> 0 | J69: =ROUND(SUM(I69*7%),2) -> 0 | K69: =ROUND(SUM(H69*I69),2) -> 0 | M69: Transfer | N69: Cat | O69: 0 | P69: No Tax Invoice | Q69: =IF(B69=B68,Q68+1,1) -> 64
E70: =IFERROR(VLOOKUP(D70,ProductMaster!$A:$B,2,FALSE),"") | F70: =IFERROR(VLOOKUP(D70,ProductMaster!$A:$C,3,FALSE),"") | G70: =IFERROR(VLOOKUP($D70,ProductMaster!$A:$O,4,FALSE),"") | I70: =IFERROR(VLOOKUP(E70,ProductMaster!B:G,6,FALSE),0) -> 0 | J70: =ROUND(SUM(I70*7%),2) -> 0 | K70: =ROUND(SUM(H70*I70),2) -> 0 | M70: Transfer | N70: Cat | O70: 0 | P70: No Tax Invoice | Q70: =IF(B70=B69,Q69+1,1) -> 65
E71: =IFERROR(VLOOKUP(D71,ProductMaster!$A:$B,2,FALSE),"") | F71: =IFERROR(VLOOKUP(D71,ProductMaster!$A:$C,3,FALSE),"") | G71: =IFERROR(VLOOKUP($D71,ProductMaster!$A:$O,4,FALSE),"") | I71: =IFERROR(VLOOKUP(E71,ProductMaster!B:G,6,FALSE),0) -> 0 | J71: =ROUND(SUM(I71*7%),2) -> 0 | K71: =ROUND(SUM(H71*I71),2) -> 0 | M71: Transfer | N71: Cat | O71: 0 | P71: No Tax Invoice | Q71: =IF(B71=B70,Q70+1,1) -> 66
E72: =IFERROR(VLOOKUP(D72,ProductMaster!$A:$B,2,FALSE),"") | F72: =IFERROR(VLOOKUP(D72,ProductMaster!$A:$C,3,FALSE),"") | G72: =IFERROR(VLOOKUP($D72,ProductMaster!$A:$O,4,FALSE),"") | I72: =IFERROR(VLOOKUP(E72,ProductMaster!B:G,6,FALSE),0) -> 0 | J72: =ROUND(SUM(I72*7%),2) -> 0 | K72: =ROUND(SUM(H72*I72),2) -> 0 | M72: Transfer | N72: Cat | O72: 0 | P72: No Tax Invoice | Q72: =IF(B72=B71,Q71+1,1) -> 67
E73: =IFERROR(VLOOKUP(D73,ProductMaster!$A:$B,2,FALSE),"") | F73: =IFERROR(VLOOKUP(D73,ProductMaster!$A:$C,3,FALSE),"") | G73: =IFERROR(VLOOKUP($D73,ProductMaster!$A:$O,4,FALSE),"") | I73: =IFERROR(VLOOKUP(E73,ProductMaster!B:G,6,FALSE),0) -> 0 | J73: =ROUND(SUM(I73*7%),2) -> 0 | K73: =ROUND(SUM(H73*I73),2) -> 0 | M73: Transfer | N73: Cat | O73: 0 | P73: No Tax Invoice | Q73: =IF(B73=B72,Q72+1,1) -> 68
E74: =IFERROR(VLOOKUP(D74,ProductMaster!$A:$B,2,FALSE),"") | F74: =IFERROR(VLOOKUP(D74,ProductMaster!$A:$C,3,FALSE),"") | G74: =IFERROR(VLOOKUP($D74,ProductMaster!$A:$O,4,FALSE),"") | I74: =IFERROR(VLOOKUP(E74,ProductMaster!B:G,6,FALSE),0) -> 0 | J74: =ROUND(SUM(I74*7%),2) -> 0 | K74: =ROUND(SUM(H74*I74),2) -> 0 | M74: Transfer | N74: Cat | O74: 0 | P74: No Tax Invoice | Q74: =IF(B74=B73,Q73+1,1) -> 69
E75: =IFERROR(VLOOKUP(D75,ProductMaster!$A:$B,2,FALSE),"") | F75: =IFERROR(VLOOKUP(D75,ProductMaster!$A:$C,3,FALSE),"") | G75: =IFERROR(VLOOKUP($D75,ProductMaster!$A:$O,4,FALSE),"") | I75: =IFERROR(VLOOKUP(E75,ProductMaster!B:G,6,FALSE),0) -> 0 | J75: =ROUND(SUM(I75*7%),2) -> 0 | K75: =ROUND(SUM(H75*I75),2) -> 0 | M75: Transfer | N75: Cat | O75: 0 | P75: No Tax Invoice | Q75: =IF(B75=B74,Q74+1,1) -> 70
... E116: =IFERROR(VLOOKUP(D116,ProductMaster!$A:$B,2,FALSE),"") | F116: =IFERROR(VLOOKUP(D116,ProductMaster!$A:$C,3,FALSE),"") | G116: =IFERROR(VLOOKUP($D116,ProductMaster!$A:$O,4,FALSE),"") | I116: =IFERROR(VLOOKUP(E116,ProductMaster!B:G,6,FALSE),0) -> 0 | J116: =ROUND(SUM(I116*7%),2) -> 0 | K116: =ROUND(SUM(H116*I116),2) -> 0 | M116: Transfer | N116: Cat | O116: 0 | P116: No Tax Invoice | Q116: =IF(B116=B115,Q115+1,1) -> 111
E117: =IFERROR(VLOOKUP(D117,ProductMaster!$A:$B,2,FALSE),"") | F117: =IFERROR(VLOOKUP(D117,ProductMaster!$A:$C,3,FALSE),"") | G117: =IFERROR(VLOOKUP($D117,ProductMaster!$A:$O,4,FALSE),"") | I117: =IFERROR(VLOOKUP(E117,ProductMaster!B:G,6,FALSE),0) -> 0 | J117: =ROUND(SUM(I117*7%),2) -> 0 | K117: =ROUND(SUM(H117*I117),2) -> 0 | M117: Transfer | N117: Cat | P117: No Tax Invoice | Q117: =IF(B117=B116,Q116+1,1) -> 112
E118: =IFERROR(VLOOKUP(D118,ProductMaster!$A:$B,2,FALSE),"") | F118: =IFERROR(VLOOKUP(D118,ProductMaster!$A:$C,3,FALSE),"") | G118: =IFERROR(VLOOKUP($D118,ProductMaster!$A:$O,4,FALSE),"") | I118: =IFERROR(VLOOKUP(E118,ProductMaster!B:G,6,FALSE),0) -> 0 | J118: =ROUND(SUM(I118*7%),2) -> 0 | K118: =ROUND(SUM(H118*I118),2) -> 0 | M118: Transfer | N118: Cat | P118: No Tax Invoice | Q118: =IF(B118=B117,Q117+1,1) -> 113
E119: =IFERROR(VLOOKUP(D119,ProductMaster!$A:$B,2,FALSE),"") | F119: =IFERROR(VLOOKUP(D119,ProductMaster!$A:$C,3,FALSE),"") | G119: =IFERROR(VLOOKUP($D119,ProductMaster!$A:$O,4,FALSE),"") | I119: =IFERROR(VLOOKUP(E119,ProductMaster!B:G,6,FALSE),0) -> 0 | J119: =ROUND(SUM(I119*7%),2) -> 0 | K119: =ROUND(SUM(H119*I119),2) -> 0 | M119: Transfer | N119: Cat | P119: No Tax Invoice | Q119: =IF(B119=B118,Q118+1,1) -> 114
E120: =IFERROR(VLOOKUP(D120,ProductMaster!$A:$B,2,FALSE),"") | F120: =IFERROR(VLOOKUP(D120,ProductMaster!$A:$C,3,FALSE),"") | G120: =IFERROR(VLOOKUP($D120,ProductMaster!$A:$O,4,FALSE),"") | I120: =IFERROR(VLOOKUP(E120,ProductMaster!B:G,6,FALSE),0) -> 0 | J120: =ROUND(SUM(I120*7%),2) -> 0 | K120: =ROUND(SUM(H120*I120),2) -> 0 | M120: Transfer | N120: Cat | P120: No Tax Invoice | Q120: =IF(B120=B119,Q119+1,1) -> 115
E121: =IFERROR(VLOOKUP(D121,ProductMaster!$A:$B,2,FALSE),"") | F121: =IFERROR(VLOOKUP(D121,ProductMaster!$A:$C,3,FALSE),"") | G121: =IFERROR(VLOOKUP($D121,ProductMaster!$A:$O,4,FALSE),"") | I121: =IFERROR(VLOOKUP(E121,ProductMaster!B:G,6,FALSE),0) -> 0 | J121: =ROUND(SUM(I121*7%),2) -> 0 | K121: =ROUND(SUM(H121*I121),2) -> 0 | M121: Transfer | N121: Cat | P121: No Tax Invoice | Q121: =IF(B121=B120,Q120+1,1) -> 116
E122: =IFERROR(VLOOKUP(D122,ProductMaster!$A:$B,2,FALSE),"") | F122: =IFERROR(VLOOKUP(D122,ProductMaster!$A:$C,3,FALSE),"") | G122: =IFERROR(VLOOKUP($D122,ProductMaster!$A:$O,4,FALSE),"") | I122: =IFERROR(VLOOKUP(E122,ProductMaster!B:G,6,FALSE),0) -> 0 | J122: =ROUND(SUM(I122*7%),2) -> 0 | K122: =ROUND(SUM(H122*I122),2) -> 0 | M122: Transfer | N122: Cat | P122: No Tax Invoice | Q122: =IF(B122=B121,Q121+1,1) -> 117
E123: =IFERROR(VLOOKUP(D123,ProductMaster!$A:$B,2,FALSE),"") | F123: =IFERROR(VLOOKUP(D123,ProductMaster!$A:$C,3,FALSE),"") | G123: =IFERROR(VLOOKUP($D123,ProductMaster!$A:$O,4,FALSE),"") | I123: =IFERROR(VLOOKUP(E123,ProductMaster!B:G,6,FALSE),0) -> 0 | J123: =ROUND(SUM(I123*7%),2) -> 0 | K123: =ROUND(SUM(H123*I123),2) -> 0 | M123: Transfer | N123: Cat | O123: 0 | P123: No Tax Invoice | Q123: =IF(B123=B122,Q122+1,1) -> 118
E124: =IFERROR(VLOOKUP(D124,ProductMaster!$A:$B,2,FALSE),"") | F124: =IFERROR(VLOOKUP(D124,ProductMaster!$A:$C,3,FALSE),"") | G124: =IFERROR(VLOOKUP($D124,ProductMaster!$A:$O,4,FALSE),"") | I124: =IFERROR(VLOOKUP(E124,ProductMaster!B:G,6,FALSE),0) -> 0 | J124: =ROUND(SUM(I124*7%),2) -> 0 | K124: =ROUND(SUM(H124*I124),2) -> 0 | M124: Transfer | N124: Cat | O124: 0 | P124: No Tax Invoice | Q124: =IF(B124=B123,Q123+1,1) -> 119
E125: =IFERROR(VLOOKUP(D125,ProductMaster!$A:$B,2,FALSE),"") | F125: =IFERROR(VLOOKUP(D125,ProductMaster!$A:$C,3,FALSE),"") | G125: =IFERROR(VLOOKUP($D125,ProductMaster!$A:$O,4,FALSE),"") | I125: =IFERROR(VLOOKUP(E125,ProductMaster!B:G,6,FALSE),0) -> 0 | J125: =ROUND(SUM(I125*7%),2) -> 0 | K125: =ROUND(SUM(H125*I125),2) -> 0 | M125: Transfer | N125: Cat | O125: 0 | P125: No Tax Invoice | Q125: =IF(B125=B124,Q124+1,1) -> 120
E126: =IFERROR(VLOOKUP(D126,ProductMaster!$A:$B,2,FALSE),"") | F126: =IFERROR(VLOOKUP(D126,ProductMaster!$A:$C,3,FALSE),"") | G126: =IFERROR(VLOOKUP($D126,ProductMaster!$A:$O,4,FALSE),"") | I126: =IFERROR(VLOOKUP(E126,ProductMaster!B:G,6,FALSE),0) -> 0 | J126: =ROUND(SUM(I126*7%),2) -> 0 | K126: =ROUND(SUM(H126*I126),2) -> 0 | M126: Transfer | N126: Cat | O126: 0 | P126: No Tax Invoice | Q126: =IF(B126=B125,Q125+1,1) -> 121
E127: =IFERROR(VLOOKUP(D127,ProductMaster!$A:$B,2,FALSE),"") | F127: =IFERROR(VLOOKUP(D127,ProductMaster!$A:$C,3,FALSE),"") | G127: =IFERROR(VLOOKUP($D127,ProductMaster!$A:$O,4,FALSE),"") | I127: =IFERROR(VLOOKUP(E127,ProductMaster!B:G,6,FALSE),0) -> 0 | J127: =ROUND(SUM(I127*7%),2) -> 0 | K127: =ROUND(SUM(H127*I127),2) -> 0 | M127: Transfer | N127: Cat | O127: 0 | P127: No Tax Invoice | Q127: =IF(B127=B126,Q126+1,1) -> 122
E128: =IFERROR(VLOOKUP(D128,ProductMaster!$A:$B,2,FALSE),"") | F128: =IFERROR(VLOOKUP(D128,ProductMaster!$A:$C,3,FALSE),"") | G128: =IFERROR(VLOOKUP($D128,ProductMaster!$A:$O,4,FALSE),"") | I128: =IFERROR(VLOOKUP(E128,ProductMaster!B:G,6,FALSE),0) -> 0 | J128: =ROUND(SUM(I128*7%),2) -> 0 | K128: =ROUND(SUM(H128*I128),2) -> 0 | M128: Transfer | N128: Cat | O128: 0 | P128: No Tax Invoice | Q128: =IF(B128=B127,Q127+1,1) -> 123
E129: =IFERROR(VLOOKUP(D129,ProductMaster!$A:$B,2,FALSE),"") | F129: =IFERROR(VLOOKUP(D129,ProductMaster!$A:$C,3,FALSE),"") | G129: =IFERROR(VLOOKUP($D129,ProductMaster!$A:$O,4,FALSE),"") | I129: =IFERROR(VLOOKUP(E129,ProductMaster!B:G,6,FALSE),0) -> 0 | J129: =ROUND(SUM(I129*7%),2) -> 0 | K129: =ROUND(SUM(H129*I129),2) -> 0 | M129: Transfer | N129: Cat | O129: 0 | P129: No Tax Invoice | Q129: =IF(B129=B128,Q128+1,1) -> 124
E130: =IFERROR(VLOOKUP(D130,ProductMaster!$A:$B,2,FALSE),"") | F130: =IFERROR(VLOOKUP(D130,ProductMaster!$A:$C,3,FALSE),"") | G130: =IFERROR(VLOOKUP($D130,ProductMaster!$A:$O,4,FALSE),"") | I130: =IFERROR(VLOOKUP(E130,ProductMaster!B:G,6,FALSE),0) -> 0 | J130: =ROUND(SUM(I130*7%),2) -> 0 | K130: =ROUND(SUM(H130*I130),2) -> 0 | M130: Transfer | N130: Cat | O130: 0 | P130: No Tax Invoice | Q130: =IF(B130=B129,Q129+1,1) -> 125
E131: =IFERROR(VLOOKUP(D131,ProductMaster!$A:$B,2,FALSE),"") | F131: =IFERROR(VLOOKUP(D131,ProductMaster!$A:$C,3,FALSE),"") | G131: =IFERROR(VLOOKUP($D131,ProductMaster!$A:$O,4,FALSE),"") | I131: =IFERROR(VLOOKUP(E131,ProductMaster!B:G,6,FALSE),0) -> 0 | J131: =ROUND(SUM(I131*7%),2) -> 0 | K131: =ROUND(SUM(H131*I131),2) -> 0 | M131: Transfer | N131: Cat | O131: 0 | P131: No Tax Invoice | Q131: =IF(B131=B130,Q130+1,1) -> 126
E132: =IFERROR(VLOOKUP(D132,ProductMaster!$A:$B,2,FALSE),"") | F132: =IFERROR(VLOOKUP(D132,ProductMaster!$A:$C,3,FALSE),"") | G132: =IFERROR(VLOOKUP($D132,ProductMaster!$A:$O,4,FALSE),"") | I132: =IFERROR(VLOOKUP(E132,ProductMaster!B:G,6,FALSE),0) -> 0 | J132: =ROUND(SUM(I132*7%),2) -> 0 | K132: =ROUND(SUM(H132*I132),2) -> 0 | M132: Transfer | N132: Cat | O132: 0 | P132: No Tax Invoice | Q132: =IF(B132=B131,Q131+1,1) -> 127
E133: =IFERROR(VLOOKUP(D133,ProductMaster!$A:$B,2,FALSE),"") | F133: =IFERROR(VLOOKUP(D133,ProductMaster!$A:$C,3,FALSE),"") | G133: =IFERROR(VLOOKUP($D133,ProductMaster!$A:$O,4,FALSE),"") | I133: =IFERROR(VLOOKUP(E133,ProductMaster!B:G,6,FALSE),0) -> 0 | J133: =ROUND(SUM(I133*7%),2) -> 0 | K133: =ROUND(SUM(H133*I133),2) -> 0 | M133: Transfer | N133: Cat | O133: 0 | P133: No Tax Invoice | Q133: =IF(B133=B132,Q132+1,1) -> 128
E134: =IFERROR(VLOOKUP(D134,ProductMaster!$A:$B,2,FALSE),"") | F134: =IFERROR(VLOOKUP(D134,ProductMaster!$A:$C,3,FALSE),"") | G134: =IFERROR(VLOOKUP($D134,ProductMaster!$A:$O,4,FALSE),"") | I134: =IFERROR(VLOOKUP(E134,ProductMaster!B:G,6,FALSE),0) -> 0 | J134: =ROUND(SUM(I134*7%),2) -> 0 | K134: =ROUND(SUM(H134*I134),2) -> 0 | M134: Transfer | N134: Cat | O134: 0 | P134: No Tax Invoice | Q134: =IF(B134=B133,Q133+1,1) -> 129
... E154: =IFERROR(VLOOKUP(D154,ProductMaster!$A:$B,2,FALSE),"") | F154: =IFERROR(VLOOKUP(D154,ProductMaster!$A:$C,3,FALSE),"") | G154: =IFERROR(VLOOKUP($D154,ProductMaster!$A:$O,4,FALSE),"") | I154: =IFERROR(VLOOKUP(E154,ProductMaster!B:G,6,FALSE),0) -> 0 | J154: =ROUND(SUM(I154*7%),2) -> 0 | K154: =ROUND(SUM(H154*I154),2) -> 0 | M154: Transfer | N154: Cat | O154: 0 | P154: No Tax Invoice | Q154: =IF(B154=B153,Q153+1,1) -> 149
E155: =IFERROR(VLOOKUP(D155,ProductMaster!$A:$B,2,FALSE),"") | F155: =IFERROR(VLOOKUP(D155,ProductMaster!$A:$C,3,FALSE),"") | G155: =IFERROR(VLOOKUP($D155,ProductMaster!$A:$O,4,FALSE),"") | I155: =IFERROR(VLOOKUP(E155,ProductMaster!B:G,6,FALSE),0) -> 0 | J155: =ROUND(SUM(I155*7%),2) -> 0 | K155: =ROUND(SUM(H155*I155),2) -> 0 | O155: 0 | Q155: =IF(B155=B154,Q154+1,1) -> 150
E156: =IFERROR(VLOOKUP(D156,ProductMaster!$A:$B,2,FALSE),"") | F156: =IFERROR(VLOOKUP(D156,ProductMaster!$A:$C,3,FALSE),"") | G156: =IFERROR(VLOOKUP($D156,ProductMaster!$A:$O,4,FALSE),"") | I156: =IFERROR(VLOOKUP(E156,ProductMaster!B:G,6,FALSE),0) -> 0 | J156: =ROUND(SUM(I156*7%),2) -> 0 | K156: =ROUND(SUM(H156*I156),2) -> 0 | O156: 0 | Q156: =IF(B156=B155,Q155+1,1) -> 151
E157: =IFERROR(VLOOKUP(D157,ProductMaster!$A:$B,2,FALSE),"") | F157: =IFERROR(VLOOKUP(D157,ProductMaster!$A:$C,3,FALSE),"") | G157: =IFERROR(VLOOKUP($D157,ProductMaster!$A:$O,4,FALSE),"") | I157: =IFERROR(VLOOKUP(E157,ProductMaster!B:G,6,FALSE),0) -> 0 | J157: =ROUND(SUM(I157*7%),2) -> 0 | K157: =ROUND(SUM(H157*I157),2) -> 0 | O157: 0 | Q157: =IF(B157=B156,Q156+1,1) -> 152
E158: =IFERROR(VLOOKUP(D158,ProductMaster!$A:$B,2,FALSE),"") | F158: =IFERROR(VLOOKUP(D158,ProductMaster!$A:$C,3,FALSE),"") | G158: =IFERROR(VLOOKUP($D158,ProductMaster!$A:$O,4,FALSE),"") | I158: =IFERROR(VLOOKUP(E158,ProductMaster!B:G,6,FALSE),0) -> 0 | J158: =ROUND(SUM(I158*7%),2) -> 0 | K158: =ROUND(SUM(H158*I158),2) -> 0 | O158: 0 | Q158: =IF(B158=B157,Q157+1,1) -> 153
E159: =IFERROR(VLOOKUP(D159,ProductMaster!$A:$B,2,FALSE),"") | F159: =IFERROR(VLOOKUP(D159,ProductMaster!$A:$C,3,FALSE),"") | G159: =IFERROR(VLOOKUP($D159,ProductMaster!$A:$O,4,FALSE),"") | I159: =IFERROR(VLOOKUP(E159,ProductMaster!B:G,6,FALSE),0) -> 0 | J159: =ROUND(SUM(I159*7%),2) -> 0 | K159: =ROUND(SUM(H159*I159),2) -> 0 | O159: 0 | Q159: =IF(B159=B158,Q158+1,1) -> 154
E160: =IFERROR(VLOOKUP(D160,ProductMaster!$A:$B,2,FALSE),"") | F160: =IFERROR(VLOOKUP(D160,ProductMaster!$A:$C,3,FALSE),"") | G160: =IFERROR(VLOOKUP($D160,ProductMaster!$A:$O,4,FALSE),"") | I160: =IFERROR(VLOOKUP(E160,ProductMaster!B:G,6,FALSE),0) -> 0 | J160: =ROUND(SUM(I160*7%),2) -> 0 | K160: =ROUND(SUM(H160*I160),2) -> 0 | O160: 0 | Q160: =IF(B160=B159,Q159+1,1) -> 155
E161: =IFERROR(VLOOKUP(D161,ProductMaster!$A:$B,2,FALSE),"") | F161: =IFERROR(VLOOKUP(D161,ProductMaster!$A:$C,3,FALSE),"") | G161: =IFERROR(VLOOKUP($D161,ProductMaster!$A:$O,4,FALSE),"") | I161: =IFERROR(VLOOKUP(E161,ProductMaster!B:G,6,FALSE),0) -> 0 | J161: =ROUND(SUM(I161*7%),2) -> 0 | K161: =ROUND(SUM(H161*I161),2) -> 0 | O161: 0 | Q161: =IF(B161=B160,Q160+1,1) -> 156
E162: =IFERROR(VLOOKUP(D162,ProductMaster!$A:$B,2,FALSE),"") | F162: =IFERROR(VLOOKUP(D162,ProductMaster!$A:$C,3,FALSE),"") | G162: =IFERROR(VLOOKUP($D162,ProductMaster!$A:$O,4,FALSE),"") | I162: =IFERROR(VLOOKUP(E162,ProductMaster!B:G,6,FALSE),0) -> 0 | J162: =ROUND(SUM(I162*7%),2) -> 0 | K162: =ROUND(SUM(H162*I162),2) -> 0 | O162: 0 | Q162: =IF(B162=B161,Q161+1,1) -> 157
E163: =IFERROR(VLOOKUP(D163,ProductMaster!$A:$B,2,FALSE),"") | F163: =IFERROR(VLOOKUP(D163,ProductMaster!$A:$C,3,FALSE),"") | G163: =IFERROR(VLOOKUP($D163,ProductMaster!$A:$O,4,FALSE),"") | I163: =IFERROR(VLOOKUP(E163,ProductMaster!B:G,6,FALSE),0) -> 0 | J163: =ROUND(SUM(I163*7%),2) -> 0 | K163: =ROUND(SUM(H163*I163),2) -> 0 | O163: 0 | Q163: =IF(B163=B162,Q162+1,1) -> 158
E164: =IFERROR(VLOOKUP(D164,ProductMaster!$A:$B,2,FALSE),"") | F164: =IFERROR(VLOOKUP(D164,ProductMaster!$A:$C,3,FALSE),"") | G164: =IFERROR(VLOOKUP($D164,ProductMaster!$A:$O,4,FALSE),"") | I164: =IFERROR(VLOOKUP(E164,ProductMaster!B:G,6,FALSE),0) -> 0 | J164: =ROUND(SUM(I164*7%),2) -> 0 | K164: =ROUND(SUM(H164*I164),2) -> 0 | O164: 0 | Q164: =IF(B164=B163,Q163+1,1) -> 159
E165: =IFERROR(VLOOKUP(D165,ProductMaster!$A:$B,2,FALSE),"") | F165: =IFERROR(VLOOKUP(D165,ProductMaster!$A:$C,3,FALSE),"") | G165: =IFERROR(VLOOKUP($D165,ProductMaster!$A:$O,4,FALSE),"") | I165: =IFERROR(VLOOKUP(E165,ProductMaster!B:G,6,FALSE),0) -> 0 | J165: =ROUND(SUM(I165*7%),2) -> 0 | K165: =ROUND(SUM(H165*I165),2) -> 0 | O165: 0 | Q165: =IF(B165=B164,Q164+1,1) -> 160
E166: =IFERROR(VLOOKUP(D166,ProductMaster!$A:$B,2,FALSE),"") | F166: =IFERROR(VLOOKUP(D166,ProductMaster!$A:$C,3,FALSE),"") | G166: =IFERROR(VLOOKUP($D166,ProductMaster!$A:$O,4,FALSE),"") | I166: =IFERROR(VLOOKUP(E166,ProductMaster!B:G,6,FALSE),0) -> 0 | J166: =ROUND(SUM(I166*7%),2) -> 0 | K166: =ROUND(SUM(H166*I166),2) -> 0 | O166: 0 | Q166: =IF(B166=B165,Q165+1,1) -> 161
... E500: =IFERROR(VLOOKUP(D500,ProductMaster!$A:$B,2,FALSE),"") | F500: =IFERROR(VLOOKUP(D500,ProductMaster!$A:$C,3,FALSE),"") | G500: =IFERROR(VLOOKUP($D500,ProductMaster!$A:$O,4,FALSE),"") | I500: =IFERROR(VLOOKUP(E500,ProductMaster!B:G,6,FALSE),0) -> 0 | J500: =ROUND(SUM(I500*7%),2) -> 0 | K500: =ROUND(SUM(H500*I500),2) -> 0 | O500: 0 | Q500: =IF(B500=B499,Q499+1,1) -> 495

Sheet Cus
A1: Code | B1: Name | C1: Address (1) | D1: Address (2) | E1: Tax ID | F1: Tel.
A2: Onetime | B2: Cash | C2: Cash | D2: - | E2: - | F2: -
A3: A001 | B3: คุณ อุทิศ บุญวัฒน์ | C3: - | E3: - | F3: -
A4: A002 | B4: คุณ สุพจน์ จัดวานิล | C4: - | E4: - | F4: 819051415
A5: A003 | B5: คุณ สัมฤทธิ์ เรืองศรี | C5: - | E5: - | F5: 879977568
A6: A004 | B6: บริษัท กรุงเทพแคนวาส จำกัด | C6: 1317 ซอยจรัญสนิทวงศ์ 13 ถนนจรัญสนิทวงศ์ แขวงวัดท่าพระ เขตบางกอกใหญ่ กรุงเทพฯ 10600 | E6: 105535053715 | F6: 28640521
A7: A005 | B7: บริษัท เค.เยนเนอรัล อีควิปเม้นท์ จำกัด สำนักงานใหญ่ | C7: 107/24-25 ถนนประชาราษฎร์ สาย 1 แขวงบางซื่อ เขตบางซื่อ กรุงเทพฯ 10800 | E7: 105559117802 | F7: 25871249
A8: A006 | B8: คุณ กุลธัช บุญบางการ | C8: 169 ซอยสบายใจ ถนนสุทธิสาร เขตห้วยขวาง แขวงสามเสนนอก กรุงเทพฯ 10310 | D8: 169 ซอยสบายใจ ถนนสุทธิสาร เขตห้วยขวาง แขวงสามเสนนอก กรุงเทพฯ 10310 | E8: - | F8: 816329099
A9: A007 | B9: คุณ กิตติพันธ์ กรรณิกาธนานนท์ | C9: - | E9: - | F9: 818203086
A10: A008 | B10: บริษัท อุตสาหกรรมแป้งเหรียญทอง จำกัด | C10: 42/7 หมู่ 1 ซอยวัดอ้อมใหญ่ ถ.เพชรเกษม ต.อ้อมใหญ่ อ.สามพราน จ.นครปฐม 73160 | E10: 735545002298 | F10: 24202432
A11: A009 | B11: คุณ อัครเดช | C11: - | D11: - | E11: - | F11: 854885769
A12: A010 | B12: คุณ อโนชา | C12: - | D12: - | E12: - | F12: 892419952
A13: A011 | B13: บริษัท ฟาโรห์ เอ็นจิเนียริ่ง จำกัด (สำนักงานใหญ่) | C13: 106/146 หมู่ที่ 4 ต.หนองหอย อ.เมืองเชียงใหม่ จ.เชียงใหม่ 50000 | D13: พรณ์ปวีฐ์ นรีรัตน์ เลขที่ 91/108 หมู่บ้านอารียาเดอะคัลเลอร์เฟส 4 หมู่ 2 ต.บ้านใหม่ อ.ปากเกร็ด จ.นนทบุรี 11120 โทร.0947181619 | E13: 655564002037 | F13: 833314309
A14: A012 | B14: คุณ ชณันภัสร์ | C14: - | D14: - | E14: - | F14: 636670556
A15: A013 | B15: คุณ แบงค์ | C15: - | D15: - | E15: - | F15: 959099974
A16: A014 | B16: คุณ อมร | C16: - | D16: - | E16: - | F16: 890433537
A17: A015 | B17: คุณ เกน | C17: - | D17: - | E17: - | F17: 984891515
A18: A016 | B18: นาย สุชาติ ห้วยนอก | C18: 32 ซ.เฉลิมพระเกียรติ ร.๙ ซอย 30 แยก 14-4 แขวงดอกไม้ เขตประเวศ กรุงเทพมหานคร 10250 | E18: 1100700616737 | F18: 870925700
A19: A017 | B19: คุณ ป๋อม | C19: - | D19: - | E19: - | F19: 814444651
A20: A018 | B20: คุณ ศุภโชค | C20: - | D20: - | E20: - | F20: 818303794
A21: A019 | B21: คุณ พงษ์ถวัช | C21: - | D21: - | E21: - | F21: 820414218
A22: A020 | B22: คุณ ถนัด | C22: 101/397 หมู่บ้านปรีชา (สาย 4) ซอย 8 ถนนพุทธมณฑล สาย 4, กระทุ่มส้ม, อ. สามพราน, จ.นครปฐม 73220 | D22: - | E22: - | F22: 851434598
A23: A021 | B23: คุณ ธนะกฤษฏิ์ เกียรติไกรเมส | C23: 19/528 ซ.นวมินทร์ 26 แยก 1 คลองกุ่ม บึงกุ่ม กทม. 10240 | D23: - | E23: - | F23: 950909969
A24: A022 | B24: คุณ ณัฐวรี | C24: - | D24: - | E24: - | F24: 905645554
A25: A023 | B25: คุณ ธวัชชัย | C25: - | D25: - | F25: 902873599
A26: A024 | B26: คุณ ศิริชัย | C26: - | D26: - | E26: - | F26: 815321017
A27: A025 | B27: คุณ ณัฐชนน พัฒนโก | C27: - | D27: - | E27: - | F27: 646396535
A28: A026 | B28: คุณ คัจฉพงษ์ เศรษฐบรมศักดิ์ | C28: - | D28: - | E28: - | F28: 814712558
A29: A027 | B29: คุณ คาวี ฆารชัย | C29: - | D29: - | E29: - | F29: 857982464
A30: A028 | B30: คุณ จริยา | C30: - | D30: - | E30: - | F30: 819040910
A31: A029 | B31: บริษัท แอบโซลูท 65 | C31: 713/4 ซอย สุขุมวิท 101 แขวงบางจาก เขตพระโขนง กรุงเทพมหานคร 10260 | D31: คุณ ณัฐนรี พันธ์ทองลาภทวี โทร. 091-795-9952 206/27 อาคารชุดพักอาศัย ชั้น 3 ถ.สุขุมวิท 64 แขวงพระโขนง เขตพระโขนง กรุงเทพมหานคร 10260 | E31: 105565066777 | F31: 925656325
A32: A030 | B32: คุณ อธิ | C32: - | D32: - | E32: - | F32: 887528799
A33: A031 | B33: คุณ ขวัญชัย อิ่มแผ่ว | C33: - | D33: - | E33: - | F33: 962454529
A34: A032 | B34: คุณ จิรชยุตม์ | C34: - | D34: - | E34: - | F34: 962454529
A35: A033 | B35: คุณ ศราวุธ | C35: - | D35: - | E35: - | F35: 971075730
A36: A034 | B36: บริษัท ซีพีอาร์ เฟอร์นิเจอร์ ไซน์ จำกัด | C36: 417/214 ซอยพิบูลอุปถัมภ์ แขวงสามเสนนอก เขตห้วยขวาง กรุงเทพมหานคร 10310 | E36: 105547145326 | F36: 944041919
A37: A035 | B37: คุณ ปริญญา | C37: - | D37: - | E37: - | F37: 625905258
A38: A036 | B38: คุณ กิตติพงษ์ | C38: - | D38: - | E38: - | F38: 815295426
A39: A037 | B39: คุณ ปกรณ์ | C39: - | D39: - | E39: - | F39: 801626994
A40: A038 | B40: คุณ สุธรณ์ | C40: - | D40: - | E40: - | F40: 818132536
A41: A039 | B41: คุณ ฤทธิชัย เพชรหนองชุม | C41: - | D41: - | E41: - | F41: 957627727
A42: A040 | B42: บจก. สี่แสงเอเชีย | C42: - | D42: - | E42: 715558001457 | F42: 869149144
A43: A041 | B43: คุณ วุฒิชัย อภินพไพบูลย์ | C43: - | D43: - | E43: - | F43: 848742682
A44: A042 | B44: คุณ เจษสุภา | C44: - | D44: - | E44: - | F44: 823292062
A45: A043 | B45: คุณ วงศ์ปิติ | C45: - | D45: - | E45: - | F45: 985632891
A46: A044 | B46: คุณ ซิน | C46: - | D46: - | E46: - | F46: 654629269
A47: A045 | B47: คุณ ดาราภรณ์ ทัพโพธิ์ | C47: บริษัท ฝ้ายการช่าง จำกัด | D47: 1/21 ม.9 ต.ทุ่งสุขลา อ.ศรีราชา จ.ชลบุรี 20230 | E47: 205562014350 | F47: 971589175
A48: A046 | B48: คุณ ชัยวัฒน์ | C48: - | D48: - | E48: - | F48: 924149936
A49: A047 | B49: คุณ นาเดีย | C49: - | D49: - | E49: - | F49: 986861437
A50: A048 | B50: คุณ อาคม ประภัทรมณีย์ | C50: - | D50: - | E50: - | F50: 907993205
A51: A049 | B51: คุณ วิริยะ | C51: - | D51: - | E51: - | F51: 806344081
A52: A050 | B52: คุณ ประวัติ บุษดี | C52: - | D52: - | E52: - | F52: 817309811
A53: A051 | B53: คุณ อนุวัตน์ จีนพั่ว | C53: - | D53: - | E53: - | F53: 929949241
A54: A052 | B54: คุณ สุวิทย์ | C54: - | D54: - | E54: - | F54: 947824546
A55: A053 | B55: บริษัท กวีวัฒน์ ดีไซน์แอนด์คอนสตรัคชั่น จำกัด | C55: 456 ซอยลาดพร้าว 47 ถนนลาดพร้าว แขวงสะพานสอง เขตวังทองหลาง กรุงเทพมหานคร 10310 | E55: 105553040514 | F55: 818109462
A56: A054 | B56: คุณ สมบูรณ์ ขุนทองน้อย | C56: - | D56: - | E56: - | F56: 891059676
A57: A055 | B57: คุณชาลี จิรเสวก | C57: 59/419 ม.ปัญญาเลคโฮม ถนนนิมิตรใหม่ ซอยนิมิตรใหม่28 แขวงคลองสามวาตะวันออก เขตคลองสามวา กรุงเทพฯ 10510 | E57: - | F57: 948795451
A58: A056 | B58: คุณ อริสรา บุญเกลี้ยง | C58: - | D58: - | E58: - | F58: 654699742
A59: A057 | B59: พ.ต. พันรบ ณ ลำปาง | C59: - | D59: - | E59: - | F59: 943945193
A60: A058 | B60: คุณ ประสิทธิ์ | C60: - | D60: - | E60: - | F60: 818426137
A61: A059 | B61: พันจ่าอากาศเอกรังสิกุล แก้วประกอบ | C61: - | D61: - | E61: - | F61: 849616887
A62: A060 | B62: บริษัท เร็กซ์คอน จำกัด | C62: 11/45 ซอยปานเวียง ถนนเลียบทางด่วน แขวงทุ่งครุ เขตทุ่งครุ กรุงเทพมหานคร 10140 | E62: 105544044481 | F62: 880191714
A63: A061 | B63: บริษัท ทรัพย์มงคล 88 จำกัด | C63: 111/30 หมู่ 7 ตำบลบางหลวง อำเภอเมืองปทุมธานี จังหวัดปทุมธานี 12000 | D63: คุณ ปิยะพันธุ์ บ้านเตย 88/136 มบ.เฟื่องสุข3 ม.5 ต.ลำโพ อ.บางบัวทอง จ.นนทบุรี 11110 | E63: 125558001720 | F63: 841965351
A64: A062 | B64: บริษัท วรศักดา จำกัด | C64: 36 หมู่ที่ 4 ตำบลหนองนาก อำเภอหนองแค จังหวัดสระบุรี 18230 | E64: 195563000922 | F64: 894959555
A65: A063 | B65: บริษัท เอ็นพี คอนสตรัคชั่น 2013 จำกัด | C65: 2018 หมู่บ้านสินธร-อ่อนนุช ถนนลาดกระบัง แขวงลาดกระบัง เขตลาดกระบัง กรุงเทพมหานคร 10520 | E65: 105556037221 | F65: 814498970
A66: A064 | B66: คุณ คมกฤษ บุญโนนยาง | C66: - | D66: - | E66: - | F66: 817402265
A67: A065 | B67: คุณ รชต ศรีลานุช | C67: - | D67: - | E67: - | F67: 863566979
A68: A066 | B68: คุณ ญาลินดา เรียนหัตถะกรรม | C68: - | D68: - | E68: - | F68: 855766932
A69: A067 | B69: บริษัท โคราช เลเบิ้ล 2004 จำกัด | C69: 254/1 ซอยมิตรภาพ 4 ตำบลในเมือง อำเภอเมือง จังหวัดนครราชสีมา 30000 | E69: 305547000873 | F69: 832429878
A70: A068 | B70: บริษัท วี.ที.เอส.เอ็นเตอร์ไพร์ส จำกัด | C70: 46 ซอยรังสิต-ปทุมธานี14 ถนนรังสิต-ปทุมธานี ตำบลประชาธิปัตย์ อำเภอธัญบุรี จังหวัดปทุมธานี 12130 | E70: 135535001529 | F70: 816275542
A71: A069 | B71: คุณ อรรถพล ศรีผ่าน | C71: - | D71: - | E71: - | F71: 988855452
A72: A070 | B72: คุณอนุสรณ์ | C72: - | D72: - | E72: - | F72: 923953889
A73: A071 | B73: บริษัท เอสที เบิร์ท พร๊อพเพอร์ตี้ จำกัด | C73: 67/8 ถนนพัฒนาชนบท 3 แขวงคลองสองต้นนุ่น เขตลาดกระบัง กรุงเทพมหานคร 10520 | E73: 105565094584 | F73: 993235366
A74: A072 | B74: คุณพชา | C74: - | D74: - | E74: -
A75: A073 | B75: คุณภาณุมาส ดุลยสิทธิ์ | C75: - | D75: - | E75: - | F75: 840251381
A76: A074 | B76: หจก.ครีเอทีฟพริ้นท์เฮด | C76: 5/14 ซอยสุขาภิบาล5 ซอย5 แยก17 แขวงท่าแร้ง เขตชางเขน กรุงเทพฯ 10220 | E76: 103552014801 | F76: 632151117
A77: A075 | B77: คุณ นุชนาฏ ม่วงปรีดา | C77: - | D77: - | E77: - | F77: 916559251
A78: A076 | B78: บริษัท หนึ่งศูนย์หนึ่ง บิสสิเนสโปรดักส์ จำกัด | C78: 16 ซอยลาดพร้าว 101 (ซอย56) ถนนลาดพร้าว แขวงคลองจั่น เขตบางกะปิ กรุงเทพฯ 10240 | D78: คุณสมใจ เภากัน 94 ซ.โพธิ์แก้ว3 แยก19 แขวงคลองจั่น เขตบางกะปิ กรุงเทพฯ 10240 | E78: 105552002872 | F78: 899203693
A79: A077 | B79: คุณวสันต์ ออมสิน | C79: - | D79: - | E79: - | F79: 815394603
A80: A078 | B80: คุณเกรียงศักดิ์ นาราศรี | C80: - | D80: - | E80: - | F80: 955255416
A81: A079 | B81: หจก. อีควอล เค | C81: 8/81 หมู่บ้านบุราสิริ พระราม2 แขวงแสมดำ เขตบางขุนเทียน กรุงเทพฯ 10150 | E81: 123561002268 | F81: 804466622
A82: A080 | B82: คุณ ศุภวัฒน์ งามพันธุ์ดิศร | C82: - | D82: - | E82: - | F82: 918413875
A83: A081 | B83: บริษัท โกลเด้น ฮอร์ส เอ็นเตอร์ไพรส์ จำกัด | C83: 81 หมู่ที่ 2 ถนนเทศบาล 3 ตำบลเหนือคลอง อำเภอเหนือคลอง จ.กระบี่ 81130 | E83: 815553000443 | F83: 810926222
A84: A081-1 | B84: ที่อยู่ในการส่งของKerry | C84: คุณอรอุมา อยู่เย็น 434/3 ต.กะรน อ.เมือง จ.ภูเก็ต 83100 | F84: 808582266
A85: A082 | B85: คุณ ธนานุวัฒน์ ชื่นประดิษ | C85: - | D85: - | E85: - | F85: 939061623
A86: A083 | B86: บริษัท มอซ ครีเอชั่น (ประเทศไทย) จำกัด | C86: 850/26 ถนนลาดกระบัง แขวงลาดกระบัง เขตลาดกระบัง กรุงเทพมหานคร 10520 | E86: 115549005483 | F86: 827901716
A87: A084 | B87: บริษัท นีโอ ออแกไนเซอร์ จำกัด | C87: 116/23 หมู่ที่ 1 ตำบลช้างเผือก อำเภอเขตเมืองเชียงใหม่ จังหวัดเชียงใหม่ 50300 | E87: 505560003714 | F87: 865630410
A88: A085 | B88: บริษัท ปิ่นทอง อาร์คิเทคท์ แอนด์ คอนสตรัคชั่น จำกัด | C88: 141/235 หมู่ที่ 2 ตำบลต้นเปา อำเภอสันกำแพง จังหวัดเชียงใหม่ 50130 | E88: 505562012672 | F88: 833045062
A89: A086 | B89: คุณพัชรวรรณ ใจปัง | C89: - | D89: - | E89: - | F89: 970839944
A90: A087 | B90: บริษัท ดีทรัสส์ โฮมลิฟต์ จำกัด | C90: 8 ซอยหัวหมาก 9 แยก 3 แขวงหัวหมาก เขตบางกะปิ กรุงเทพมหานคร 10240 | E90: 105560100861
A91: A088 | B91: บริษัท อาร์ทิไซน์ คอมเมอเชี่ยล ดีไซน์ จำกัด | C91: 237/120 ซอยพหลโยธิน 32 แขวงเสนานิคม เขตจตุจักร กรุงเทพมหานคร 10900 | E91: 105562192194 | F91: 958978949
A92: A089 | B92: ห้างหุ้นส่วนจำกัด ศิริไชยวรรณ | C92: 20/2 หมู่ที่ 5 ตำบลบางกะดี อำเภอเมืองปทุมธานี จังหวัดปทุมธานี 12000 | E92: 133542001006 | F92: 804559463
A93: A090 | B93: คุณณัฐดนัย | C93: - | D93: - | E93: - | F93: 958978949
A94: A091 | B94: คุณ ธีรพัฒน์ สู่วงศ์ธรรม | C94: - | D94: - | E94: - | F94: 891490011
A95: A092 | B95: คุณศิลปชัย คล้ายเอม | C95: - | D95: - | E95: - | F95: 081-7421994
A96: A093 | B96: บริษัท สยามแมททีเรียลแอนด์บิสซิเนส จำกัด | C96: 46 ซอยพัฒนาการ20 ถนนพัฒนาการ แขวงสวนหลวง เขตสวนหลวง กรุงเทพฯ 10250 | E96: 105538008532 | F96: 891555819
A97: A094 | B97: บริษัท ไฟน์ วู๊ด จำกัด | C97: 3/318-3/321 อาคารอุตสาหกรรมบี หมู่ 9 ถนนสุวินทวงศ์ แขวงลำผักชี เขตหนองจอก กรุงเทพฯ 10530 | E97: 105554146103 | F97: 088-7888945
A98: A095 | B98: บริษัท พรประเสริฐอาหารสัตว์ จำกัด | C98: 19 หมู่ 4 ตำบลบ้านปรือ อำเภอกระสัง จังหวัดบุรีรัมย์ 31160 | E98: 315547000229 | F98: 618716444
A99: A096 | B99: คุณนนทัช วงศ์พาณิชยกุล | C99: 358 ม.2 ถ.นิตโย ต.สว่างแดนดิน อ.สว่างแดนดิน จ.สกลนคร 47110 | E99: 8439988012855 | F99: 085-6448800
A100: A097 | B100: ณรงค์ศักดิ์ ซัพพลาย | C100: 651/2 หมู่ที่ 4 ตำบลไสไทย อำเภอเมืองกระบี่ จังหวัดกระบี่ 81000 | F100: 084-6697178 | G100: **ส่งKerry ไม่ใช้Tax
...

Sheet Bill
C1: บริษัท มิลวอกี้ ทูล (ประเทศไทย) จํากัด | I1: ต้นฉบับใบเสร็จรับเงิน
C2: Milwaukee Tool (Thailand) Company Limited | I2: Original Receipt
A3: 65/116-117 ชั้น 14 อาคารชำนาญเพ็ญชาติ ถ.พระราม 9 แขวงห้วยขวาง เขตห้วยขวาง กรุงเทพฯ 10310
A4: 65/116-117 Chamnan Phenjati Building, 14th Floor,Rama 9 Road, Huaykwang District, Bangkok 10310
A5: โทรศัพท์ : 66(02) 246 1074-7 แฟกซ์ : 66(02) 246 1078
A6: เลขประจำตัวผู้เสียภาษี : 0105558005717 สำนักงานใหญ่ : Head Office | I6: สำหรับลูกค้า / Customer
A8: ชื่อลูกค้า/Customer : | C8: =VLOOKUP(J8,Cus!A:B,2,FALSE) -> บริษัท พิทักษ์ธนทรัพย์ จำกัด | G8: เลขที่/No. : | H8: 505042 | J8: =VLOOKUP(H8,Data!B:C,2,FALSE) -> A123 | K8: Total Item | L8: =COUNTIF(Data!$B:$B,Bill!$H$8) -> 4
A9: ที่อยู่/Address : | C9: =VLOOKUP(J8,Cus!A:C,3,FALSE) -> อาคาร ชุดคอนโดมิเนียมอุตสาหกรรม ไคตัค ห้องเลขที่ K 005007 ชั้นที่ 5 เลขที่ 47/315 ถนน ป๊อบปูล่า ตำบลบ้านใหม่ อำเภอปากเกร็ด จังหวัดนนทบุรี 11120 | G9: วันที่/Date : | H9: =INDEX(Data!A:A,MATCH(Bill!H8,Data!B:B,0)) -> 45417
A10: เลขประจำตัวผู้เสียภาษี/Tax ID : | C10: =VLOOKUP(J8,Cus!A:E,5,FALSE) -> 135562018801 | E10: เบอร์โทร/Telephone : | F10: =VLOOKUP(J8,Cus!A:F,6,FALSE) -> 1994585159
A12: ลำดับที่ Items | B12: รายละเอียด Description | G12: ปริมาณ Quantity | H12: ราคา / หน่วย Price per Unit | I12: จำนวนเงิน Amount
A13: =ROW(A1) -> 1 | B13: {=IFERROR(IF($L$8>=1,INDEX(Data!$E:$E,MATCH(1,(Data!$B:$B=Bill!$H$8)*(Data!$Q:$Q=Bill!$A13),0),1),0),"")} -> 076800013 | C13: =IFERROR(VLOOKUP(B13,ProductMaster!B:D,2,FALSE)," ") -> 48-22-8336 | E13: =IFERROR(VLOOKUP(B13,ProductMaster!B:D,3,FALSE)," ") -> PACKOUT Cup Holder | G13: {=IFERROR(IF($L$8>=1,INDEX(Data!$H:$H,MATCH(1,(Data!$B:$B=Bill!$H$8)*(Data!$Q:$Q=Bill!$A13),0),1),0),"")} -> 1 | H13: {=IFERROR(IF($L$8>=1,INDEX(Data!$I:$I,MATCH(1,(Data!$B:$B=Bill!$H$8)*(Data!$Q:$Q=Bill!$A13),0),1),0),"")} -> 362.61682 | I13: =IF(ISERROR(G13*H13),"",G13*H13) -> 362.61682 | J13: =H13*1.07 -> 388 | L13: =IFERROR(VLOOKUP(B13,ProductMaster_iPST_iPower[[SKU]:[ProductGroup]],4,0),"") -> Accessories | N13: Hand Tools | O13: =((SUMIF(L13:L27,N13,I13:I27))*1.07) -> 0
A14: =ROW(A2) -> 2 | B14: {=IFERROR(IF($L$8>=1,INDEX(Data!$E:$E,MATCH(1,(Data!$B:$B=Bill!$H$8)*(Data!$Q:$Q=Bill!$A14),0),1),0),"")} -> 129305990 | C14: =IFERROR(VLOOKUP(B14,ProductMaster!B:D,2,FALSE)," ") -> 48-22-8487 | E14: =IFERROR(VLOOKUP(B14,ProductMaster!B:D,3,FALSE)," ") -> PACKOUT Large Mounting Plate | G14: {=IFERROR(IF($L$8>=1,INDEX(Data!$H:$H,MATCH(1,(Data!$B:$B=Bill!$H$8)*(Data!$Q:$Q=Bill!$A14),0),1),0),"")} -> 1 | H14: {=IFERROR(IF($L$8>=1,INDEX(Data!$I:$I,MATCH(1,(Data!$B:$B=Bill!$H$8)*(Data!$Q:$Q=Bill!$A14),0),1),0),"")} -> 2138.3178 | I14: =IF(ISERROR(G14*H14),"",G14*H14) -> 2138.3178 | J14: =H14*1.07 -> 2288 | L14: =IFERROR(VLOOKUP(B14,ProductMaster_iPST_iPower[[SKU]:[ProductGroup]],4,0),"") -> Packout | N14: Accessories | O14: =((SUMIF(L13:L27,N14,I13:I27))*1.07) -> 388
A15: =ROW(A3) -> 3 | B15: {=IFERROR(IF($L$8>=1,INDEX(Data!$E:$E,MATCH(1,(Data!$B:$B=Bill!$H$8)*(Data!$Q:$Q=Bill!$A15),0),1),0),"")} -> 129305469 | C15: =IFERROR(VLOOKUP(B15,ProductMaster!B:D,2,FALSE)," ") -> 48-22-8422 | E15: =IFERROR(VLOOKUP(B15,ProductMaster!B:D,3,FALSE)," ") -> กล่องเครื่องมือคอมแพ็ค PACKOUT | G15: {=IFERROR(IF($L$8>=1,INDEX(Data!$H:$H,MATCH(1,(Data!$B:$B=Bill!$H$8)*(Data!$Q:$Q=Bill!$A15),0),1),0),"")} -> 1 | H15: {=IFERROR(IF($L$8>=1,INDEX(Data!$I:$I,MATCH(1,(Data!$B:$B=Bill!$H$8)*(Data!$Q:$Q=Bill!$A15),0),1),0),"")} -> 3540.1869 | I15: =IF(ISERROR(G15*H15),"",G15*H15) -> 3540.1869 | J15: =H15*1.07 -> 3788 | L15: =IFERROR(VLOOKUP(B15,ProductMaster_iPST_iPower[[SKU]:[ProductGroup]],4,0),"") -> Packout | N15: Sum | O15: =SUM(O13:O14) -> 388
A16: =ROW(A4) -> 4 | B16: {=IFERROR(IF($L$8>=1,INDEX(Data!$E:$E,MATCH(1,(Data!$B:$B=Bill!$H$8)*(Data!$Q:$Q=Bill!$A16),0),1),0),"")} -> 006138401 | C16: =IFERROR(VLOOKUP(B16,ProductMaster!B:D,2,FALSE)," ") -> 48-22-8392R | E16: =IFERROR(VLOOKUP(B16,ProductMaster!B:D,3,FALSE)," ") -> แก้วเก็บความเย็น PACKOUT™ ขนาด 20 ออนซ์ | G16: {=IFERROR(IF($L$8>=1,INDEX(Data!$H:$H,MATCH(1,(Data!$B:$B=Bill!$H$8)*(Data!$Q:$Q=Bill!$A16),0),1),0),"")} -> 1 | H16: {=IFERROR(IF($L$8>=1,INDEX(Data!$I:$I,MATCH(1,(Data!$B:$B=Bill!$H$8)*(Data!$Q:$Q=Bill!$A16),0),1),0),"")} -> 1110.2804 | I16: =IF(ISERROR(G16*H16),"",G16*H16) -> 1110.2804 | J16: =H16*1.07 -> 1188 | L16: =IFERROR(VLOOKUP(B16,ProductMaster_iPST_iPower[[SKU]:[ProductGroup]],4,0),"") -> Packout
A17: =ROW(B5) -> 5 | B17: {=IFERROR(IF($L$8>=1,INDEX(Data!$E:$E,MATCH(1,(Data!$B:$B=Bill!$H$8)*(Data!$Q:$Q=Bill!$A17),0),1),0),"")} | C17: =IFERROR(VLOOKUP(B17,ProductMaster!B:D,2,FALSE)," ") | E17: =IFERROR(VLOOKUP(B17,ProductMaster!B:D,3,FALSE)," ") | G17: {=IFERROR(IF($L$8>=1,INDEX(Data!$H:$H,MATCH(1,(Data!$B:$B=Bill!$H$8)*(Data!$Q:$Q=Bill!$A17),0),1),0),"")} | H17: {=IFERROR(IF($L$8>=1,INDEX(Data!$I:$I,MATCH(1,(Data!$B:$B=Bill!$H$8)*(Data!$Q:$Q=Bill!$A17),0),1),0),"")} | I17: =IF(ISERROR(G17*H17),"",G17*H17) | J17: =H17*1.07 -> #VALUE! | L17: =IFERROR(VLOOKUP(B17,ProductMaster_iPST_iPower[[SKU]:[ProductGroup]],4,0),"") | O17: 5888
A18: =ROW(B6) -> 6 | B18: {=IFERROR(IF($L$8>=1,INDEX(Data!$E:$E,MATCH(1,(Data!$B:$B=Bill!$H$8)*(Data!$Q:$Q=Bill!$A18),0),1),0),"")} | C18: =IFERROR(VLOOKUP(B18,ProductMaster!B:D,2,FALSE)," ") | E18: =IFERROR(VLOOKUP(B18,ProductMaster!B:D,3,FALSE)," ") | G18: {=IFERROR(IF($L$8>=1,INDEX(Data!$H:$H,MATCH(1,(Data!$B:$B=Bill!$H$8)*(Data!$Q:$Q=Bill!$A18),0),1),0),"")} | H18: {=IFERROR(IF($L$8>=1,INDEX(Data!$I:$I,MATCH(1,(Data!$B:$B=Bill!$H$8)*(Data!$Q:$Q=Bill!$A18),0),1),0),"")} | I18: =IF(ISERROR(G18*H18),"",G18*H18) | J18: =H18*1.07 -> #VALUE! | L18: =IFERROR(VLOOKUP(B18,ProductMaster_iPST_iPower[[SKU]:[ProductGroup]],4,0),"") | O18: =O17-O15 -> 5500
A19: =ROW(B7) -> 7 | B19: {=IFERROR(IF($L$8>=1,INDEX(Data!$E:$E,MATCH(1,(Data!$B:$B=Bill!$H$8)*(Data!$Q:$Q=Bill!$A19),0),1),0),"")} | C19: =IFERROR(VLOOKUP(B19,ProductMaster!B:D,2,FALSE)," ") | E19: =IFERROR(VLOOKUP(B19,ProductMaster!B:D,3,FALSE)," ") | G19: {=IFERROR(IF($L$8>=1,INDEX(Data!$H:$H,MATCH(1,(Data!$B:$B=Bill!$H$8)*(Data!$Q:$Q=Bill!$A19),0),1),0),"")} | H19: {=IFERROR(IF($L$8>=1,INDEX(Data!$I:$I,MATCH(1,(Data!$B:$B=Bill!$H$8)*(Data!$Q:$Q=Bill!$A19),0),1),0),"")} | I19: =IF(ISERROR(G19*H19),"",G19*H19) | J19: =H19*1.07 -> #VALUE! | L19: =IFERROR(VLOOKUP(B19,ProductMaster_iPST_iPower[[SKU]:[ProductGroup]],4,0),"")
A20: =ROW(B8) -> 8 | B20: {=IFERROR(IF($L$8>=1,INDEX(Data!$E:$E,MATCH(1,(Data!$B:$B=Bill!$H$8)*(Data!$Q:$Q=Bill!$A20),0),1),0),"")} | C20: =IFERROR(VLOOKUP(B20,ProductMaster!B:D,2,FALSE)," ") | E20: =IFERROR(VLOOKUP(B20,ProductMaster!B:D,3,FALSE)," ") | G20: {=IFERROR(IF($L$8>=1,INDEX(Data!$H:$H,MATCH(1,(Data!$B:$B=Bill!$H$8)*(Data!$Q:$Q=Bill!$A20),0),1),0),"")} | H20: {=IFERROR(IF($L$8>=1,INDEX(Data!$I:$I,MATCH(1,(Data!$B:$B=Bill!$H$8)*(Data!$Q:$Q=Bill!$A20),0),1),0),"")} | I20: =IF(ISERROR(G20*H20),"",G20*H20) | L20: =IFERROR(VLOOKUP(B20,ProductMaster_iPST_iPower[[SKU]:[ProductGroup]],4,0),"")
A21: =ROW(B9) -> 9 | B21: {=IFERROR(IF($L$8>=1,INDEX(Data!$E:$E,MATCH(1,(Data!$B:$B=Bill!$H$8)*(Data!$Q:$Q=Bill!$A21),0),1),0),"")} | C21: =IFERROR(VLOOKUP(B21,ProductMaster!B:D,2,FALSE)," ") | E21: =IFERROR(VLOOKUP(B21,ProductMaster!B:D,3,FALSE)," ") | G21: {=IFERROR(IF($L$8>=1,INDEX(Data!$H:$H,MATCH(1,(Data!$B:$B=Bill!$H$8)*(Data!$Q:$Q=Bill!$A21),0),1),0),"")} | H21: {=IFERROR(IF($L$8>=1,INDEX(Data!$I:$I,MATCH(1,(Data!$B:$B=Bill!$H$8)*(Data!$Q:$Q=Bill!$A21),0),1),0),"")} | I21: =IF(ISERROR(G21*H21),"",G21*H21) | J21: =216/2 -> 108 | L21: =IFERROR(VLOOKUP(B21,ProductMaster_iPST_iPower[[SKU]:[ProductGroup]],4,0),"")
A22: =ROW(B10) -> 10 | B22: {=IFERROR(IF($L$8>=1,INDEX(Data!$E:$E,MATCH(1,(Data!$B:$B=Bill!$H$8)*(Data!$Q:$Q=Bill!$A22),0),1),0),"")} | C22: =IFERROR(VLOOKUP(B22,ProductMaster!B:D,2,FALSE)," ") | E22: =IFERROR(VLOOKUP(B22,ProductMaster!B:D,3,FALSE)," ") | G22: {=IFERROR(IF($L$8>=1,INDEX(Data!$H:$H,MATCH(1,(Data!$B:$B=Bill!$H$8)*(Data!$Q:$Q=Bill!$A22),0),1),0),"")} | H22: {=IFERROR(IF($L$8>=1,INDEX(Data!$I:$I,MATCH(1,(Data!$B:$B=Bill!$H$8)*(Data!$Q:$Q=Bill!$A22),0),1),0),"")} | I22: =IF(ISERROR(G22*H22),"",G22*H22) | J22: =J21/1.07 -> 100.93458 | L22: =IFERROR(VLOOKUP(B22,ProductMaster_iPST_iPower[[SKU]:[ProductGroup]],4,0),"")
A23: =ROW(B11) -> 11 | B23: {=IFERROR(IF($L$8>=1,INDEX(Data!$E:$E,MATCH(1,(Data!$B:$B=Bill!$H$8)*(Data!$Q:$Q=Bill!$A23),0),1),0),"")} | C23: =IFERROR(VLOOKUP(B23,ProductMaster!B:D,2,FALSE)," ") | E23: =IFERROR(VLOOKUP(B23,ProductMaster!B:D,3,FALSE)," ") | G23: {=IFERROR(IF($L$8>=1,INDEX(Data!$H:$H,MATCH(1,(Data!$B:$B=Bill!$H$8)*(Data!$Q:$Q=Bill!$A23),0),1),0),"")} | H23: {=IFERROR(IF($L$8>=1,INDEX(Data!$I:$I,MATCH(1,(Data!$B:$B=Bill!$H$8)*(Data!$Q:$Q=Bill!$A23),0),1),0),"")} | I23: =IF(ISERROR(G23*H23),"",G23*H23) | L23: =IFERROR(VLOOKUP(B23,ProductMaster_iPST_iPower[[SKU]:[ProductGroup]],4,0),"")
A24: =ROW(B12) -> 12 | B24: {=IFERROR(IF($L$8>=1,INDEX(Data!$E:$E,MATCH(1,(Data!$B:$B=Bill!$H$8)*(Data!$Q:$Q=Bill!$A24),0),1),0),"")} | C24: =IFERROR(VLOOKUP(B24,ProductMaster!B:D,2,FALSE)," ") | E24: =IFERROR(VLOOKUP(B24,ProductMaster!B:D,3,FALSE)," ") | G24: {=IFERROR(IF($L$8>=1,INDEX(Data!$H:$H,MATCH(1,(Data!$B:$B=Bill!$H$8)*(Data!$Q:$Q=Bill!$A24),0),1),0),"")} | H24: {=IFERROR(IF($L$8>=1,INDEX(Data!$I:$I,MATCH(1,(Data!$B:$B=Bill!$H$8)*(Data!$Q:$Q=Bill!$A24),0),1),0),"")} | I24: =IF(ISERROR(G24*H24),"",G24*H24) | J24: =I24*1.07 -> #VALUE! | L24: =IFERROR(VLOOKUP(B24,ProductMaster_iPST_iPower[[SKU]:[ProductGroup]],4,0),"")
A25: =ROW(B13) -> 13 | B25: {=IFERROR(IF($L$8>=1,INDEX(Data!$E:$E,MATCH(1,(Data!$B:$B=Bill!$H$8)*(Data!$Q:$Q=Bill!$A25),0),1),0),"")} | C25: =IFERROR(VLOOKUP(B25,ProductMaster!B:D,2,FALSE)," ") | E25: =IFERROR(VLOOKUP(B25,ProductMaster!B:D,3,FALSE)," ") | G25: {=IFERROR(IF($L$8>=1,INDEX(Data!$H:$H,MATCH(1,(Data!$B:$B=Bill!$H$8)*(Data!$Q:$Q=Bill!$A25),0),1),0),"")} | H25: {=IFERROR(IF($L$8>=1,INDEX(Data!$I:$I,MATCH(1,(Data!$B:$B=Bill!$H$8)*(Data!$Q:$Q=Bill!$A25),0),1),0),"")} | I25: =IF(ISERROR(G25*H25),"",G25*H25) | L25: =IFERROR(VLOOKUP(B25,ProductMaster_iPST_iPower[[SKU]:[ProductGroup]],4,0),"")
A26: =ROW(B14) -> 14 | B26: {=IFERROR(IF($L$8>=1,INDEX(Data!$E:$E,MATCH(1,(Data!$B:$B=Bill!$H$8)*(Data!$Q:$Q=Bill!$A26),0),1),0),"")} | C26: =IFERROR(VLOOKUP(B26,ProductMaster!B:D,2,FALSE)," ") | E26: =IFERROR(VLOOKUP(B26,ProductMaster!B:D,3,FALSE)," ") | G26: {=IFERROR(IF($L$8>=1,INDEX(Data!$H:$H,MATCH(1,(Data!$B:$B=Bill!$H$8)*(Data!$Q:$Q=Bill!$A26),0),1),0),"")} | H26: {=IFERROR(IF($L$8>=1,INDEX(Data!$I:$I,MATCH(1,(Data!$B:$B=Bill!$H$8)*(Data!$Q:$Q=Bill!$A26),0),1),0),"")} | I26: =IF(ISERROR(G26*H26),"",G26*H26) | L26: =IFERROR(VLOOKUP(B26,ProductMaster_iPST_iPower[[SKU]:[ProductGroup]],4,0),"")
A27: =ROW(B15) -> 15 | B27: {=IFERROR(IF($L$8>=1,INDEX(Data!$E:$E,MATCH(1,(Data!$B:$B=Bill!$H$8)*(Data!$Q:$Q=Bill!$A27),0),1),0),"")} | C27: =IFERROR(VLOOKUP(B27,ProductMaster!B:D,2,FALSE)," ") | E27: =IFERROR(VLOOKUP(B27,ProductMaster!B:D,3,FALSE)," ") | G27: {=IFERROR(IF($L$8>=1,INDEX(Data!$H:$H,MATCH(1,(Data!$B:$B=Bill!$H$8)*(Data!$Q:$Q=Bill!$A27),0),1),0),"")} | H27: {=IFERROR(IF($L$8>=1,INDEX(Data!$I:$I,MATCH(1,(Data!$B:$B=Bill!$H$8)*(Data!$Q:$Q=Bill!$A27),0),1),0),"")} | I27: =IF(ISERROR(G27*H27),"",G27*H27) | L27: =IFERROR(VLOOKUP(B27,ProductMaster_iPST_iPower[[SKU]:[ProductGroup]],4,0),"")
A29: หมายเหตุ : | C29: =_xlfn.IFS(O15>5888,"สิทธิรับฟรี กระเป๋าช่างไฟฟ้า จำนวน 1 ชิ้น",O15>2888,"สิทธิรับฟรี มีดคัทเตอร์ขนาดพกพา จำนวน 1 ชิ้น",TRUE,"") | G29: จำนวนเงินรวม / Total Amount | I29: =ROUND(SUM(I13:I28),2) -> 7151.4 | K29: =SUMIF(Data!B:B,Bill!H8,Data!K:K) -> 7151.41 | L29: =I29-K29 -> -0.01
A30: รับประกันสินค้าตามเงื่อนไขของผู้ผลิต ไม่รับเปลี่ยนหรือคืนสินค้า เว้นแต่กรณีที่สินค้าชำรุดเนื่องมาจากความบกพร่องของตัวสินค้าเอง | G30: ภาษีมูลค่าเพิ่ม / Vat 7% | I30: =ROUND(I29*0.07,2) -> 500.6
A31: ชำระโดย : | C31: =INDEX(Data!M:M,MATCH(Bill!H8,Data!B:B,0)) -> Transfer | G31: จำนวนเงินรวมทั้งสิ้น / Grand Total | I31: =ROUND(SUM(I29:I30),2) -> 7652 | Q31: =256-300 -> -44
G32: จำนวนส่วนลด / Discount
A33: บาท / Baht | C33: =BAHTTEXT(I33) -> เจ็ดพันหกร้อยห้าสิบสองบาทถ้วน | G33: จำนวนเงินรวมสุทธิ / Total Net | I33: =ROUND(I31-I32,2) -> 7652 | O33: =500-308 -> 192
C35: *** | D35: =VLOOKUP(H8,Data!B:P,15,FALSE) -> Tax Invoice
G36: ผู้รับเงิน / Received by
C38: บริษัท มิลวอกี้ ทูล (ประเทศไทย) จํากัด | I38: สำเนาใบเสร็จรับเงิน
C39: Milwaukee Tool (Thailand) Company Limited | I39: Copy Receipt
A40: 65/116-117 ชั้น 14 อาคารชำนาญเพ็ญชาติ ถ.พระราม 9 แขวงห้วยขวาง เขตห้วยขวาง กรุงเทพฯ 10310
A41: 65/116-117 Chamnan Phenjati Building, 14th Floor,Rama 9 Road, Huaykwang District, Bangkok 10310
A42: โทรศัพท์ : 66(02) 246 1074-7 แฟกซ์ : 66(02) 246 1078
A43: เลขประจำตัวผู้เสียภาษี : 0105558005717 สำนักงานใหญ่ : Head Office | I43: สำหรับบริษัท / Company
A45: ชื่อลูกค้า/Customer : | C45: =C8 -> บริษัท พิทักษ์ธนทรัพย์ จำกัด | G45: เลขที่/No. : | H45: =H8 -> 505042
A46: ที่อยู่/Address : | C46: =C9 -> อาคาร ชุดคอนโดมิเนียมอุตสาหกรรม ไคตัค ห้องเลขที่ K 005007 ชั้นที่ 5 เลขที่ 47/315 ถนน ป๊อบปูล่า ตำบลบ้านใหม่ อำเภอปากเกร็ด จังหวัดนนทบุรี 11120 | G46: วันที่/Date : | H46: =H9 -> 45417
A47: เลขประจำตัวผู้เสียภาษี/Tax ID : | C47: =C10 -> 135562018801 | E47: เบอร์โทร/Telephone : | F47: =F10 -> 1994585159
A49: ลำดับที่ Items | B49: รายละเอียด Description | G49: ปริมาณ Quantity | H49: ราคา / หน่วย Price per Unit | I49: จำนวนเงิน Amount
A50: =ROW(A1) -> 1 | B50: {=IFERROR(IF($L$8>=1,INDEX(Data!$E:$E,MATCH(1,(Data!$B:$B=Bill!$H$8)*(Data!$Q:$Q=Bill!$A50),0),1),0),"")} -> 076800013 | C50: =IFERROR(VLOOKUP(B50,ProductMaster!B:D,2,FALSE)," ") -> 48-22-8336 | E50: =IFERROR(VLOOKUP(B50,ProductMaster!B:D,3,FALSE)," ") -> PACKOUT Cup Holder | G50: {=IFERROR(IF($L$8>=1,INDEX(Data!$H:$H,MATCH(1,(Data!$B:$B=Bill!$H$8)*(Data!$Q:$Q=Bill!$A50),0),1),0),"")} -> 1 | H50: {=IFERROR(IF($L$8>=1,INDEX(Data!$I:$I,MATCH(1,(Data!$B:$B=Bill!$H$8)*(Data!$Q:$Q=Bill!$A50),0),1),0),"")} -> 362.61682 | I50: =IF(ISERROR(G50*H50),"",G50*H50) -> 362.61682
A51: =ROW(A2) -> 2 | B51: {=IFERROR(IF($L$8>=1,INDEX(Data!$E:$E,MATCH(1,(Data!$B:$B=Bill!$H$8)*(Data!$Q:$Q=Bill!$A51),0),1),0),"")} -> 129305990 | C51: =IFERROR(VLOOKUP(B51,ProductMaster!B:D,2,FALSE)," ") -> 48-22-8487 | E51: =IFERROR(VLOOKUP(B51,ProductMaster!B:D,3,FALSE)," ") -> PACKOUT Large Mounting Plate | G51: {=IFERROR(IF($L$8>=1,INDEX(Data!$H:$H,MATCH(1,(Data!$B:$B=Bill!$H$8)*(Data!$Q:$Q=Bill!$A51),0),1),0),"")} -> 1 | H51: {=IFERROR(IF($L$8>=1,INDEX(Data!$I:$I,MATCH(1,(Data!$B:$B=Bill!$H$8)*(Data!$Q:$Q=Bill!$A51),0),1),0),"")} -> 2138.3178 | I51: =IF(ISERROR(G51*H51),"",G51*H51) -> 2138.3178
A52: =ROW(A3) -> 3 | B52: {=IFERROR(IF($L$8>=1,INDEX(Data!$E:$E,MATCH(1,(Data!$B:$B=Bill!$H$8)*(Data!$Q:$Q=Bill!$A52),0),1),0),"")} -> 129305469 | C52: =IFERROR(VLOOKUP(B52,ProductMaster!B:D,2,FALSE)," ") -> 48-22-8422 | E52: =IFERROR(VLOOKUP(B52,ProductMaster!B:D,3,FALSE)," ") -> กล่องเครื่องมือคอมแพ็ค PACKOUT | G52: {=IFERROR(IF($L$8>=1,INDEX(Data!$H:$H,MATCH(1,(Data!$B:$B=Bill!$H$8)*(Data!$Q:$Q=Bill!$A52),0),1),0),"")} -> 1 | H52: {=IFERROR(IF($L$8>=1,INDEX(Data!$I:$I,MATCH(1,(Data!$B:$B=Bill!$H$8)*(Data!$Q:$Q=Bill!$A52),0),1),0),"")} -> 3540.1869 | I52: =IF(ISERROR(G52*H52),"",G52*H52) -> 3540.1869
A53: =ROW(A4) -> 4 | B53: {=IFERROR(IF($L$8>=1,INDEX(Data!$E:$E,MATCH(1,(Data!$B:$B=Bill!$H$8)*(Data!$Q:$Q=Bill!$A53),0),1),0),"")} -> 006138401 | C53: =IFERROR(VLOOKUP(B53,ProductMaster!B:D,2,FALSE)," ") -> 48-22-8392R | E53: =IFERROR(VLOOKUP(B53,ProductMaster!B:D,3,FALSE)," ") -> แก้วเก็บความเย็น PACKOUT™ ขนาด 20 ออนซ์ | G53: {=IFERROR(IF($L$8>=1,INDEX(Data!$H:$H,MATCH(1,(Data!$B:$B=Bill!$H$8)*(Data!$Q:$Q=Bill!$A53),0),1),0),"")} -> 1 | H53: {=IFERROR(IF($L$8>=1,INDEX(Data!$I:$I,MATCH(1,(Data!$B:$B=Bill!$H$8)*(Data!$Q:$Q=Bill!$A53),0),1),0),"")} -> 1110.2804 | I53: =IF(ISERROR(G53*H53),"",G53*H53) -> 1110.2804
A54: =ROW(A5) -> 5 | B54: {=IFERROR(IF($L$8>=1,INDEX(Data!$E:$E,MATCH(1,(Data!$B:$B=Bill!$H$8)*(Data!$Q:$Q=Bill!$A54),0),1),0),"")} | C54: =IFERROR(VLOOKUP(B54,ProductMaster!B:D,2,FALSE)," ") | E54: =IFERROR(VLOOKUP(B54,ProductMaster!B:D,3,FALSE)," ") | G54: {=IFERROR(IF($L$8>=1,INDEX(Data!$H:$H,MATCH(1,(Data!$B:$B=Bill!$H$8)*(Data!$Q:$Q=Bill!$A54),0),1),0),"")} | H54: {=IFERROR(IF($L$8>=1,INDEX(Data!$I:$I,MATCH(1,(Data!$B:$B=Bill!$H$8)*(Data!$Q:$Q=Bill!$A54),0),1),0),"")} | I54: =IF(ISERROR(G54*H54),"",G54*H54)
A55: =ROW(A6) -> 6 | B55: {=IFERROR(IF($L$8>=1,INDEX(Data!$E:$E,MATCH(1,(Data!$B:$B=Bill!$H$8)*(Data!$Q:$Q=Bill!$A55),0),1),0),"")} | C55: =IFERROR(VLOOKUP(B55,ProductMaster!B:D,2,FALSE)," ") | E55: =IFERROR(VLOOKUP(B55,ProductMaster!B:D,3,FALSE)," ") | G55: {=IFERROR(IF($L$8>=1,INDEX(Data!$H:$H,MATCH(1,(Data!$B:$B=Bill!$H$8)*(Data!$Q:$Q=Bill!$A55),0),1),0),"")} | H55: {=IFERROR(IF($L$8>=1,INDEX(Data!$I:$I,MATCH(1,(Data!$B:$B=Bill!$H$8)*(Data!$Q:$Q=Bill!$A55),0),1),0),"")} | I55: =IF(ISERROR(G55*H55),"",G55*H55)
A56: =ROW(A7) -> 7 | B56: {=IFERROR(IF($L$8>=1,INDEX(Data!$E:$E,MATCH(1,(Data!$B:$B=Bill!$H$8)*(Data!$Q:$Q=Bill!$A56),0),1),0),"")} | C56: =IFERROR(VLOOKUP(B56,ProductMaster!B:D,2,FALSE)," ") | E56: =IFERROR(VLOOKUP(B56,ProductMaster!B:D,3,FALSE)," ") | G56: {=IFERROR(IF($L$8>=1,INDEX(Data!$H:$H,MATCH(1,(Data!$B:$B=Bill!$H$8)*(Data!$Q:$Q=Bill!$A56),0),1),0),"")} | H56: {=IFERROR(IF($L$8>=1,INDEX(Data!$I:$I,MATCH(1,(Data!$B:$B=Bill!$H$8)*(Data!$Q:$Q=Bill!$A56),0),1),0),"")} | I56: =IF(ISERROR(G56*H56),"",G56*H56)
A57: =ROW(A8) -> 8 | B57: {=IFERROR(IF($L$8>=1,INDEX(Data!$E:$E,MATCH(1,(Data!$B:$B=Bill!$H$8)*(Data!$Q:$Q=Bill!$A57),0),1),0),"")} | C57: =IFERROR(VLOOKUP(B57,ProductMaster!B:D,2,FALSE)," ") | E57: =IFERROR(VLOOKUP(B57,ProductMaster!B:D,3,FALSE)," ") | G57: {=IFERROR(IF($L$8>=1,INDEX(Data!$H:$H,MATCH(1,(Data!$B:$B=Bill!$H$8)*(Data!$Q:$Q=Bill!$A57),0),1),0),"")} | H57: {=IFERROR(IF($L$8>=1,INDEX(Data!$I:$I,MATCH(1,(Data!$B:$B=Bill!$H$8)*(Data!$Q:$Q=Bill!$A57),0),1),0),"")} | I57: =IF(ISERROR(G57*H57),"",G57*H57)
A58: =ROW(A9) -> 9 | B58: {=IFERROR(IF($L$8>=1,INDEX(Data!$E:$E,MATCH(1,(Data!$B:$B=Bill!$H$8)*(Data!$Q:$Q=Bill!$A58),0),1),0),"")} | C58: =IFERROR(VLOOKUP(B58,ProductMaster!B:D,2,FALSE)," ") | E58: =IFERROR(VLOOKUP(B58,ProductMaster!B:D,3,FALSE)," ") | G58: {=IFERROR(IF($L$8>=1,INDEX(Data!$H:$H,MATCH(1,(Data!$B:$B=Bill!$H$8)*(Data!$Q:$Q=Bill!$A58),0),1),0),"")} | H58: {=IFERROR(IF($L$8>=1,INDEX(Data!$I:$I,MATCH(1,(Data!$B:$B=Bill!$H$8)*(Data!$Q:$Q=Bill!$A58),0),1),0),"")} | I58: =IF(ISERROR(G58*H58),"",G58*H58)
A59: =ROW(A10) -> 10 | B59: {=IFERROR(IF($L$8>=1,INDEX(Data!$E:$E,MATCH(1,(Data!$B:$B=Bill!$H$8)*(Data!$Q:$Q=Bill!$A59),0),1),0),"")} | C59: =IFERROR(VLOOKUP(B59,ProductMaster!B:D,2,FALSE)," ") | E59: =IFERROR(VLOOKUP(B59,ProductMaster!B:D,3,FALSE)," ") | G59: {=IFERROR(IF($L$8>=1,INDEX(Data!$H:$H,MATCH(1,(Data!$B:$B=Bill!$H$8)*(Data!$Q:$Q=Bill!$A59),0),1),0),"")} | H59: {=IFERROR(IF($L$8>=1,INDEX(Data!$I:$I,MATCH(1,(Data!$B:$B=Bill!$H$8)*(Data!$Q:$Q=Bill!$A59),0),1),0),"")} | I59: =IF(ISERROR(G59*H59),"",G59*H59)
A60: =ROW(A11) -> 11 | B60: {=IFERROR(IF($L$8>=1,INDEX(Data!$E:$E,MATCH(1,(Data!$B:$B=Bill!$H$8)*(Data!$Q:$Q=Bill!$A60),0),1),0),"")} | C60: =IFERROR(VLOOKUP(B60,ProductMaster!B:D,2,FALSE)," ") | E60: =IFERROR(VLOOKUP(B60,ProductMaster!B:D,3,FALSE)," ") | G60: {=IFERROR(IF($L$8>=1,INDEX(Data!$H:$H,MATCH(1,(Data!$B:$B=Bill!$H$8)*(Data!$Q:$Q=Bill!$A60),0),1),0),"")} | H60: {=IFERROR(IF($L$8>=1,INDEX(Data!$I:$I,MATCH(1,(Data!$B:$B=Bill!$H$8)*(Data!$Q:$Q=Bill!$A60),0),1),0),"")} | I60: =IF(ISERROR(G60*H60),"",G60*H60)
A61: =ROW(A12) -> 12 | B61: {=IFERROR(IF($L$8>=1,INDEX(Data!$E:$E,MATCH(1,(Data!$B:$B=Bill!$H$8)*(Data!$Q:$Q=Bill!$A61),0),1),0),"")} | C61: =IFERROR(VLOOKUP(B61,ProductMaster!B:D,2,FALSE)," ") | E61: =IFERROR(VLOOKUP(B61,ProductMaster!B:D,3,FALSE)," ") | G61: {=IFERROR(IF($L$8>=1,INDEX(Data!$H:$H,MATCH(1,(Data!$B:$B=Bill!$H$8)*(Data!$Q:$Q=Bill!$A61),0),1),0),"")} | H61: {=IFERROR(IF($L$8>=1,INDEX(Data!$I:$I,MATCH(1,(Data!$B:$B=Bill!$H$8)*(Data!$Q:$Q=Bill!$A61),0),1),0),"")} | I61: =IF(ISERROR(G61*H61),"",G61*H61)
... A64: =ROW(A15) -> 15 | B64: {=IFERROR(IF($L$8>=1,INDEX(Data!$E:$E,MATCH(1,(Data!$B:$B=Bill!$H$8)*(Data!$Q:$Q=Bill!$A64),0),1),0),"")} | C64: =IFERROR(VLOOKUP(B64,ProductMaster!B:D,2,FALSE)," ") | E64: =IFERROR(VLOOKUP(B64,ProductMaster!B:D,3,FALSE)," ") | G64: {=IFERROR(IF($L$8>=1,INDEX(Data!$H:$H,MATCH(1,(Data!$B:$B=Bill!$H$8)*(Data!$Q:$Q=Bill!$A64),0),1),0),"")} | H64: {=IFERROR(IF($L$8>=1,INDEX(Data!$I:$I,MATCH(1,(Data!$B:$B=Bill!$H$8)*(Data!$Q:$Q=Bill!$A64),0),1),0),"")} | I64: =IF(ISERROR(G64*H64),"",G64*H64)
A66: หมายเหตุ : | C66: =C29 | G66: จำนวนเงินรวม / Total Amount | I66: =ROUND(SUM(I50:I65),2) -> 7151.4
A67: รับประกันสินค้าตามเงื่อนไขของผู้ผลิต ไม่รับเปลี่ยนหรือคืนสินค้า เว้นแต่กรณีที่สินค้าชำรุดเนื่องมาจากความบกพร่องของตัวสินค้าเอง | G67: ภาษีมูลค่าเพิ่ม / Vat 7% | I67: =ROUND(I66*0.07,2) -> 500.6
A68: ชำระโดย : | C68: =INDEX(Data!M:M,MATCH(Bill!H45,Data!B:B,0)) -> Transfer | G68: จำนวนเงินรวมทั้งสิ้น / Grand Total | I68: =ROUND(SUM(I66:I67),2) -> 7652
G69: จำนวนส่วนลด / Discount | I69: =+I32 -> 0
A70: บาท / Baht | C70: =BAHTTEXT(I70) -> เจ็ดพันหกร้อยห้าสิบสองบาทถ้วน | G70: จำนวนเงินรวมสุทธิ / Total Net | I70: =ROUND(I68-I69,2) -> 7652
C72: *** | D72: =VLOOKUP(H45,Data!B:P,15,FALSE) -> Tax Invoice
A73: Cashier : | B73: =INDEX(Data!N:N,MATCH(Bill!H45,Data!B:B,0)) -> Cat | G73: ผู้รับเงิน / Received by

Sheet Data
A1: Date | B1: Invoice no. | C1: Customer | D1: UPC | E1: SKU | F1: Model Name | G1: Description | H1: Qty | I1: PriceBook | J1: Vat 7% | K1: Total Price (Exclude Vat) | L1: Discount | M1: Payment | N1: Staff | O1: Kerry | P1: Remark | Q1: No.# | R1: =ROUND(SUM(K:K)+SUM(K:K)*7%,2)-R3 -> 549573.19 | S1: =ROUND(SUM(K:K),2)-R3 -> 512444.92 | T1: =SUM(T2:T76)-T3 -> 548316.06 | U1: =S1*7% -> 35871.144
A2: 45417 | B2: 505001 | C2: A105 | D2: 4892210222503 | E2: =IFERROR(VLOOKUP(D2,ProductMaster!$A:$B,2,FALSE),"") -> 018655011 | F2: =IFERROR(VLOOKUP(D2,ProductMaster!$A:$C,3,FALSE),"") -> M18 F2BL-0 | G2: =IFERROR(VLOOKUP($D2,ProductMaster!$A:$O,4,FALSE),"") -> เครื่องเป่าใบไม้ไร้สาย 18 โวลต์ ระบบแบตเตอรี่คู่ (เครื่องเปล่า) | H2: 1 | I2: =IFERROR(VLOOKUP(E2,ProductMaster!B:G,6,FALSE),0) -> 9241.1215 | J2: =ROUND(SUM(I2*7%),2) -> 646.88 | K2: =ROUND(SUM(H2*I2),2) -> 9241.12 | M2: Transfer | N2: Cat | O2: 0 | P2: No Tax Invoice | Q2: =IF(B2=B1,Q1+1,1) -> 1 | R2: =SUMIF($B$2:$K$500,S2,$K$2:$K$500) -> 9241.12 | S2: 505001 | T2: =R2*1.07 -> 9887.9984
A3: 45417 | B3: 505002 | C3: A041 | D3: 4892210204080 | E3: =IFERROR(VLOOKUP(D3,ProductMaster!$A:$B,2,FALSE),"") -> 018472009 | F3: =IFERROR(VLOOKUP(D3,ProductMaster!$A:$C,3,FALSE),"") -> M18 FHX-0X0 | G3: =IFERROR(VLOOKUP($D3,ProductMaster!$A:$O,4,FALSE),"") -> สว่านโรตารี่ไร้สาย 18 โวลต์ 26 มม. SDS PLUS 3 ระบบ (เครื่องเปล่า) | H3: 1 | I3: =IFERROR(VLOOKUP(E3,ProductMaster!B:G,6,FALSE),0) -> 11951.402 | J3: =ROUND(SUM(I3*7%),2) -> 836.6 | K3: =ROUND(SUM(H3*I3),2) -> 11951.4 | M3: Transfer | N3: Cat | O3: 0 | P3: Tax Invoice | Q3: =IF(B3=B2,Q2+1,1) -> 1 | R3: =SUMIF($B$2:$K$500,S3,$K$2:$K$500) -> 17958.89 | S3: 505002 | T3: =R3*1.07 -> 19216.012 | U3: บิล 0505002 เปิดบิลใหม่แทนบิล 0105028(ยกเลิกทั้งบิลออกใหม่) เนื่องจากลูกค้าได้แบตไปผิดรุ่น ลูกค้าเพิ่มเงิน 2,200 บาท
A4: 45417 | B4: 505002 | C4: A041 | D4: 4892210139313-BF | E4: =IFERROR(VLOOKUP(D4,ProductMaster!$A:$B,2,FALSE),"") -> 001997014-(BF) | F4: =IFERROR(VLOOKUP(D4,ProductMaster!$A:$C,3,FALSE),"") -> M12-18FCSA-(BF) | G4: =IFERROR(VLOOKUP($D4,ProductMaster!$A:$O,4,FALSE),"") -> แท่นชาร์จแบตเตอรี่ 12-18 โวลต์ แบบชาร์จเร็ว | H4: 1 | I4: =IFERROR(VLOOKUP(E4,ProductMaster!B:G,6,FALSE),0) -> 1766.3551 | J4: =ROUND(SUM(I4*7%),2) -> 123.64 | K4: =ROUND(SUM(H4*I4),2) -> 1766.36 | M4: Transfer | N4: Cat | O4: 0 | P4: Tax Invoice | Q4: =IF(B4=B3,Q3+1,1) -> 2 | R4: =SUMIF($B$2:$K$500,S4,$K$2:$K$500) -> 8493.46 | S4: 505003 | T4: =R4*1.07 -> 9088.0022
A5: 45417 | B5: 505002 | C5: A041 | D5: 4892210180988-BF | E5: =IFERROR(VLOOKUP(D5,ProductMaster!$A:$B,2,FALSE),"") -> 001998236DG9-(BF) | F5: =IFERROR(VLOOKUP(D5,ProductMaster!$A:$C,3,FALSE),"") -> M18HB8ASIA-(BF) | G5: =IFERROR(VLOOKUP($D5,ProductMaster!$A:$O,4,FALSE),"") -> แบตเตอรี่ 18 โวลต์ 8.0 แอมป์อาว HIGH OUTPUT | H5: 1 | I5: =IFERROR(VLOOKUP(E5,ProductMaster!B:G,6,FALSE),0) -> 3542.0561 | J5: =ROUND(SUM(I5*7%),2) -> 247.94 | K5: =ROUND(SUM(H5*I5),2) -> 3542.06 | M5: Transfer | N5: Cat | O5: 0 | P5: Tax Invoice | Q5: =IF(B5=B4,Q4+1,1) -> 3 | R5: =SUMIF($B$2:$K$500,S5,$K$2:$K$500) -> 27444.87 | S5: 505004 | T5: =R5*1.07 -> 29366.011
A6: 45417 | B6: 505002 | C6: A041 | D6: 45242573912 | E6: =IFERROR(VLOOKUP(D6,ProductMaster!$A:$B,2,FALSE),"") -> 006105507 | F6: =IFERROR(VLOOKUP(D6,ProductMaster!$A:$C,3,FALSE),"") -> 48-22-1505 | G6: =IFERROR(VLOOKUP($D6,ProductMaster!$A:$O,4,FALSE),"") -> มีดพับอเนกประสงค์ พร้อมช่องเก็บใบมีด รุ่น FASTBACK™ 6 IN 1 | H6: 1 | I6: =IFERROR(VLOOKUP(E6,ProductMaster!B:G,6,FALSE),0) -> 699.06542 | J6: =ROUND(SUM(I6*7%),2) -> 48.93 | K6: =ROUND(SUM(H6*I6),2) -> 699.07 | M6: Transfer | N6: Cat | O6: 0 | P6: Tax Invoice | Q6: =IF(B6=B5,Q5+1,1) -> 4 | R6: =SUMIF($B$2:$K$500,S6,$K$2:$K$500) -> 6624.3 | S6: 505005 | T6: =R6*1.07 -> 7088.001
A7: 45417 | B7: 505003 | C7: A107 | D7: 4892210179524 | E7: =IFERROR(VLOOKUP(D7,ProductMaster!$A:$B,2,FALSE),"") -> 018080020 | F7: =IFERROR(VLOOKUP(D7,ProductMaster!$A:$C,3,FALSE),"") -> M18 GG-0 ASIA | G7: =IFERROR(VLOOKUP($D7,ProductMaster!$A:$O,4,FALSE),"") -> M18 เครื่องอัดจารบี | H7: 1 | I7: =IFERROR(VLOOKUP(E7,ProductMaster!B:G,6,FALSE),0) -> 8493.4579 | J7: =ROUND(SUM(I7*7%),2) -> 594.54 | K7: =ROUND(SUM(H7*I7),2) -> 8493.46 | M7: Credit Card | N7: Cat | O7: 0 | P7: Tax Invoice | Q7: =IF(B7=B6,Q6+1,1) -> 1 | R7: =SUMIF($B$2:$K$500,S7,$K$2:$K$500) -> 239.25 | S7: 505006 | T7: =R7*1.07 -> 255.9975
A8: 45417 | B8: 505004 | C8: A106 | D8: 4892210240033 | E8: =IFERROR(VLOOKUP(D8,ProductMaster!$A:$B,2,FALSE),"") -> 059600307 | F8: =IFERROR(VLOOKUP(D8,ProductMaster!$A:$C,3,FALSE),"") -> M18 FPP2AC3-502LR SA | G8: =IFERROR(VLOOKUP($D8,ProductMaster!$A:$O,4,FALSE),"") -> M18 FPP2AC3-502LR SA (ชุดคอมโบสำหรับช่างไฟ) | H8: 1 | I8: =IFERROR(VLOOKUP(E8,ProductMaster!B:G,6,FALSE),0) -> 17652.336 | J8: =ROUND(SUM(I8*7%),2) -> 1235.66 | K8: =ROUND(SUM(H8*I8),2) -> 17652.34 | L8: 2000 | M8: Credit Card | N8: Cat | O8: 0 | P8: Tax Invoice | Q8: =IF(B8=B7,Q7+1,1) -> 1 | R8: =SUMIF($B$2:$K$500,S8,$K$2:$K$500) -> 856.08 | S8: 505007 | T8: =R8*1.07 -> 916.0056
A9: 45417 | B9: 505004 | C9: A106 | D9: 4892210163752 | E9: =IFERROR(VLOOKUP(D9,ProductMaster!$A:$B,2,FALSE),"") -> 018262012 | F9: =IFERROR(VLOOKUP(D9,ProductMaster!$A:$C,3,FALSE),"") -> M18 FHZ-0 | G9: =IFERROR(VLOOKUP($D9,ProductMaster!$A:$O,4,FALSE),"") -> เลื่อยชักอเนกประสงค์ไร้สาย 18 โวลต์ (เครื่องเปล่า) | H9: 1 | I9: =IFERROR(VLOOKUP(E9,ProductMaster!B:G,6,FALSE),0) -> 6250.4673 | J9: =ROUND(SUM(I9*7%),2) -> 437.53 | K9: =ROUND(SUM(H9*I9),2) -> 6250.47 | L9: 500 | M9: Credit Card | N9: Cat | O9: 0 | P9: Tax Invoice | Q9: =IF(B9=B8,Q8+1,1) -> 2 | R9: =SUMIF($B$2:$K$500,S9,$K$2:$K$500) -> 715.89 | S9: 505008 | T9: =R9*1.07 -> 766.0023
A10: 45417 | B10: 505004 | C10: A106 | D10: 4892210180988-BF | E10: =IFERROR(VLOOKUP(D10,ProductMaster!$A:$B,2,FALSE),"") -> 001998236DG9-(BF) | F10: =IFERROR(VLOOKUP(D10,ProductMaster!$A:$C,3,FALSE),"") -> M18HB8ASIA-(BF) | G10: =IFERROR(VLOOKUP($D10,ProductMaster!$A:$O,4,FALSE),"") -> แบตเตอรี่ 18 โวลต์ 8.0 แอมป์อาว HIGH OUTPUT | H10: 1 | I10: =IFERROR(VLOOKUP(E10,ProductMaster!B:G,6,FALSE),0) -> 3542.0561 | J10: =ROUND(SUM(I10*7%),2) -> 247.94 | K10: =ROUND(SUM(H10*I10),2) -> 3542.06 | M10: Credit Card | N10: Cat | O10: 0 | P10: Tax Invoice | Q10: =IF(B10=B9,Q9+1,1) -> 3 | R10: =SUMIF($B$2:$K$500,S10,$K$2:$K$500) -> 287.85 | S10: 505009 | T10: =R10*1.07 -> 307.9995
A11: 45417 | B11: 505005 | C11: A106 | D11: 4892210205896 | E11: =IFERROR(VLOOKUP(D11,ProductMaster!$A:$B,2,FALSE),"") -> 018521012 | F11: =IFERROR(VLOOKUP(D11,ProductMaster!$A:$C,3,FALSE),"") -> M18 FSAGV100XPDB-0X0 ASIA | G11: =IFERROR(VLOOKUP($D11,ProductMaster!$A:$O,4,FALSE),"") -> M18 FUEL GEN II 100MM VARIABLE SPEED BRAKING ANGLE GRINDER,P | H11: 1 | I11: =IFERROR(VLOOKUP(E11,ProductMaster!B:G,6,FALSE),0) -> 6624.2991 | J11: =ROUND(SUM(I11*7%),2) -> 463.7 | K11: =ROUND(SUM(H11*I11),2) -> 6624.3 | L11: 500 | M11: Credit Card | N11: Cat | O11: 0 | P11: Tax Invoice | Q11: =IF(B11=B10,Q10+1,1) -> 1 | R11: =SUMIF($B$2:$K$500,S11,$K$2:$K$500) -> 2783.18 | S11: 505010 | T11: =R11*1.07 -> 2978.0026
A12: 45417 | B12: 505006 | C12: Onetime | D12: 45242509171 | E12: =IFERROR(VLOOKUP(D12,ProductMaster!$A:$B,2,FALSE),"") -> 006067501 | F12: =IFERROR(VLOOKUP(D12,ProductMaster!$A:$C,3,FALSE),"") -> 48-22-8901 | G12: =IFERROR(VLOOKUP($D12,ProductMaster!$A:$O,4,FALSE),"") -> ถุงมือกันบาด Cut 1 Dipped Gloves - M | H12: 1 | I12: =IFERROR(VLOOKUP(E12,ProductMaster!B:G,6,FALSE),0) -> 157.00935 | J12: =ROUND(SUM(I12*7%),2) -> 10.99 | K12: =ROUND(SUM(H12*I12),2) -> 157.01 | M12: Cash | N12: Cat | O12: 0 | P12: No Tax Invoice | Q12: =IF(B12=B11,Q11+1,1) -> 1 | R12: =SUMIF($B$2:$K$500,S12,$K$2:$K$500) -> 82.24 | S12: 505011 | T12: =R12*1.07 -> 87.9968
A13: 45417 | B13: 505006 | C13: Onetime | D13: 45242268061 | E13: =IFERROR(VLOOKUP(D13,ProductMaster!$A:$B,2,FALSE),"") -> 129226207 | F13: =IFERROR(VLOOKUP(D13,ProductMaster!$A:$C,3,FALSE),"") -> 48-22-1905 | G13: =IFERROR(VLOOKUP($D13,ProductMaster!$A:$O,4,FALSE),"") -> ใบมีดอเนกประสงค์ 5ใบ | H13: 1 | I13: =IFERROR(VLOOKUP(E13,ProductMaster!B:G,6,FALSE),0) -> 82.242991 | J13: =ROUND(SUM(I13*7%),2) -> 5.76 | K13: =ROUND(SUM(H13*I13),2) -> 82.24 | M13: Cash | N13: Cat | O13: 0 | P13: No Tax Invoice | Q13: =IF(B13=B12,Q12+1,1) -> 2 | R13: =SUMIF($B$2:$K$500,S13,$K$2:$K$500) -> 1099.06 | S13: 505012 | T13: =R13*1.07 -> 1175.9942
A14: 45417 | B14: 505007 | C14: Onetime | D14: 45242509188 | E14: =IFERROR(VLOOKUP(D14,ProductMaster!$A:$B,2,FALSE),"") -> 006067601 | F14: =IFERROR(VLOOKUP(D14,ProductMaster!$A:$C,3,FALSE),"") -> 48-22-8902 | G14: =IFERROR(VLOOKUP($D14,ProductMaster!$A:$O,4,FALSE),"") -> ถุงมือกันบาด Cut 1 Dipped Gloves - L | H14: 1 | I14: =IFERROR(VLOOKUP(E14,ProductMaster!B:G,6,FALSE),0) -> 157.00935 | J14: =ROUND(SUM(I14*7%),2) -> 10.99 | K14: =ROUND(SUM(H14*I14),2) -> 157.01 | M14: Cash | N14: Cat | O14: 0 | P14: No Tax Invoice | Q14: =IF(B14=B13,Q13+1,1) -> 1 | R14: =SUMIF($B$2:$K$500,S14,$K$2:$K$500) -> 938.32 | S14: 505013 | T14: =R14*1.07 -> 1004.0024
A15: 45417 | B15: 505007 | C15: Onetime | D15: 45242573912 | E15: =IFERROR(VLOOKUP(D15,ProductMaster!$A:$B,2,FALSE),"") -> 006105507 | F15: =IFERROR(VLOOKUP(D15,ProductMaster!$A:$C,3,FALSE),"") -> 48-22-1505 | G15: =IFERROR(VLOOKUP($D15,ProductMaster!$A:$O,4,FALSE),"") -> มีดพับอเนกประสงค์ พร้อมช่องเก็บใบมีด รุ่น FASTBACK™ 6 IN 1 | H15: 1 | I15: =IFERROR(VLOOKUP(E15,ProductMaster!B:G,6,FALSE),0) -> 699.06542 | J15: =ROUND(SUM(I15*7%),2) -> 48.93 | K15: =ROUND(SUM(H15*I15),2) -> 699.07 | M15: Cash | N15: Cat | O15: 0 | P15: No Tax Invoice | Q15: =IF(B15=B14,Q14+1,1) -> 2 | R15: =SUMIF($B$2:$K$500,S15,$K$2:$K$500) -> 4287.85 | S15: 505014 | T15: =R15*1.07 -> 4587.9995
A16: 45417 | B16: 505008 | C16: Onetime | D16: 45242509287 | E16: =IFERROR(VLOOKUP(D16,ProductMaster!$A:$B,2,FALSE),"") -> 006068601 | F16: =IFERROR(VLOOKUP(D16,ProductMaster!$A:$C,3,FALSE),"") -> 48-22-8952 | G16: =IFERROR(VLOOKUP($D16,ProductMaster!$A:$O,4,FALSE),"") -> ถุงมือกันบาด Cut 5 Dipped Gloves - L | H16: 1 | I16: =IFERROR(VLOOKUP(E16,ProductMaster!B:G,6,FALSE),0) -> 558.8785 | J16: =ROUND(SUM(I16*7%),2) -> 39.12 | K16: =ROUND(SUM(H16*I16),2) -> 558.88 | M16: Transfer | N16: Cat | O16: 0 | P16: No Tax Invoice | Q16: =IF(B16=B15,Q15+1,1) -> 1 | R16: =SUMIF($B$2:$K$500,S16,$K$2:$K$500) -> 829.91 | S16: 505015 | T16: =R16*1.07 -> 888.0037
A17: 45417 | B17: 505008 | C17: Onetime | D17: 45242509188 | E17: =IFERROR(VLOOKUP(D17,ProductMaster!$A:$B,2,FALSE),"") -> 006067601 | F17: =IFERROR(VLOOKUP(D17,ProductMaster!$A:$C,3,FALSE),"") -> 48-22-8902 | G17: =IFERROR(VLOOKUP($D17,ProductMaster!$A:$O,4,FALSE),"") -> ถุงมือกันบาด Cut 1 Dipped Gloves - L | H17: 1 | I17: =IFERROR(VLOOKUP(E17,ProductMaster!B:G,6,FALSE),0) -> 157.00935 | J17: =ROUND(SUM(I17*7%),2) -> 10.99 | K17: =ROUND(SUM(H17*I17),2) -> 157.01 | M17: Transfer | N17: Cat | O17: 0 | P17: No Tax Invoice | Q17: =IF(B17=B16,Q16+1,1) -> 2 | R17: =SUMIF($B$2:$K$500,S17,$K$2:$K$500) -> 25403.74 | S17: 505016 | T17: =R17*1.07 -> 27182.002
A18: 45417 | B18: 505009 | C18: Onetime | D18: 45242502691 | E18: =IFERROR(VLOOKUP(D18,ProductMaster!$A:$B,2,FALSE),"") -> 076002284 | F18: =IFERROR(VLOOKUP(D18,ProductMaster!$A:$C,3,FALSE),"") -> 48-22-7816 | G18: =IFERROR(VLOOKUP($D18,ProductMaster!$A:$O,4,FALSE),"") -> ตลับเมตรรุ่น RED 5 เมตร/16 ฟุต | H18: 1 | I18: =IFERROR(VLOOKUP(E18,ProductMaster!B:G,6,FALSE),0) -> 287.85047 | J18: =ROUND(SUM(I18*7%),2) -> 20.15 | K18: =ROUND(SUM(H18*I18),2) -> 287.85 | M18: Transfer | N18: Cat | O18: 0 | P18: No Tax Invoice | Q18: =IF(B18=B17,Q17+1,1) -> 1 | R18: =SUMIF($B$2:$K$500,S18,$K$2:$K$500) -> 818.7 | S18: 505017 | T18: =R18*1.07 -> 876.009
A19: 45417 | B19: 505010 | C19: Onetime | D19: 4892210220677-BF | E19: =IFERROR(VLOOKUP(D19,ProductMaster!$A:$B,2,FALSE),"") -> 001997033-(BF) | F19: =IFERROR(VLOOKUP(D19,ProductMaster!$A:$C,3,FALSE),"") -> M12HB5-(BF) | G19: =IFERROR(VLOOKUP($D19,ProductMaster!$A:$O,4,FALSE),"") -> แบตเตอรี่ 12 โวลต์ 5.0 แอมป์อาว HIGH OUTPUT | H19: 1 | I19: =IFERROR(VLOOKUP(E19,ProductMaster!B:G,6,FALSE),0) -> 1485.9813 | J19: =ROUND(SUM(I19*7%),2) -> 104.02 | K19: =ROUND(SUM(H19*I19),2) -> 1485.98 | M19: Transfer | N19: Cat | O19: 0 | P19: No Tax Invoice | Q19: =IF(B19=B18,Q18+1,1) -> 1 | R19: =SUMIF($B$2:$K$500,S19,$K$2:$K$500) -> 633.64 | S19: 505018 | T19: =R19*1.07 -> 677.9948
A20: 45417 | B20: 505010 | C20: Onetime | D20: 45242505326 | E20: =IFERROR(VLOOKUP(D20,ProductMaster!$A:$B,2,FALSE),"") -> 129305053 | F20: =IFERROR(VLOOKUP(D20,ProductMaster!$A:$C,3,FALSE),"") -> 48-22-8435 | G20: =IFERROR(VLOOKUP($D20,ProductMaster!$A:$O,4,FALSE),"") -> กล่องอุปกรณ์ช่าง PACKOUT Compact Organizer | H20: 1 | I20: =IFERROR(VLOOKUP(E20,ProductMaster!B:G,6,FALSE),0) -> 1297.1963 | J20: =ROUND(SUM(I20*7%),2) -> 90.8 | K20: =ROUND(SUM(H20*I20),2) -> 1297.2 | M20: Transfer | N20: Cat | O20: 0 | P20: No Tax Invoice | Q20: =IF(B20=B19,Q19+1,1) -> 2 | R20: =SUMIF($B$2:$K$500,S20,$K$2:$K$500) -> 60564.5 | S20: 505019 | T20: =R20*1.07 -> 64804.015
A21: 45417 | B21: 505011 | C21: A041 | D21: 45242268061 | E21: =IFERROR(VLOOKUP(D21,ProductMaster!$A:$B,2,FALSE),"") -> 129226207 | F21: =IFERROR(VLOOKUP(D21,ProductMaster!$A:$C,3,FALSE),"") -> 48-22-1905 | G21: =IFERROR(VLOOKUP($D21,ProductMaster!$A:$O,4,FALSE),"") -> ใบมีดอเนกประสงค์ 5ใบ | H21: 1 | I21: =IFERROR(VLOOKUP(E21,ProductMaster!B:G,6,FALSE),0) -> 82.242991 | J21: =ROUND(SUM(I21*7%),2) -> 5.76 | K21: =ROUND(SUM(H21*I21),2) -> 82.24 | M21: Transfer | N21: Cat | O21: 0 | P21: Tax Invoice | Q21: =IF(B21=B20,Q20+1,1) -> 1 | R21: =SUMIF($B$2:$K$500,S21,$K$2:$K$500) -> 8676.63 | S21: 505020 | T21: =R21*1.07 -> 9283.9941 | U21: โอนรวมกับบิล 0505002 ยอด 2,288
A22: 45417 | B22: 505012 | C22: A108 | D22: 45242645701 | E22: =IFERROR(VLOOKUP(D22,ProductMaster!$A:$B,2,FALSE),"") -> 006157301 | F22: =IFERROR(VLOOKUP(D22,ProductMaster!$A:$C,3,FALSE),"") -> 48-22-2184 | G22: =IFERROR(VLOOKUP($D22,ProductMaster!$A:$O,4,FALSE),"") -> ประแจหกเหลี่ยมหัวทอร์คแบบพับเก็บ 8 ชิ้น | H22: 1 | I22: =IFERROR(VLOOKUP(E22,ProductMaster!B:G,6,FALSE),0) -> 549.53271 | J22: =ROUND(SUM(I22*7%),2) -> 38.47 | K22: =ROUND(SUM(H22*I22),2) -> 549.53 | M22: Transfer | N22: Cat | O22: 0 | P22: Tax Invoice | Q22: =IF(B22=B21,Q21+1,1) -> 1 | R22: =SUMIF($B$2:$K$500,S22,$K$2:$K$500) -> 633.64 | S22: 505021 | T22: =R22*1.07 -> 677.9948
A23: 45417 | B23: 505012 | C23: A108 | D23: 45242630585 | E23: =IFERROR(VLOOKUP(D23,ProductMaster!$A:$B,2,FALSE),"") -> 006138701 | F23: =IFERROR(VLOOKUP(D23,ProductMaster!$A:$C,3,FALSE),"") -> 48-22-2182 | G23: =IFERROR(VLOOKUP($D23,ProductMaster!$A:$O,4,FALSE),"") -> ประแจหกเหลี่ยมแบบพับเก็บ 8 ชิ้น | H23: 1 | I23: =IFERROR(VLOOKUP(E23,ProductMaster!B:G,6,FALSE),0) -> 549.53271 | J23: =ROUND(SUM(I23*7%),2) -> 38.47 | K23: =ROUND(SUM(H23*I23),2) -> 549.53 | M23: Transfer | N23: Cat | O23: 0 | P23: Tax Invoice | Q23: =IF(B23=B22,Q22+1,1) -> 2 | R23: =SUMIF($B$2:$K$500,S23,$K$2:$K$500) -> 633.64 | S23: 505022 | T23: =R23*1.07 -> 677.9948
A24: 45417 | B24: 505013 | C24: Onetime | D24: 45242534395 | E24: =IFERROR(VLOOKUP(D24,ProductMaster!$A:$B,2,FALSE),"") -> 006084404 | F24: =IFERROR(VLOOKUP(D24,ProductMaster!$A:$C,3,FALSE),"") -> 48-22-1906 | G24: =IFERROR(VLOOKUP($D24,ProductMaster!$A:$O,4,FALSE),"") -> มีดพับคอมแพ็คอเนกประสงค์ | H24: 1 | I24: =IFERROR(VLOOKUP(E24,ProductMaster!B:G,6,FALSE),0) -> 446.72897 | J24: =ROUND(SUM(I24*7%),2) -> 31.27 | K24: =ROUND(SUM(H24*I24),2) -> 446.73 | M24: Cash | N24: Cat | O24: 0 | P24: No Tax Invoice | Q24: =IF(B24=B23,Q23+1,1) -> 1 | R24: =SUMIF($B$2:$K$500,S24,$K$2:$K$500) -> 2390.65 | S24: 505023 | T24: =R24*1.07 -> 2557.9955
A25: 45417 | B25: 505013 | C25: Onetime | D25: 45242268061 | E25: =IFERROR(VLOOKUP(D25,ProductMaster!$A:$B,2,FALSE),"") -> 129226207 | F25: =IFERROR(VLOOKUP(D25,ProductMaster!$A:$C,3,FALSE),"") -> 48-22-1905 | G25: =IFERROR(VLOOKUP($D25,ProductMaster!$A:$O,4,FALSE),"") -> ใบมีดอเนกประสงค์ 5ใบ | H25: 1 | I25: =IFERROR(VLOOKUP(E25,ProductMaster!B:G,6,FALSE),0) -> 82.242991 | J25: =ROUND(SUM(I25*7%),2) -> 5.76 | K25: =ROUND(SUM(H25*I25),2) -> 82.24 | M25: Cash | N25: Cat | O25: 0 | P25: No Tax Invoice | Q25: =IF(B25=B24,Q24+1,1) -> 2 | R25: =SUMIF($B$2:$K$500,S25,$K$2:$K$500) -> 29555.15 | S25: 505024 | T25: =R25*1.07 -> 31624.011
A26: 45417 | B26: 505013 | C26: Onetime | D26: 45242082834 | E26: =IFERROR(VLOOKUP(D26,ProductMaster!$A:$B,2,FALSE),"") -> 129221226 | F26: =IFERROR(VLOOKUP(D26,ProductMaster!$A:$C,3,FALSE),"") -> 48-00-5182 | G26: =IFERROR(VLOOKUP($D26,ProductMaster!$A:$O,4,FALSE),"") -> ใบเลื่อยซอว์ซอลตัดเหล็ก 6" Thin Kerf 14 TPI (5 ใบ) | H26: 1 | I26: =IFERROR(VLOOKUP(E26,ProductMaster!B:G,6,FALSE),0) -> 409.34579 | J26: =ROUND(SUM(I26*7%),2) -> 28.65 | K26: =ROUND(SUM(H26*I26),2) -> 409.35 | M26: Cash | N26: Cat | O26: 0 | P26: No Tax Invoice | Q26: =IF(B26=B25,Q25+1,1) -> 3 | R26: =SUMIF($B$2:$K$500,S26,$K$2:$K$500) -> 6080.38 | S26: 505025 | T26: =R26*1.07 -> 6506.0066
A27: 45417 | B27: 505014 | C27: Onetime | D27: 45242531684 | E27: =IFERROR(VLOOKUP(D27,ProductMaster!$A:$B,2,FALSE),"") -> 006082201 | F27: =IFERROR(VLOOKUP(D27,ProductMaster!$A:$C,3,FALSE),"") -> 48-22-8301 | G27: =IFERROR(VLOOKUP($D27,ProductMaster!$A:$O,4,FALSE),"") -> เป้สะพายหลังใส่เครื่องมือ PACKOUT Backpack | H27: 1 | I27: =IFERROR(VLOOKUP(E27,ProductMaster!B:G,6,FALSE),0) -> 4287.8505 | J27: =ROUND(SUM(I27*7%),2) -> 300.15 | K27: =ROUND(SUM(H27*I27),2) -> 4287.85 | M27: Credit Card | N27: Cat | O27: 0 | P27: No Tax Invoice | Q27: =IF(B27=B26,Q26+1,1) -> 1 | R27: =SUMIF($B$2:$K$500,S27,$K$2:$K$500) -> 17652.34 | S27: 505026 | T27: =R27*1.07 -> 18888.004
A28: 45417 | B28: 505015 | C28: Onetime | D28: 45242638796 | E28: =IFERROR(VLOOKUP(D28,ProductMaster!$A:$B,2,FALSE),"") -> 006143201 | F28: =IFERROR(VLOOKUP(D28,ProductMaster!$A:$C,3,FALSE),"") -> 48-22-0307 | G28: =IFERROR(VLOOKUP($D28,ProductMaster!$A:$O,4,FALSE),"") -> เลื่อยอเนกประสงค์แบบพับ | H28: 1 | I28: =IFERROR(VLOOKUP(E28,ProductMaster!B:G,6,FALSE),0) -> 829.90654 | J28: =ROUND(SUM(I28*7%),2) -> 58.09 | K28: =ROUND(SUM(H28*I28),2) -> 829.91 | M28: Transfer | N28: Cat | O28: 0 | P28: No Tax Invoice | Q28: =IF(B28=B27,Q27+1,1) -> 1 | R28: =SUMIF($B$2:$K$500,S28,$K$2:$K$500) -> 17652.34 | S28: 505027 | T28: =R28*1.07 -> 18888.004
A29: 45417 | B29: 505016 | C29: Onetime | D29: 4892210196293 | E29: =IFERROR(VLOOKUP(D29,ProductMaster!$A:$B,2,FALSE),"") -> 018508015 | F29: =IFERROR(VLOOKUP(D29,ProductMaster!$A:$C,3,FALSE),"") -> M18 FMTIW2F12-0X0 ASIA | G29: =IFERROR(VLOOKUP($D29,ProductMaster!$A:$O,4,FALSE),"") -> M18 FUEL บล็อกกระแทกไร้สาย 1/2" มิดทอร์ค | H29: 1 | I29: =IFERROR(VLOOKUP(E29,ProductMaster!B:G,6,FALSE),0) -> 7465.4206 | J29: =ROUND(SUM(I29*7%),2) -> 522.58 | K29: =ROUND(SUM(H29*I29),2) -> 7465.42 | M29: Credit Card | N29: Cat | O29: 0 | P29: No Tax Invoice | Q29: =IF(B29=B28,Q28+1,1) -> 1 | R29: =SUMIF($B$2:$K$500,S29,$K$2:$K$500) -> 699.07 | S29: 505028 | T29: =R29*1.07 -> 748.0049
A30: 45417 | B30: 505016 | C30: Onetime | D30: 4892210222107 | E30: =IFERROR(VLOOKUP(D30,ProductMaster!$A:$B,2,FALSE),"") -> 018677003 | F30: =IFERROR(VLOOKUP(D30,ProductMaster!$A:$C,3,FALSE),"") -> M18 FHS20-0B0 ASIA | G30: =IFERROR(VLOOKUP($D30,ProductMaster!$A:$O,4,FALSE),"") -> M18 FUEL เลื่อยโซ่ 8” | H30: 1 | I30: =IFERROR(VLOOKUP(E30,ProductMaster!B:G,6,FALSE),0) -> 9334.5794 | J30: =ROUND(SUM(I30*7%),2) -> 653.42 | K30: =ROUND(SUM(H30*I30),2) -> 9334.58 | M30: Credit Card | N30: Cat | O30: 0 | P30: No Tax Invoice | Q30: =IF(B30=B29,Q29+1,1) -> 2 | R30: =SUMIF($B$2:$K$500,S30,$K$2:$K$500) -> 586.92 | S30: 505029 | T30: =R30*1.07 -> 628.0044
A31: 45417 | B31: 505016 | C31: Onetime | D31: 4892210180988-BF | E31: =IFERROR(VLOOKUP(D31,ProductMaster!$A:$B,2,FALSE),"") -> 001998236DG9-(BF) | F31: =IFERROR(VLOOKUP(D31,ProductMaster!$A:$C,3,FALSE),"") -> M18HB8ASIA-(BF) | G31: =IFERROR(VLOOKUP($D31,ProductMaster!$A:$O,4,FALSE),"") -> แบตเตอรี่ 18 โวลต์ 8.0 แอมป์อาว HIGH OUTPUT | H31: 1 | I31: =IFERROR(VLOOKUP(E31,ProductMaster!B:G,6,FALSE),0) -> 3542.0561 | J31: =ROUND(SUM(I31*7%),2) -> 247.94 | K31: =ROUND(SUM(H31*I31),2) -> 3542.06 | L31: 500 | M31: Credit Card | N31: Cat | O31: 0 | P31: No Tax Invoice | Q31: =IF(B31=B30,Q30+1,1) -> 3 | R31: =SUMIF($B$2:$K$500,S31,$K$2:$K$500) -> 10175.7 | S31: 505030 | T31: =R31*1.07 -> 10887.999
A32: 45417 | B32: 505016 | C32: Onetime | D32: 4892210141347-BF | E32: =IFERROR(VLOOKUP(D32,ProductMaster!$A:$B,2,FALSE),"") -> 001998238-(BF) | F32: =IFERROR(VLOOKUP(D32,ProductMaster!$A:$C,3,FALSE),"") -> M18B5ASIA-(BF) | G32: =IFERROR(VLOOKUP($D32,ProductMaster!$A:$O,4,FALSE),"") -> แบตเตอรี่ 18 โวลต์ 5.0 แอมป์อาว | H32: 1 | I32: =IFERROR(VLOOKUP(E32,ProductMaster!B:G,6,FALSE),0) -> 1859.8131 | J32: =ROUND(SUM(I32*7%),2) -> 130.19 | K32: =ROUND(SUM(H32*I32),2) -> 1859.81 | M32: Credit Card | N32: Cat | O32: 0 | P32: No Tax Invoice | Q32: =IF(B32=B31,Q31+1,1) -> 4 | R32: =SUMIF($B$2:$K$500,S32,$K$2:$K$500) -> 287.85 | S32: 505031 | T32: =R32*1.07 -> 307.9995
A33: 45417 | B33: 505016 | C33: Onetime | D33: 4892210139313-BF | E33: =IFERROR(VLOOKUP(D33,ProductMaster!$A:$B,2,FALSE),"") -> 001997014-(BF) | F33: =IFERROR(VLOOKUP(D33,ProductMaster!$A:$C,3,FALSE),"") -> M12-18FCSA-(BF) | G33: =IFERROR(VLOOKUP($D33,ProductMaster!$A:$O,4,FALSE),"") -> แท่นชาร์จแบตเตอรี่ 12-18 โวลต์ แบบชาร์จเร็ว | H33: 1 | I33: =IFERROR(VLOOKUP(E33,ProductMaster!B:G,6,FALSE),0) -> 1766.3551 | J33: =ROUND(SUM(I33*7%),2) -> 123.64 | K33: =ROUND(SUM(H33*I33),2) -> 1766.36 | M33: Credit Card | N33: Cat | O33: 0 | P33: No Tax Invoice | Q33: =IF(B33=B32,Q32+1,1) -> 5 | R33: =SUMIF($B$2:$K$500,S33,$K$2:$K$500) -> 633.64 | S33: 505032 | T33: =R33*1.07 -> 677.9948
A34: 45417 | B34: 505016 | C34: Onetime | D34: 4058546404611 | E34: =IFERROR(VLOOKUP(D34,ProductMaster!$A:$B,2,FALSE),"") -> 001998668 | F34: =IFERROR(VLOOKUP(D34,ProductMaster!$A:$C,3,FALSE),"") -> 4932480176 | G34: =IFERROR(VLOOKUP($D34,ProductMaster!$A:$O,4,FALSE),"") -> โซ่เลื่อย 8" สำหรับ M18 FHS | H34: 1 | I34: =IFERROR(VLOOKUP(E34,ProductMaster!B:G,6,FALSE),0) -> 801.86916 | J34: =ROUND(SUM(I34*7%),2) -> 56.13 | K34: =ROUND(SUM(H34*I34),2) -> 801.87 | M34: Credit Card | N34: Cat | O34: 0 | P34: No Tax Invoice | Q34: =IF(B34=B33,Q33+1,1) -> 6 | R34: =SUMIF($B$2:$K$500,S34,$K$2:$K$500) -> 18706.55 | S34: 505033 | T34: =R34*1.07 -> 20016.009
A35: 45417 | B35: 505016 | C35: Onetime | D35: 4058546348144 | E35: =IFERROR(VLOOKUP(D35,ProductMaster!$A:$B,2,FALSE),"") -> 006126701 | F35: =IFERROR(VLOOKUP(D35,ProductMaster!$A:$C,3,FALSE),"") -> 4932478621 | G35: =IFERROR(VLOOKUP($D35,ProductMaster!$A:$O,4,FALSE),"") -> ชุดประแจหกเหลี่ยม 9 ชิ้น | H35: 1 | I35: =IFERROR(VLOOKUP(E35,ProductMaster!B:G,6,FALSE),0) -> 633.64486 | J35: =ROUND(SUM(I35*7%),2) -> 44.36 | K35: =ROUND(SUM(H35*I35),2) -> 633.64 | M35: Credit Card | N35: Cat | O35: 0 | P35: No Tax Invoice | Q35: =IF(B35=B34,Q34+1,1) -> 7 | R35: =SUMIF($B$2:$K$500,S35,$K$2:$K$500) -> 9771.96 | S35: 505034 | T35: =R35*1.07 -> 10455.997
A36: 45417 | B36: 505017 | C36: Onetime | D36: 45242475216 | E36: =IFERROR(VLOOKUP(D36,ProductMaster!$A:$B,2,FALSE),"") -> 008051202 | F36: =IFERROR(VLOOKUP(D36,ProductMaster!$A:$C,3,FALSE),"") -> 48-32-4361 | G36: =IFERROR(VLOOKUP($D36,ProductMaster!$A:$O,4,FALSE),"") -> ดอกไขควง PH2-65 มม. Double Ended (10 ดอก) | H36: 1 | I36: =IFERROR(VLOOKUP(E36,ProductMaster!B:G,6,FALSE),0) -> 409.34579 | J36: =ROUND(SUM(I36*7%),2) -> 28.65 | K36: =ROUND(SUM(H36*I36),2) -> 409.35 | M36: Transfer | N36: Cat | O36: 0 | P36: No Tax Invoice | Q36: =IF(B36=B35,Q35+1,1) -> 1 | R36: =SUMIF($B$2:$K$500,S36,$K$2:$K$500) -> 409.35 | S36: 505035 | T36: =R36*1.07 -> 438.0045
A37: 45417 | B37: 505017 | C37: Onetime | D37: 45242475216 | E37: =IFERROR(VLOOKUP(D37,ProductMaster!$A:$B,2,FALSE),"") -> 008051202 | F37: =IFERROR(VLOOKUP(D37,ProductMaster!$A:$C,3,FALSE),"") -> 48-32-4361 | G37: =IFERROR(VLOOKUP($D37,ProductMaster!$A:$O,4,FALSE),"") -> ดอกไขควง PH2-65 มม. Double Ended (10 ดอก) | H37: 1 | I37: =IFERROR(VLOOKUP(E37,ProductMaster!B:G,6,FALSE),0) -> 409.34579 | J37: =ROUND(SUM(I37*7%),2) -> 28.65 | K37: =ROUND(SUM(H37*I37),2) -> 409.35 | M37: Transfer | N37: Cat | O37: 0 | P37: No Tax Invoice | Q37: =IF(B37=B36,Q36+1,1) -> 2 | R37: =SUMIF($B$2:$K$500,S37,$K$2:$K$500) -> 304.67 | S37: 505036 | T37: =R37*1.07 -> 325.9969
A38: 45417 | B38: 505018 | C38: Onetime | D38: 4892210183637 | E38: =IFERROR(VLOOKUP(D38,ProductMaster!$A:$B,2,FALSE),"") -> 076002492 | F38: =IFERROR(VLOOKUP(D38,ProductMaster!$A:$C,3,FALSE),"") -> 48-22-0616 | G38: =IFERROR(VLOOKUP($D38,ProductMaster!$A:$O,4,FALSE),"") -> ตลับเมตรรุ่น COMPACT MAGNETIC 5 เมตร/16 ฟุต | H38: 1 | I38: =IFERROR(VLOOKUP(E38,ProductMaster!B:G,6,FALSE),0) -> 633.64486 | J38: =ROUND(SUM(I38*7%),2) -> 44.36 | K38: =ROUND(SUM(H38*I38),2) -> 633.64 | M38: Transfer | N38: Cat | O38: 0 | P38: No Tax Invoice | Q38: =IF(B38=B37,Q37+1,1) -> 1 | R38: =SUMIF($B$2:$K$500,S38,$K$2:$K$500) -> 2138.32 | S38: 505037 | T38: =R38*1.07 -> 2288.0024
A39: 45417 | B39: 505019 | C39: A109 | D39: 1318423879118 | E39: =IFERROR(VLOOKUP(D39,ProductMaster!$A:$B,2,FALSE),"") -> 059600345 | F39: =IFERROR(VLOOKUP(D39,ProductMaster!$A:$C,3,FALSE),"") -> M18 BPP2U-801BLR SA | G39: =IFERROR(VLOOKUP($D39,ProductMaster!$A:$O,4,FALSE),"") -> M18 Vacuum Combo | H39: 1 | I39: =IFERROR(VLOOKUP(E39,ProductMaster!B:G,6,FALSE),0) -> 13914.019 | J39: =ROUND(SUM(I39*7%),2) -> 973.98 | K39: =ROUND(SUM(H39*I39),2) -> 13914.02 | M39: Online (Kerry) | N39: Cat | O39: 0 | P39: No Tax Invoice | Q39: =IF(B39=B38,Q38+1,1) -> 1 | R39: =SUMIF($B$2:$K$500,S39,$K$2:$K$500) -> 418.69 | S39: 505038 | T39: =R39*1.07 -> 447.9983
A40: 45417 | B40: 505019 | C40: A109 | D40: 4892210183927 | E40: =IFERROR(VLOOKUP(D40,ProductMaster!$A:$B,2,FALSE),"") -> 018350011 | F40: =IFERROR(VLOOKUP(D40,ProductMaster!$A:$C,3,FALSE),"") -> M18 FOPH-0 ASIA | G40: =IFERROR(VLOOKUP($D40,ProductMaster!$A:$O,4,FALSE),"") -> เครื่องมืองานสวนอเนกประสงค์ไร้สาย 18 โวลต์ ระบบ QUIK-LOK (เครื่องเปล่า) | H40: 1 | I40: =IFERROR(VLOOKUP(E40,ProductMaster!B:G,6,FALSE),0) -> 7371.9626 | J40: =ROUND(SUM(I40*7%),2) -> 516.04 | K40: =ROUND(SUM(H40*I40),2) -> 7371.96 | M40: Online (Kerry) | N40: Cat | O40: 0 | P40: No Tax Invoice | Q40: =IF(B40=B39,Q39+1,1) -> 2 | R40: =SUMIF($B$2:$K$500,S40,$K$2:$K$500) -> 9809.34 | S40: 505039 | T40: =R40*1.07 -> 10495.994
A41: 45417 | B41: 505019 | C41: A109 | D41: 4892210183897 | E41: =IFERROR(VLOOKUP(D41,ProductMaster!$A:$B,2,FALSE),"") -> 018376004 | F41: =IFERROR(VLOOKUP(D41,ProductMaster!$A:$C,3,FALSE),"") -> M18 FOPH-HTA ASIA | G41: =IFERROR(VLOOKUP($D41,ProductMaster!$A:$O,4,FALSE),"") -> หัวต่อตัดแต่งพุ่ม | H41: 1 | I41: =IFERROR(VLOOKUP(E41,ProductMaster!B:G,6,FALSE),0) -> 5876.6355 | J41: =ROUND(SUM(I41*7%),2) -> 411.36 | K41: =ROUND(SUM(H41*I41),2) -> 5876.64 | M41: Online (Kerry) | N41: Cat | O41: 0 | P41: No Tax Invoice | Q41: =IF(B41=B40,Q40+1,1) -> 3 | R41: =SUMIF($B$2:$K$500,S41,$K$2:$K$500) -> 642.99 | S41: 505040 | T41: =R41*1.07 -> 687.9993
A42: 45417 | B42: 505019 | C42: A109 | D42: 4892210211262 | E42: =IFERROR(VLOOKUP(D42,ProductMaster!$A:$B,2,FALSE),"") -> 018331015 | F42: =IFERROR(VLOOKUP(D42,ProductMaster!$A:$C,3,FALSE),"") -> L4 FFL-301 ASIA | G42: =IFERROR(VLOOKUP($D42,ProductMaster!$A:$O,4,FALSE),"") -> ไฟส่องทำงาน แบบบานพับ | H42: 1 | I42: =IFERROR(VLOOKUP(E42,ProductMaster!B:G,6,FALSE),0) -> 2699.0654 | J42: =ROUND(SUM(I42*7%),2) -> 188.93 | K42: =ROUND(SUM(H42*I42),2) -> 2699.07 | M42: Online (Kerry) | N42: Cat | O42: 0 | P42: No Tax Invoice | Q42: =IF(B42=B41,Q41+1,1) -> 4 | R42: =SUMIF($B$2:$K$500,S42,$K$2:$K$500) -> 69181.3 | S42: 505041 | T42: =R42*1.07 -> 74023.991
A43: 45417 | B43: 505019 | C43: A109 | D43: 4892210141347-BF | E43: =IFERROR(VLOOKUP(D43,ProductMaster!$A:$B,2,FALSE),"") -> 001998238-(BF) | F43: =IFERROR(VLOOKUP(D43,ProductMaster!$A:$C,3,FALSE),"") -> M18B5ASIA-(BF) | G43: =IFERROR(VLOOKUP($D43,ProductMaster!$A:$O,4,FALSE),"") -> แบตเตอรี่ 18 โวลต์ 5.0 แอมป์อาว | H43: 1 | I43: =IFERROR(VLOOKUP(E43,ProductMaster!B:G,6,FALSE),0) -> 1859.8131 | J43: =ROUND(SUM(I43*7%),2) -> 130.19 | K43: =ROUND(SUM(H43*I43),2) -> 1859.81 | M43: Online (Kerry) | N43: Cat | O43: 0 | P43: No Tax Invoice | Q43: =IF(B43=B42,Q42+1,1) -> 5 | R43: =SUMIF($B$2:$K$500,S43,$K$2:$K$500) -> 7151.41 | S43: 505042 | T43: =R43*1.07 -> 7652.0087
A44: 45417 | B44: 505019 | C44: A109 | D44: 4892210233608 | E44: =IFERROR(VLOOKUP(D44,ProductMaster!$A:$B,2,FALSE),"") -> 018689005 | F44: =IFERROR(VLOOKUP(D44,ProductMaster!$A:$C,3,FALSE),"") -> M18 FVP50-0 ASIA | G44: =IFERROR(VLOOKUP($D44,ProductMaster!$A:$O,4,FALSE),"") -> M18 ปั้มสูญญากาศ | H44: 1 | I44: =IFERROR(VLOOKUP(E44,ProductMaster!B:G,6,FALSE),0) -> 17652.336 | J44: =ROUND(SUM(I44*7%),2) -> 1235.66 | K44: =ROUND(SUM(H44*I44),2) -> 17652.34 | M44: Online (Kerry) | N44: Cat | O44: 0 | P44: No Tax Invoice | Q44: =IF(B44=B43,Q43+1,1) -> 6 | R44: =SUMIF($B$2:$K$500,S44,$K$2:$K$500) -> 1585.04 | S44: 505043 | T44: =R44*1.07 -> 1695.9928
A45: 45417 | B45: 505019 | C45: A109 | D45: 4892210172082-BF | E45: =IFERROR(VLOOKUP(D45,ProductMaster!$A:$B,2,FALSE),"") -> 001998237DG9-(BF) | F45: =IFERROR(VLOOKUP(D45,ProductMaster!$A:$C,3,FALSE),"") -> M18HB12ASIA-(BF) | G45: =IFERROR(VLOOKUP($D45,ProductMaster!$A:$O,4,FALSE),"") -> แบตเตอรี่ 18 โวลต์ 12.0 แอมป์อาว HIGH OUTPUT | H45: 1 | I45: =IFERROR(VLOOKUP(E45,ProductMaster!B:G,6,FALSE),0) -> 5224.2991 | J45: =ROUND(SUM(I45*7%),2) -> 365.7 | K45: =ROUND(SUM(H45*I45),2) -> 5224.3 | M45: Online (Kerry) | N45: Cat | O45: 0 | P45: No Tax Invoice | Q45: =IF(B45=B44,Q44+1,1) -> 7 | R45: =SUMIF($B$2:$K$500,S45,$K$2:$K$500) -> 3779.44 | S45: 505044 | T45: =R45*1.07 -> 4044.0008
A46: 45417 | B46: 505019 | C46: A109 | D46: 45242195039 | E46: =IFERROR(VLOOKUP(D46,ProductMaster!$A:$B,2,FALSE),"") -> 129225591 | F46: =IFERROR(VLOOKUP(D46,ProductMaster!$A:$C,3,FALSE),"") -> 48-32-5030 | G46: =IFERROR(VLOOKUP($D46,ProductMaster!$A:$O,4,FALSE),"") -> อะแดปเตอร์หัวบล็อก 1/4" แกนหกเหลี่ยม | H46: 2 | I46: =IFERROR(VLOOKUP(E46,ProductMaster!B:G,6,FALSE),0) -> 82.242991 | J46: =ROUND(SUM(I46*7%),2) -> 5.76 | K46: =ROUND(SUM(H46*I46),2) -> 164.49 | M46: Online (Kerry) | N46: Cat | O46: 0 | P46: No Tax Invoice | Q46: =IF(B46=B45,Q45+1,1) -> 8 | R46: =SUMIF($B$2:$K$500,S46,$K$2:$K$500) -> 8917.75 | S46: 505045 | T46: =R46*1.07 -> 9541.9925 | W46: =+V46-V45 -> 0
A47: 45417 | B47: 505019 | C47: A109 | D47: 45242268061 | E47: =IFERROR(VLOOKUP(D47,ProductMaster!$A:$B,2,FALSE),"") -> 129226207 | F47: =IFERROR(VLOOKUP(D47,ProductMaster!$A:$C,3,FALSE),"") -> 48-22-1905 | G47: =IFERROR(VLOOKUP($D47,ProductMaster!$A:$O,4,FALSE),"") -> ใบมีดอเนกประสงค์ 5ใบ | H47: 1 | I47: =IFERROR(VLOOKUP(E47,ProductMaster!B:G,6,FALSE),0) -> 82.242991 | J47: =ROUND(SUM(I47*7%),2) -> 5.76 | K47: =ROUND(SUM(H47*I47),2) -> 82.24 | M47: Online (Kerry) | N47: Cat | O47: 0 | P47: No Tax Invoice | Q47: =IF(B47=B46,Q46+1,1) -> 9 | R47: =SUMIF($B$2:$K$500,S47,$K$2:$K$500) -> 353.27 | S47: 505046 | T47: =R47*1.07 -> 377.9989
A48: 45417 | B48: 505019 | C48: A109 | D48: 45242509171 | E48: =IFERROR(VLOOKUP(D48,ProductMaster!$A:$B,2,FALSE),"") -> 006067501 | F48: =IFERROR(VLOOKUP(D48,ProductMaster!$A:$C,3,FALSE),"") -> 48-22-8901 | G48: =IFERROR(VLOOKUP($D48,ProductMaster!$A:$O,4,FALSE),"") -> ถุงมือกันบาด Cut 1 Dipped Gloves - M | H48: 32 | I48: =IFERROR(VLOOKUP(E48,ProductMaster!B:G,6,FALSE),0) -> 157.00935 | J48: =ROUND(SUM(I48*7%),2) -> 10.99 | K48: =ROUND(SUM(H48*I48),2) -> 5024.3 | M48: Online (Kerry) | N48: Cat | O48: 0 | P48: No Tax Invoice | Q48: =IF(B48=B47,Q47+1,1) -> 10 | R48: =SUMIF($B$2:$K$500,S48,$K$2:$K$500) -> 474.77 | S48: 505047 | T48: =R48*1.07 -> 508.0039
A49: 45417 | B49: 505019 | C49: A109 | D49: 45242325276 | E49: =IFERROR(VLOOKUP(D49,ProductMaster!$A:$B,2,FALSE),"") -> 006033705 | F49: =IFERROR(VLOOKUP(D49,ProductMaster!$A:$C,3,FALSE),"") -> 48-22-3420 | G49: =IFERROR(VLOOKUP($D49,ProductMaster!$A:$O,4,FALSE),"") -> คีมล็อคปากโค้ง 10" | H49: 1 | I49: =IFERROR(VLOOKUP(E49,ProductMaster!B:G,6,FALSE),0) -> 493.45794 | J49: =ROUND(SUM(I49*7%),2) -> 34.54 | K49: =ROUND(SUM(H49*I49),2) -> 493.46 | M49: Online (Kerry) | N49: Cat | O49: 0 | P49: No Tax Invoice | Q49: =IF(B49=B48,Q48+1,1) -> 11 | R49: =SUMIF($B$2:$K$500,S49,$K$2:$K$500) -> 27842.99 | S49: 505048 | T49: =R49*1.07 -> 29791.999
A50: 45417 | B50: 505019 | C50: A109 | D50: 48-32-5034 | E50: =IFERROR(VLOOKUP(D50,ProductMaster!$A:$B,2,FALSE),"") -> 48-32-5034 | F50: =IFERROR(VLOOKUP(D50,ProductMaster!$A:$C,3,FALSE),"") -> 48-32-5034 | G50: =IFERROR(VLOOKUP($D50,ProductMaster!$A:$O,4,FALSE),"") -> Adaptor หัวบล๊อค 1/2" | H50: 2 | I50: =IFERROR(VLOOKUP(E50,ProductMaster!B:G,6,FALSE),0) -> 100.93458 | J50: =ROUND(SUM(I50*7%),2) -> 7.07 | K50: =ROUND(SUM(H50*I50),2) -> 201.87 | L50: 2500 | M50: Online (Kerry) | N50: Cat | O50: 0 | P50: No Tax Invoice | Q50: =IF(B50=B49,Q49+1,1) -> 12 | R50: =SUMIF($B$2:$K$500,S50,$K$2:$K$500) -> 2865.42 | S50: 505049 | T50: =R50*1.07 -> 3065.9994 | U50: ไม่มีข้อมูลในระบบ เพิ่มให้หน่อยค่ะ คิดราคาลูกค้าถูกแล้วค่ะ
A51: 45417 | B51: 505020 | C51: A113 | D51: 45242251209 | E51: =IFERROR(VLOOKUP(D51,ProductMaster!$A:$B,2,FALSE),"") -> 006050802 | F51: =IFERROR(VLOOKUP(D51,ProductMaster!$A:$C,3,FALSE),"") -> 48-22-3079 | G51: =IFERROR(VLOOKUP($D51,ProductMaster!$A:$O,4,FALSE),"") -> คีมอเนกประสงค์ 6 IN1 | H51: 1 | I51: =IFERROR(VLOOKUP(E51,ProductMaster!B:G,6,FALSE),0) -> 1044.8598 | J51: =ROUND(SUM(I51*7%),2) -> 73.14 | K51: =ROUND(SUM(H51*I51),2) -> 1044.86 | M51: Transfer | N51: Cat | O51: 0 | P51: Tax Invoice | Q51: =IF(B51=B50,Q50+1,1) -> 1 | R51: =SUMIF($B$2:$K$500,S51,$K$2:$K$500) -> 31555.14 | S51: 505050 | T51: =R51*1.07 -> 33764
A52: 45417 | B52: 505020 | C52: A113 | D52: 4058546348144 | E52: =IFERROR(VLOOKUP(D52,ProductMaster!$A:$B,2,FALSE),"") -> 006126701 | F52: =IFERROR(VLOOKUP(D52,ProductMaster!$A:$C,3,FALSE),"") -> 4932478621 | G52: =IFERROR(VLOOKUP($D52,ProductMaster!$A:$O,4,FALSE),"") -> ชุดประแจหกเหลี่ยม 9 ชิ้น | H52: 1 | I52: =IFERROR(VLOOKUP(E52,ProductMaster!B:G,6,FALSE),0) -> 633.64486 | J52: =ROUND(SUM(I52*7%),2) -> 44.36 | K52: =ROUND(SUM(H52*I52),2) -> 633.64 | M52: Transfer | N52: Cat | O52: 0 | P52: Tax Invoice | Q52: =IF(B52=B51,Q51+1,1) -> 2 | R52: =SUMIF($B$2:$K$500,S52,$K$2:$K$500) -> 977.57 | S52: 505051 | T52: =R52*1.07 -> 1045.9999
A53: 45417 | B53: 505020 | C53: A113 | D53: 45242559541 | E53: =IFERROR(VLOOKUP(D53,ProductMaster!$A:$B,2,FALSE),"") -> 129305677 | F53: =IFERROR(VLOOKUP(D53,ProductMaster!$A:$C,3,FALSE),"") -> 48-22-8442 | G53: =IFERROR(VLOOKUP($D53,ProductMaster!$A:$O,4,FALSE),"") -> PACKOUT 2 DRAWER TOOL BOX | H53: 1 | I53: =IFERROR(VLOOKUP(E53,ProductMaster!B:G,6,FALSE),0) -> 6998.1308 | J53: =ROUND(SUM(I53*7%),2) -> 489.87 | K53: =ROUND(SUM(H53*I53),2) -> 6998.13 | M53: Transfer | N53: Cat | O53: 0 | P53: Tax Invoice | Q53: =IF(B53=B52,Q52+1,1) -> 3 | R53: =SUMIF($B$2:$K$500,S53,$K$2:$K$500) -> 287.85 | S53: 505052 | T53: =R53*1.07 -> 307.9995
A54: 45417 | B54: 505021 | C54: Onetime | D54: 4892210183637 | E54: =IFERROR(VLOOKUP(D54,ProductMaster!$A:$B,2,FALSE),"") -> 076002492 | F54: =IFERROR(VLOOKUP(D54,ProductMaster!$A:$C,3,FALSE),"") -> 48-22-0616 | G54: =IFERROR(VLOOKUP($D54,ProductMaster!$A:$O,4,FALSE),"") -> ตลับเมตรรุ่น COMPACT MAGNETIC 5 เมตร/16 ฟุต | H54: 1 | I54: =IFERROR(VLOOKUP(E54,ProductMaster!B:G,6,FALSE),0) -> 633.64486 | J54: =ROUND(SUM(I54*7%),2) -> 44.36 | K54: =ROUND(SUM(H54*I54),2) -> 633.64 | M54: Transfer | N54: Cat | O54: 0 | P54: No Tax Invoice | Q54: =IF(B54=B53,Q53+1,1) -> 1 | R54: =SUMIF($B$2:$K$500,S54,$K$2:$K$500) -> 2691.59 | S54: 505053 | T54: =R54*1.07 -> 2880.0013
A55: 45417 | B55: 505022 | C55: Onetime | D55: 4892210183637 | E55: =IFERROR(VLOOKUP(D55,ProductMaster!$A:$B,2,FALSE),"") -> 076002492 | F55: =IFERROR(VLOOKUP(D55,ProductMaster!$A:$C,3,FALSE),"") -> 48-22-0616 | G55: =IFERROR(VLOOKUP($D55,ProductMaster!$A:$O,4,FALSE),"") -> ตลับเมตรรุ่น COMPACT MAGNETIC 5 เมตร/16 ฟุต | H55: 1 | I55: =IFERROR(VLOOKUP(E55,ProductMaster!B:G,6,FALSE),0) -> 633.64486 | J55: =ROUND(SUM(I55*7%),2) -> 44.36 | K55: =ROUND(SUM(H55*I55),2) -> 633.64 | M55: Transfer | N55: Cat | O55: 0 | P55: No Tax Invoice | Q55: =IF(B55=B54,Q54+1,1) -> 1 | R55: =SUMIF($B$2:$K$500,S55,$K$2:$K$500) -> 1426.17 | S55: 505054 | T55: =R55*1.07 -> 1526.0019
A56: 45417 | B56: 505023 | C56: Onetime | D56: 45242568420 | E56: =IFERROR(VLOOKUP(D56,ProductMaster!$A:$B,2,FALSE),"") -> 006913001 | F56: =IFERROR(VLOOKUP(D56,ProductMaster!$A:$C,3,FALSE),"") -> 48-35-1411 | G56: =IFERROR(VLOOKUP($D56,ProductMaster!$A:$O,4,FALSE),"") -> ขาตั้งเลเซอร์ 180 เซนติเมตร | H56: 1 | I56: =IFERROR(VLOOKUP(E56,ProductMaster!B:G,6,FALSE),0) -> 2390.6542 | J56: =ROUND(SUM(I56*7%),2) -> 167.35 | K56: =ROUND(SUM(H56*I56),2) -> 2390.65 | M56: Transfer | N56: Cat | O56: 0 | P56: No Tax Invoice | Q56: =IF(B56=B55,Q55+1,1) -> 1 | R56: =SUMIF($B$2:$K$500,S56,$K$2:$K$500) -> 287.85 | S56: 505055 | T56: =R56*1.07 -> 307.9995
A57: 45417 | B57: 505024 | C57: A110 | D57: 45242251209 | E57: =IFERROR(VLOOKUP(D57,ProductMaster!$A:$B,2,FALSE),"") -> 006050802 | F57: =IFERROR(VLOOKUP(D57,ProductMaster!$A:$C,3,FALSE),"") -> 48-22-3079 | G57: =IFERROR(VLOOKUP($D57,ProductMaster!$A:$O,4,FALSE),"") -> คีมอเนกประสงค์ 6 IN1 | H57: 1 | I57: =IFERROR(VLOOKUP(E57,ProductMaster!B:G,6,FALSE),0) -> 1044.8598 | J57: =ROUND(SUM(I57*7%),2) -> 73.14 | K57: =ROUND(SUM(H57*I57),2) -> 1044.86 | M57: Online (Kerry) | N57: Cat | O57: 0 | P57: Tax Invoice | Q57: =IF(B57=B56,Q56+1,1) -> 1 | R57: =SUMIF($B$2:$K$500,S57,$K$2:$K$500) -> 1519.63 | S57: 505056 | T57: =R57*1.07 -> 1626.0041
A58: 45417 | B58: 505024 | C58: A110 | D58: 45242268061 | E58: =IFERROR(VLOOKUP(D58,ProductMaster!$A:$B,2,FALSE),"") -> 129226207 | F58: =IFERROR(VLOOKUP(D58,ProductMaster!$A:$C,3,FALSE),"") -> 48-22-1905 | G58: =IFERROR(VLOOKUP($D58,ProductMaster!$A:$O,4,FALSE),"") -> ใบมีดอเนกประสงค์ 5ใบ | H58: 1 | I58: =IFERROR(VLOOKUP(E58,ProductMaster!B:G,6,FALSE),0) -> 82.242991 | J58: =ROUND(SUM(I58*7%),2) -> 5.76 | K58: =ROUND(SUM(H58*I58),2) -> 82.24 | M58: Online (Kerry) | N58: Cat | O58: 0 | P58: Tax Invoice | Q58: =IF(B58=B57,Q57+1,1) -> 2 | R58: =SUMIF($B$2:$K$500,S58,$K$2:$K$500) -> 923.36 | S58: 505057 | T58: =R58*1.07 -> 987.9952
A59: 45417 | B59: 505024 | C59: A110 | D59: 45242509171 | E59: =IFERROR(VLOOKUP(D59,ProductMaster!$A:$B,2,FALSE),"") -> 006067501 | F59: =IFERROR(VLOOKUP(D59,ProductMaster!$A:$C,3,FALSE),"") -> 48-22-8901 | G59: =IFERROR(VLOOKUP($D59,ProductMaster!$A:$O,4,FALSE),"") -> ถุงมือกันบาด Cut 1 Dipped Gloves - M | H59: 1 | I59: =IFERROR(VLOOKUP(E59,ProductMaster!B:G,6,FALSE),0) -> 157.00935 | J59: =ROUND(SUM(I59*7%),2) -> 10.99 | K59: =ROUND(SUM(H59*I59),2) -> 157.01 | M59: Online (Kerry) | N59: Cat | O59: 0 | P59: Tax Invoice | Q59: =IF(B59=B58,Q58+1,1) -> 3 | R59: =SUMIF($B$2:$K$500,S59,$K$2:$K$500) -> 19035.52 | S59: 505058 | T59: =R59*1.07 -> 20368.006
A60: 45417 | B60: 505024 | C60: A110 | D60: 45242573912 | E60: =IFERROR(VLOOKUP(D60,ProductMaster!$A:$B,2,FALSE),"") -> 006105507 | F60: =IFERROR(VLOOKUP(D60,ProductMaster!$A:$C,3,FALSE),"") -> 48-22-1505 | G60: =IFERROR(VLOOKUP($D60,ProductMaster!$A:$O,4,FALSE),"") -> มีดพับอเนกประสงค์ พร้อมช่องเก็บใบมีด รุ่น FASTBACK™ 6 IN 1 | H60: 1 | I60: =IFERROR(VLOOKUP(E60,ProductMaster!B:G,6,FALSE),0) -> 699.06542 | J60: =ROUND(SUM(I60*7%),2) -> 48.93 | K60: =ROUND(SUM(H60*I60),2) -> 699.07 | M60: Online (Kerry) | N60: Cat | O60: 0 | P60: Tax Invoice | Q60: =IF(B60=B59,Q59+1,1) -> 4 | R60: =SUMIF($B$2:$K$500,S60,$K$2:$K$500) -> 568.22 | S60: 505059 | T60: =R60*1.07 -> 607.9954
A61: 45417 | B61: 505024 | C61: A110 | D61: 45242509171 | E61: =IFERROR(VLOOKUP(D61,ProductMaster!$A:$B,2,FALSE),"") -> 006067501 | F61: =IFERROR(VLOOKUP(D61,ProductMaster!$A:$C,3,FALSE),"") -> 48-22-8901 | G61: =IFERROR(VLOOKUP($D61,ProductMaster!$A:$O,4,FALSE),"") -> ถุงมือกันบาด Cut 1 Dipped Gloves - M | H61: 1 | I61: =IFERROR(VLOOKUP(E61,ProductMaster!B:G,6,FALSE),0) -> 157.00935 | J61: =ROUND(SUM(I61*7%),2) -> 10.99 | K61: =ROUND(SUM(H61*I61),2) -> 157.01 | M61: Online (Kerry) | N61: Cat | O61: 0 | P61: Tax Invoice | Q61: =IF(B61=B60,Q60+1,1) -> 5 | R61: =SUMIF($B$2:$K$500,S61,$K$2:$K$500) -> 633.64 | S61: 505060 | T61: =R61*1.07 -> 677.9948
A62: 45417 | B62: 505024 | C62: A110 | D62: 45242324996 | E62: =IFERROR(VLOOKUP(D62,ProductMaster!$A:$B,2,FALSE),"") -> 006033706 | F62: =IFERROR(VLOOKUP(D62,ProductMaster!$A:$C,3,FALSE),"") -> 48-22-3510 | G62: =IFERROR(VLOOKUP($D62,ProductMaster!$A:$O,4,FALSE),"") -> คีมล็อคปากตรง 10" | H62: 1 | I62: =IFERROR(VLOOKUP(E62,ProductMaster!B:G,6,FALSE),0) -> 586.91589 | J62: =ROUND(SUM(I62*7%),2) -> 41.08 | K62: =ROUND(SUM(H62*I62),2) -> 586.92 | M62: Online (Kerry) | N62: Cat | O62: 0 | P62: Tax Invoice | Q62: =IF(B62=B61,Q61+1,1) -> 6 | R62: =SUMIF($B$2:$K$500,S62,$K$2:$K$500) -> 829.91 | S62: 505061 | T62: =R62*1.07 -> 888.0037
A63: 45417 | B63: 505024 | C63: A110 | D63: 4892210240033 | E63: =IFERROR(VLOOKUP(D63,ProductMaster!$A:$B,2,FALSE),"") -> 059600307 | F63: =IFERROR(VLOOKUP(D63,ProductMaster!$A:$C,3,FALSE),"") -> M18 FPP2AC3-502LR SA | G63: =IFERROR(VLOOKUP($D63,ProductMaster!$A:$O,4,FALSE),"") -> M18 FPP2AC3-502LR SA (ชุดคอมโบสำหรับช่างไฟ) | H63: 1 | I63: =IFERROR(VLOOKUP(E63,ProductMaster!B:G,6,FALSE),0) -> 17652.336 | J63: =ROUND(SUM(I63*7%),2) -> 1235.66 | K63: =ROUND(SUM(H63*I63),2) -> 17652.34 | M63: Online (Kerry) | N63: Cat | P63: Tax Invoice | Q63: =IF(B63=B62,Q62+1,1) -> 7 | R63: =SUMIF($B$2:$K$500,S63,$K$2:$K$500) -> 353.27 | S63: 505062 | T63: =R63*1.07 -> 377.9989
A64: 45417 | B64: 505024 | C64: A110 | D64: 4892210132253-BF | E64: =IFERROR(VLOOKUP(D64,ProductMaster!$A:$B,2,FALSE),"") -> 000138153-(BF) | F64: =IFERROR(VLOOKUP(D64,ProductMaster!$A:$C,3,FALSE),"") -> C12CSA-(BF) | G64: =IFERROR(VLOOKUP($D64,ProductMaster!$A:$O,4,FALSE),"") -> แท่นชาร์จแบตเตอรี่ 12 โวลต์ | H64: 1 | I64: =IFERROR(VLOOKUP(E64,ProductMaster!B:G,6,FALSE),0) -> 925.23364 | J64: =ROUND(SUM(I64*7%),2) -> 64.77 | K64: =ROUND(SUM(H64*I64),2) -> 925.23 | M64: Online (Kerry) | N64: Cat | O64: 0 | P64: Tax Invoice | Q64: =IF(B64=B63,Q63+1,1) -> 8 | R64: =SUMIF($B$2:$K$500,S64,$K$2:$K$500) -> 444.86 | S64: 505063 | T64: =R64*1.07 -> 476.0002
A65: 45417 | B65: 505024 | C65: A110 | D65: 4892210220677-BF | E65: =IFERROR(VLOOKUP(D65,ProductMaster!$A:$B,2,FALSE),"") -> 001997033-(BF) | F65: =IFERROR(VLOOKUP(D65,ProductMaster!$A:$C,3,FALSE),"") -> M12HB5-(BF) | G65: =IFERROR(VLOOKUP($D65,ProductMaster!$A:$O,4,FALSE),"") -> แบตเตอรี่ 12 โวลต์ 5.0 แอมป์อาว HIGH OUTPUT | H65: 1 | I65: =IFERROR(VLOOKUP(E65,ProductMaster!B:G,6,FALSE),0) -> 1485.9813 | J65: =ROUND(SUM(I65*7%),2) -> 104.02 | K65: =ROUND(SUM(H65*I65),2) -> 1485.98 | M65: Online (Kerry) | N65: Cat | O65: 0 | P65: Tax Invoice | Q65: =IF(B65=B64,Q64+1,1) -> 9 | R65: =SUMIF($B$2:$K$500,S65,$K$2:$K$500) -> 19811.22 | S65: 505064 | T65: =R65*1.07 -> 21198.005
A66: 45417 | B66: 505024 | C66: A110 | D66: 4892210159175 | E66: =IFERROR(VLOOKUP(D66,ProductMaster!$A:$B,2,FALSE),"") -> 018098036 | F66: =IFERROR(VLOOKUP(D66,ProductMaster!$A:$C,3,FALSE),"") -> M12 CH-0C | G66: =IFERROR(VLOOKUP($D66,ProductMaster!$A:$O,4,FALSE),"") -> สว่านโรตารี่ไร้สาย 12 โวลต์ ระบบ SDS+ (เครื่องเปล่า) | H66: 1 | I66: =IFERROR(VLOOKUP(E66,ProductMaster!B:G,6,FALSE),0) -> 6764.486 | J66: =ROUND(SUM(I66*7%),2) -> 473.51 | K66: =ROUND(SUM(H66*I66),2) -> 6764.49 | M66: Online (Kerry) | N66: Cat | O66: 0 | P66: Tax Invoice | Q66: =IF(B66=B65,Q65+1,1) -> 10 | R66: =SUMIF($B$2:$K$500,S66,$K$2:$K$500) -> 4287.85 | S66: 505065 | T66: =R66*1.07 -> 4587.9995
A67: 45417 | B67: 505025 | C67: A111 | D67: 4892210219831 | E67: =IFERROR(VLOOKUP(D67,ProductMaster!$A:$B,2,FALSE),"") -> 018620017 | F67: =IFERROR(VLOOKUP(D67,ProductMaster!$A:$C,3,FALSE),"") -> M12 FID2-0 | G67: =IFERROR(VLOOKUP($D67,ProductMaster!$A:$O,4,FALSE),"") -> ไขควงกระแทกไร้สาย 18 โวลต์ (เครื่องเปล่า) | H67: 1 | I67: =IFERROR(VLOOKUP(E67,ProductMaster!B:G,6,FALSE),0) -> 4231.7757 | J67: =ROUND(SUM(I67*7%),2) -> 296.22 | K67: =ROUND(SUM(H67*I67),2) -> 4231.78 | M67: Online (Kerry) | N67: Cat | O67: 0 | P67: No Tax Invoice | Q67: =IF(B67=B66,Q66+1,1) -> 1 | R67: =SUMIF($B$2:$K$500,S67,$K$2:$K$500) -> 3300.94 | S67: 505066 | T67: =R67*1.07 -> 3532.0058
A68: 45417 | B68: 505025 | C68: A111 | D68: 4892210130266-BF | E68: =IFERROR(VLOOKUP(D68,ProductMaster!$A:$B,2,FALSE),"") -> 001998232-(BF) | F68: =IFERROR(VLOOKUP(D68,ProductMaster!$A:$C,3,FALSE),"") -> M12B2ASIA-(BF) | G68: =IFERROR(VLOOKUP($D68,ProductMaster!$A:$O,4,FALSE),"") -> แบตเตอรี่ 12 โวลต์ 2.0 แอมป์อาว | H68: 1 | I68: =IFERROR(VLOOKUP(E68,ProductMaster!B:G,6,FALSE),0) -> 738.31776 | J68: =ROUND(SUM(I68*7%),2) -> 51.68 | K68: =ROUND(SUM(H68*I68),2) -> 738.32 | M68: Online (Kerry) | N68: Cat | O68: 0 | P68: No Tax Invoice | Q68: =IF(B68=B67,Q67+1,1) -> 2 | R68: =SUMIF($B$2:$K$500,S68,$K$2:$K$500) -> 5633.66 | S68: 505067 | T68: =R68*1.07 -> 6028.0162
A69: 45417 | B69: 505025 | C69: A111 | D69: 4892210130266 | E69: =IFERROR(VLOOKUP(D69,ProductMaster!$A:$B,2,FALSE),"") -> 001998232 | F69: =IFERROR(VLOOKUP(D69,ProductMaster!$A:$C,3,FALSE),"") -> M12 B2 ASIA | G69: =IFERROR(VLOOKUP($D69,ProductMaster!$A:$O,4,FALSE),"") -> แบตเตอรี่ 12 โวลต์ 2.0 แอมป์อาว | H69: 1 | I69: =IFERROR(VLOOKUP(E69,ProductMaster!B:G,6,FALSE),0) -> 1110.2804 | J69: =ROUND(SUM(I69*7%),2) -> 77.72 | K69: =ROUND(SUM(H69*I69),2) -> 1110.28 | M69: Online (Kerry) | N69: Cat | O69: 0 | P69: No Tax Invoice | Q69: =IF(B69=B68,Q68+1,1) -> 3 | R69: =SUMIF($B$2:$K$500,S69,$K$2:$K$500) -> 790.65 | S69: 505068 | T69: =R69*1.07 -> 845.9955
A70: 45417 | B70: 505026 | C70: A112 | D70: 4892210240033 | E70: =IFERROR(VLOOKUP(D70,ProductMaster!$A:$B,2,FALSE),"") -> 059600307 | F70: =IFERROR(VLOOKUP(D70,ProductMaster!$A:$C,3,FALSE),"") -> M18 FPP2AC3-502LR SA | G70: =IFERROR(VLOOKUP($D70,ProductMaster!$A:$O,4,FALSE),"") -> M18 FPP2AC3-502LR SA (ชุดคอมโบสำหรับช่างไฟ) | H70: 1 | I70: =IFERROR(VLOOKUP(E70,ProductMaster!B:G,6,FALSE),0) -> 17652.336 | J70: =ROUND(SUM(I70*7%),2) -> 1235.66 | K70: =ROUND(SUM(H70*I70),2) -> 17652.34 | M70: Transfer | N70: Cat | O70: 0 | P70: Tax Invoice | Q70: =IF(B70=B69,Q69+1,1) -> 1 | R70: =SUMIF($B$2:$K$500,S70,$K$2:$K$500) -> 5573.84 | S70: 505069 | T70: =R70*1.07 -> 5964.0088
A71: 45417 | B71: 505027 | C71: A119 | D71: 4892210240033 | E71: =IFERROR(VLOOKUP(D71,ProductMaster!$A:$B,2,FALSE),"") -> 059600307 | F71: =IFERROR(VLOOKUP(D71,ProductMaster!$A:$C,3,FALSE),"") -> M18 FPP2AC3-502LR SA | G71: =IFERROR(VLOOKUP($D71,ProductMaster!$A:$O,4,FALSE),"") -> M18 FPP2AC3-502LR SA (ชุดคอมโบสำหรับช่างไฟ) | H71: 1 | I71: =IFERROR(VLOOKUP(E71,ProductMaster!B:G,6,FALSE),0) -> 17652.336 | J71: =ROUND(SUM(I71*7%),2) -> 1235.66 | K71: =ROUND(SUM(H71*I71),2) -> 17652.34 | M71: Transfer | N71: Cat | O71: 0 | P71: Tax Invoice | Q71: =IF(B71=B70,Q70+1,1) -> 1 | R71: =SUMIF($B$2:$K$500,S71,$K$2:$K$500) -> 157.01 | S71: 505070 | T71: =R71*1.07 -> 168.0007
A72: 45417 | B72: 505028 | C72: Onetime | D72: 45242573912 | E72: =IFERROR(VLOOKUP(D72,ProductMaster!$A:$B,2,FALSE),"") -> 006105507 | F72: =IFERROR(VLOOKUP(D72,ProductMaster!$A:$C,3,FALSE),"") -> 48-22-1505 | G72: =IFERROR(VLOOKUP($D72,ProductMaster!$A:$O,4,FALSE),"") -> มีดพับอเนกประสงค์ พร้อมช่องเก็บใบมีด รุ่น FASTBACK™ 6 IN 1 | H72: 1 | I72: =IFERROR(VLOOKUP(E72,ProductMaster!B:G,6,FALSE),0) -> 699.06542 | J72: =ROUND(SUM(I72*7%),2) -> 48.93 | K72: =ROUND(SUM(H72*I72),2) -> 699.07 | M72: Transfer | N72: Cat | O72: 0 | P72: No Tax Invoice | Q72: =IF(B72=B71,Q71+1,1) -> 1 | R72: =SUMIF($B$2:$K$500,S72,$K$2:$K$500) -> 0 | S72: 505071 | T72: =R72*1.07 -> 0
A73: 45417 | B73: 505029 | C73: Onetime | D73: 45242475230 | E73: =IFERROR(VLOOKUP(D73,ProductMaster!$A:$B,2,FALSE),"") -> 008051205 | F73: =IFERROR(VLOOKUP(D73,ProductMaster!$A:$C,3,FALSE),"") -> 48-32-4364 | G73: =IFERROR(VLOOKUP($D73,ProductMaster!$A:$O,4,FALSE),"") -> ดอกไขควง PH2-110 มม. Double Ended (10 ดอก) | H73: 1 | I73: =IFERROR(VLOOKUP(E73,ProductMaster!B:G,6,FALSE),0) -> 586.91589 | J73: =ROUND(SUM(I73*7%),2) -> 41.08 | K73: =ROUND(SUM(H73*I73),2) -> 586.92 | M73: Transfer | N73: Cat | O73: 0 | P73: No Tax Invoice | Q73: =IF(B73=B72,Q72+1,1) -> 1 | R73: =SUMIF($B$2:$K$500,S73,$K$2:$K$500) -> 0 | S73: 505072 | T73: =R73*1.07 -> 0
A74: 45417 | B74: 505030 | C74: Onetime | D74: 1318423879119 | E74: =IFERROR(VLOOKUP(D74,ProductMaster!$A:$B,2,FALSE),"") -> 059600269 | F74: =IFERROR(VLOOKUP(D74,ProductMaster!$A:$C,3,FALSE),"") -> M12 FPP2CB-401BLR SA | G74: =IFERROR(VLOOKUP($D74,ProductMaster!$A:$O,4,FALSE),"") -> M12 Vacuum Combo | H74: 1 | I74: =IFERROR(VLOOKUP(E74,ProductMaster!B:G,6,FALSE),0) -> 10175.701 | J74: =ROUND(SUM(I74*7%),2) -> 712.3 | K74: =ROUND(SUM(H74*I74),2) -> 10175.7 | L74: 2000 | M74: Credit Card | N74: Cat | O74: 0 | P74: No Tax Invoice | Q74: =IF(B74=B73,Q73+1,1) -> 1 | R74: =SUMIF($B$2:$K$500,S74,$K$2:$K$500) -> 0 | S74: 505073 | T74: =R74*1.07 -> 0
A75: 45417 | B75: 505031 | C75: Onetime | D75: 45242502691 | E75: =IFERROR(VLOOKUP(D75,ProductMaster!$A:$B,2,FALSE),"") -> 076002284 | F75: =IFERROR(VLOOKUP(D75,ProductMaster!$A:$C,3,FALSE),"") -> 48-22-7816 | G75: =IFERROR(VLOOKUP($D75,ProductMaster!$A:$O,4,FALSE),"") -> ตลับเมตรรุ่น RED 5 เมตร/16 ฟุต | H75: 1 | I75: =IFERROR(VLOOKUP(E75,ProductMaster!B:G,6,FALSE),0) -> 287.85047 | J75: =ROUND(SUM(I75*7%),2) -> 20.15 | K75: =ROUND(SUM(H75*I75),2) -> 287.85 | M75: Transfer | N75: Cat | O75: 0 | P75: No Tax Invoice | Q75: =IF(B75=B74,Q74+1,1) -> 1 | R75: =SUMIF($B$2:$K$500,S75,$K$2:$K$500) -> 0 | S75: 505074 | T75: =R75*1.07 -> 0
A76: 45417 | B76: 505032 | C76: Onetime | D76: 4892210183637 | E76: =IFERROR(VLOOKUP(D76,ProductMaster!$A:$B,2,FALSE),"") -> 076002492 | F76: =IFERROR(VLOOKUP(D76,ProductMaster!$A:$C,3,FALSE),"") -> 48-22-0616 | G76: =IFERROR(VLOOKUP($D76,ProductMaster!$A:$O,4,FALSE),"") -> ตลับเมตรรุ่น COMPACT MAGNETIC 5 เมตร/16 ฟุต | H76: 1 | I76: =IFERROR(VLOOKUP(E76,ProductMaster!B:G,6,FALSE),0) -> 633.64486 | J76: =ROUND(SUM(I76*7%),2) -> 44.36 | K76: =ROUND(SUM(H76*I76),2) -> 633.64 | M76: Transfer | N76: Cat | O76: 0 | P76: No Tax Invoice | Q76: =IF(B76=B75,Q75+1,1) -> 1 | R76: =SUMIF($B$2:$K$500,S76,$K$2:$K$500) -> 0 | S76: 505075 | T76: =R76*1.07 -> 0
A77: 45417 | B77: 505033 | C77: A118 | D77: 45242524211 | E77: =IFERROR(VLOOKUP(D77,ProductMaster!$A:$B,2,FALSE),"") -> 129305302 | F77: =IFERROR(VLOOKUP(D77,ProductMaster!$A:$C,3,FALSE),"") -> 48-22-8436 | G77: =IFERROR(VLOOKUP($D77,ProductMaster!$A:$O,4,FALSE),"") -> กล่องอุปกรณ์ช่าง PACKOUT Low Profile Compact Organizer | H77: 2 | I77: =IFERROR(VLOOKUP(E77,ProductMaster!B:G,6,FALSE),0) -> 1203.7383 | J77: =ROUND(SUM(I77*7%),2) -> 84.26 | K77: =ROUND(SUM(H77*I77),2) -> 2407.48 | M77: Transfer | N77: Cat | O77: 0 | P77: Tax Invoice | Q77: =IF(B77=B76,Q76+1,1) -> 1
A78: 45417 | B78: 505033 | C78: A118 | D78: 45242505333 | E78: =IFERROR(VLOOKUP(D78,ProductMaster!$A:$B,2,FALSE),"") -> 129305051 | F78: =IFERROR(VLOOKUP(D78,ProductMaster!$A:$C,3,FALSE),"") -> 48-22-8424 | G78: =IFERROR(VLOOKUP($D78,ProductMaster!$A:$O,4,FALSE),"") -> กล่องเครื่องมือ PACKOUT ขนาดกลาง | H78: 1 | I78: =IFERROR(VLOOKUP(E78,ProductMaster!B:G,6,FALSE),0) -> 3166.3551 | J78: =ROUND(SUM(I78*7%),2) -> 221.64 | K78: =ROUND(SUM(H78*I78),2) -> 3166.36 | M78: Transfer | N78: Cat | O78: 0 | P78: Tax Invoice | Q78: =IF(B78=B77,Q77+1,1) -> 2
A79: 45417 | B79: 505033 | C79: A118 | D79: 45242505319 | E79: =IFERROR(VLOOKUP(D79,ProductMaster!$A:$B,2,FALSE),"") -> 129305052 | F79: =IFERROR(VLOOKUP(D79,ProductMaster!$A:$C,3,FALSE),"") -> 48-22-8430 | G79: =IFERROR(VLOOKUP($D79,ProductMaster!$A:$O,4,FALSE),"") -> กล่องเครื่องมือ PACKOUT ออแกนไนซ์เซอร์ | H79: 1 | I79: =IFERROR(VLOOKUP(E79,ProductMaster!B:G,6,FALSE),0) -> 2512.1495 | J79: =ROUND(SUM(I79*7%),2) -> 175.85 | K79: =ROUND(SUM(H79*I79),2) -> 2512.15 | M79: Transfer | N79: Cat | O79: 0 | P79: Tax Invoice | Q79: =IF(B79=B78,Q78+1,1) -> 3
A80: 45417 | B80: 505033 | C80: A118 | D80: 45242630585 | E80: =IFERROR(VLOOKUP(D80,ProductMaster!$A:$B,2,FALSE),"") -> 006138701 | F80: =IFERROR(VLOOKUP(D80,ProductMaster!$A:$C,3,FALSE),"") -> 48-22-2182 | G80: =IFERROR(VLOOKUP($D80,ProductMaster!$A:$O,4,FALSE),"") -> ประแจหกเหลี่ยมแบบพับเก็บ 8 ชิ้น | H80: 1 | I80: =IFERROR(VLOOKUP(E80,ProductMaster!B:G,6,FALSE),0) -> 549.53271 | J80: =ROUND(SUM(I80*7%),2) -> 38.47 | K80: =ROUND(SUM(H80*I80),2) -> 549.53 | M80: Transfer | N80: Cat | O80: 0 | P80: Tax Invoice | Q80: =IF(B80=B79,Q79+1,1) -> 4
A81: 45417 | B81: 505033 | C81: A118 | D81: 45242600694 | E81: =IFERROR(VLOOKUP(D81,ProductMaster!$A:$B,2,FALSE),"") -> 129305883 | F81: =IFERROR(VLOOKUP(D81,ProductMaster!$A:$C,3,FALSE),"") -> 48-22-8432 | G81: =IFERROR(VLOOKUP($D81,ProductMaster!$A:$O,4,FALSE),"") -> กล่องเครื่องมือ PACKOUT Deep Organizer | H81: 1 | I81: =IFERROR(VLOOKUP(E81,ProductMaster!B:G,6,FALSE),0) -> 3353.271 | J81: =ROUND(SUM(I81*7%),2) -> 234.73 | K81: =ROUND(SUM(H81*I81),2) -> 3353.27 | M81: Transfer | N81: Cat | O81: 0 | P81: Tax Invoice | Q81: =IF(B81=B80,Q80+1,1) -> 5
A82: 45417 | B82: 505033 | C82: A118 | D82: 45242505357 | E82: =IFERROR(VLOOKUP(D82,ProductMaster!$A:$B,2,FALSE),"") -> 129305049 | F82: =IFERROR(VLOOKUP(D82,ProductMaster!$A:$C,3,FALSE),"") -> 48-22-8426 | G82: =IFERROR(VLOOKUP($D82,ProductMaster!$A:$O,4,FALSE),"") -> กล่องเครื่องมือ PACKOUT ล้อลาก | H82: 1 | I82: =IFERROR(VLOOKUP(E82,ProductMaster!B:G,6,FALSE),0) -> 6717.757 | J82: =ROUND(SUM(I82*7%),2) -> 470.24 | K82: =ROUND(SUM(H82*I82),2) -> 6717.76 | M82: Transfer | N82: Cat | O82: 0 | P82: Tax Invoice | Q82: =IF(B82=B81,Q81+1,1) -> 6
A83: 45417 | B83: 505034 | C83: Onetime | D83: 4892210132215 | E83: =IFERROR(VLOOKUP(D83,ProductMaster!$A:$B,2,FALSE),"") -> 000999671 | F83: =IFERROR(VLOOKUP(D83,ProductMaster!$A:$C,3,FALSE),"") -> M1218C | G83: =IFERROR(VLOOKUP($D83,ProductMaster!$A:$O,4,FALSE),"") -> แท่นชาร์จแบตเตอรี่ 12-18 โวลต์ | H83: 1 | I83: =IFERROR(VLOOKUP(E83,ProductMaster!B:G,6,FALSE),0) -> 1764.486 | J83: =ROUND(SUM(I83*7%),2) -> 123.51 | K83: =ROUND(SUM(H83*I83),2) -> 1764.49 | M83: Transfer | N83: Cat | O83: 0 | P83: No Tax Invoice | Q83: =IF(B83=B82,Q82+1,1) -> 1
A84: 45417 | B84: 505034 | C84: Onetime | D84: 4892210182494 | E84: =IFERROR(VLOOKUP(D84,ProductMaster!$A:$B,2,FALSE),"") -> 018370003 | F84: =IFERROR(VLOOKUP(D84,ProductMaster!$A:$C,3,FALSE),"") -> M12 FQID-0 ASIA | G84: =IFERROR(VLOOKUP($D84,ProductMaster!$A:$O,4,FALSE),"") -> ไขควงกระแทกไร้สาย 12 โวลต์ ระบบไฮดรอลิก (เครื่องเปล่า) | H84: 1 | I84: =IFERROR(VLOOKUP(E84,ProductMaster!B:G,6,FALSE),0) -> 5970.0935 | J84: =ROUND(SUM(I84*7%),2) -> 417.91 | K84: =ROUND(SUM(H84*I84),2) -> 5970.09 | M84: Transfer | N84: Cat | O84: 0 | P84: No Tax Invoice | Q84: =IF(B84=B83,Q83+1,1) -> 2
A85: 45417 | B85: 505034 | C85: Onetime | D85: 4892210130273-BF | E85: =IFERROR(VLOOKUP(D85,ProductMaster!$A:$B,2,FALSE),"") -> 001998233-(BF) | F85: =IFERROR(VLOOKUP(D85,ProductMaster!$A:$C,3,FALSE),"") -> M12B4ASIA-(BF) | G85: =IFERROR(VLOOKUP($D85,ProductMaster!$A:$O,4,FALSE),"") -> แบตเตอรี่ 12 โวลต์ 4.0 แอมป์อาว | H85: 1 | I85: =IFERROR(VLOOKUP(E85,ProductMaster!B:G,6,FALSE),0) -> 1112.1495 | J85: =ROUND(SUM(I85*7%),2) -> 77.85 | K85: =ROUND(SUM(H85*I85),2) -> 1112.15 | M85: Transfer | N85: Cat | O85: 0 | P85: No Tax Invoice | Q85: =IF(B85=B84,Q84+1,1) -> 3
A86: 45417 | B86: 505034 | C86: Onetime | D86: 4892210132253-BF | E86: =IFERROR(VLOOKUP(D86,ProductMaster!$A:$B,2,FALSE),"") -> 000138153-(BF) | F86: =IFERROR(VLOOKUP(D86,ProductMaster!$A:$C,3,FALSE),"") -> C12CSA-(BF) | G86: =IFERROR(VLOOKUP($D86,ProductMaster!$A:$O,4,FALSE),"") -> แท่นชาร์จแบตเตอรี่ 12 โวลต์ | H86: 1 | I86: =IFERROR(VLOOKUP(E86,ProductMaster!B:G,6,FALSE),0) -> 925.23364 | J86: =ROUND(SUM(I86*7%),2) -> 64.77 | K86: =ROUND(SUM(H86*I86),2) -> 925.23 | M86: Transfer | N86: Cat | O86: 0 | P86: No Tax Invoice | Q86: =IF(B86=B85,Q85+1,1) -> 4
A87: 45417 | B87: 505035 | C87: Onetime | D87: 45242475216 | E87: =IFERROR(VLOOKUP(D87,ProductMaster!$A:$B,2,FALSE),"") -> 008051202 | F87: =IFERROR(VLOOKUP(D87,ProductMaster!$A:$C,3,FALSE),"") -> 48-32-4361 | G87: =IFERROR(VLOOKUP($D87,ProductMaster!$A:$O,4,FALSE),"") -> ดอกไขควง PH2-65 มม. Double Ended (10 ดอก) | H87: 1 | I87: =IFERROR(VLOOKUP(E87,ProductMaster!B:G,6,FALSE),0) -> 409.34579 | J87: =ROUND(SUM(I87*7%),2) -> 28.65 | K87: =ROUND(SUM(H87*I87),2) -> 409.35 | M87: Transfer | N87: Cat | O87: 0 | P87: No Tax Invoice | Q87: =IF(B87=B86,Q86+1,1) -> 1
A88: 45417 | B88: 505036 | C88: Onetime | D88: 45242195022 | E88: =IFERROR(VLOOKUP(D88,ProductMaster!$A:$B,2,FALSE),"") -> 129225592 | F88: =IFERROR(VLOOKUP(D88,ProductMaster!$A:$C,3,FALSE),"") -> 48-32-5031 | G88: =IFERROR(VLOOKUP($D88,ProductMaster!$A:$O,4,FALSE),"") -> อะแดปเตอร์หัวบล็อก 3/8" แกนหกเหลี่ยม | H88: 1 | I88: =IFERROR(VLOOKUP(E88,ProductMaster!B:G,6,FALSE),0) -> 82.242991 | J88: =ROUND(SUM(I88*7%),2) -> 5.76 | K88: =ROUND(SUM(H88*I88),2) -> 82.24 | M88: Cash | N88: Cat | O88: 0 | P88: No Tax Invoice | Q88: =IF(B88=B87,Q87+1,1) -> 1
A89: 45417 | B89: 505036 | C89: Onetime | D89: 45242502684 | E89: =IFERROR(VLOOKUP(D89,ProductMaster!$A:$B,2,FALSE),"") -> 076002283 | F89: =IFERROR(VLOOKUP(D89,ProductMaster!$A:$C,3,FALSE),"") -> 48-22-7812 | G89: =IFERROR(VLOOKUP($D89,ProductMaster!$A:$O,4,FALSE),"") -> ตลับเมตรรุ่น RED 3 เมตร/10 ฟุต | H89: 1 | I89: =IFERROR(VLOOKUP(E89,ProductMaster!B:G,6,FALSE),0) -> 222.42991 | J89: =ROUND(SUM(I89*7%),2) -> 15.57 | K89: =ROUND(SUM(H89*I89),2) -> 222.43 | M89: Cash | N89: Cat | O89: 0 | P89: No Tax Invoice | Q89: =IF(B89=B88,Q88+1,1) -> 2
A90: 45417 | B90: 505037 | C90: Onetime | D90: 4892210203441 | E90: =IFERROR(VLOOKUP(D90,ProductMaster!$A:$B,2,FALSE),"") -> 016141004 | F90: =IFERROR(VLOOKUP(D90,ProductMaster!$A:$C,3,FALSE),"") -> IR PL250 | G90: =IFERROR(VLOOKUP($D90,ProductMaster!$A:$O,4,FALSE),"") -> ไฟฉายปากกา แบบชาร์จไฟได้ 250 ลูเมน | H90: 1 | I90: =IFERROR(VLOOKUP(E90,ProductMaster!B:G,6,FALSE),0) -> 2138.3178 | J90: =ROUND(SUM(I90*7%),2) -> 149.68 | K90: =ROUND(SUM(H90*I90),2) -> 2138.32 | M90: Credit Card | N90: Cat | O90: 0 | P90: No Tax Invoice | Q90: =IF(B90=B89,Q89+1,1) -> 1
A91: 45417 | B91: 505038 | C91: Onetime | D91: 45242082858 | E91: =IFERROR(VLOOKUP(D91,ProductMaster!$A:$B,2,FALSE),"") -> 129221228 | F91: =IFERROR(VLOOKUP(D91,ProductMaster!$A:$C,3,FALSE),"") -> 48-00-5184 | G91: =IFERROR(VLOOKUP($D91,ProductMaster!$A:$O,4,FALSE),"") -> ใบเลื่อยซอว์ซอลตัดเหล็ก 6" Thin Kerf 18 TPI (5ใบ) | H91: 1 | I91: =IFERROR(VLOOKUP(E91,ProductMaster!B:G,6,FALSE),0) -> 418.69159 | J91: =ROUND(SUM(I91*7%),2) -> 29.31 | K91: =ROUND(SUM(H91*I91),2) -> 418.69 | M91: Transfer | N91: Cat | O91: 0 | P91: No Tax Invoice | Q91: =IF(B91=B90,Q90+1,1) -> 1
A92: 45417 | B92: 505039 | C92: A120 | D92: 4892210174987 | E92: =IFERROR(VLOOKUP(D92,ProductMaster!$A:$B,2,FALSE),"") -> 018252007 | F92: =IFERROR(VLOOKUP(D92,ProductMaster!$A:$C,3,FALSE),"") -> M12 BPRT-0C | G92: =IFERROR(VLOOKUP($D92,ProductMaster!$A:$O,4,FALSE),"") -> เครื่องยิงรีเวทไร้สาย 12 โวลต์ (เครื่องเปล่า) | H92: 1 | I92: =IFERROR(VLOOKUP(E92,ProductMaster!B:G,6,FALSE),0) -> 6811.215 | J92: =ROUND(SUM(I92*7%),2) -> 476.79 | K92: =ROUND(SUM(H92*I92),2) -> 6811.21 | M92: Credit Card | N92: Cat | O92: 0 | P92: Tax Invoice | Q92: =IF(B92=B91,Q91+1,1) -> 1
A93: 45417 | B93: 505039 | C93: A120 | D93: 4892210220677-BF | E93: =IFERROR(VLOOKUP(D93,ProductMaster!$A:$B,2,FALSE),"") -> 001997033-(BF) | F93: =IFERROR(VLOOKUP(D93,ProductMaster!$A:$C,3,FALSE),"") -> M12HB5-(BF) | G93: =IFERROR(VLOOKUP($D93,ProductMaster!$A:$O,4,FALSE),"") -> แบตเตอรี่ 12 โวลต์ 5.0 แอมป์อาว HIGH OUTPUT | H93: 1 | I93: =IFERROR(VLOOKUP(E93,ProductMaster!B:G,6,FALSE),0) -> 1485.9813 | J93: =ROUND(SUM(I93*7%),2) -> 104.02 | K93: =ROUND(SUM(H93*I93),2) -> 1485.98 | M93: Credit Card | N93: Cat | O93: 0 | P93: Tax Invoice | Q93: =IF(B93=B92,Q92+1,1) -> 2
A94: 45417 | B94: 505039 | C94: A120 | D94: 4892210132253-BF | E94: =IFERROR(VLOOKUP(D94,ProductMaster!$A:$B,2,FALSE),"") -> 000138153-(BF) | F94: =IFERROR(VLOOKUP(D94,ProductMaster!$A:$C,3,FALSE),"") -> C12CSA-(BF) | G94: =IFERROR(VLOOKUP($D94,ProductMaster!$A:$O,4,FALSE),"") -> แท่นชาร์จแบตเตอรี่ 12 โวลต์ | H94: 1 | I94: =IFERROR(VLOOKUP(E94,ProductMaster!B:G,6,FALSE),0) -> 925.23364 | J94: =ROUND(SUM(I94*7%),2) -> 64.77 | K94: =ROUND(SUM(H94*I94),2) -> 925.23 | M94: Credit Card | N94: Cat | O94: 0 | P94: Tax Invoice | Q94: =IF(B94=B93,Q93+1,1) -> 3
A95: 45417 | B95: 505039 | C95: A120 | D95: 45242324996 | E95: =IFERROR(VLOOKUP(D95,ProductMaster!$A:$B,2,FALSE),"") -> 006033706 | F95: =IFERROR(VLOOKUP(D95,ProductMaster!$A:$C,3,FALSE),"") -> 48-22-3510 | G95: =IFERROR(VLOOKUP($D95,ProductMaster!$A:$O,4,FALSE),"") -> คีมล็อคปากตรง 10" | H95: 1 | I95: =IFERROR(VLOOKUP(E95,ProductMaster!B:G,6,FALSE),0) -> 586.91589 | J95: =ROUND(SUM(I95*7%),2) -> 41.08 | K95: =ROUND(SUM(H95*I95),2) -> 586.92 | M95: Credit Card | N95: Cat | O95: 0 | P95: Tax Invoice | Q95: =IF(B95=B94,Q94+1,1) -> 4
A96: 45417 | B96: 505040 | C96: Onetime | D96: 45242479887 | E96: =IFERROR(VLOOKUP(D96,ProductMaster!$A:$B,2,FALSE),"") -> 006059112 | F96: =IFERROR(VLOOKUP(D96,ProductMaster!$A:$C,3,FALSE),"") -> 48-22-8722 | G96: =IFERROR(VLOOKUP($D96,ProductMaster!$A:$O,4,FALSE),"") -> ถุงมือ General Purpose Gloves - L | H96: 1 | I96: =IFERROR(VLOOKUP(E96,ProductMaster!B:G,6,FALSE),0) -> 642.99065 | J96: =ROUND(SUM(I96*7%),2) -> 45.01 | K96: =ROUND(SUM(H96*I96),2) -> 642.99 | M96: Transfer | N96: Cat | O96: 0 | P96: No Tax Invoice | Q96: =IF(B96=B95,Q95+1,1) -> 1
A97: 45417 | B97: 505041 | C97: A115 | D97: 45242645701 | E97: =IFERROR(VLOOKUP(D97,ProductMaster!$A:$B,2,FALSE),"") -> 006157301 | F97: =IFERROR(VLOOKUP(D97,ProductMaster!$A:$C,3,FALSE),"") -> 48-22-2184 | G97: =IFERROR(VLOOKUP($D97,ProductMaster!$A:$O,4,FALSE),"") -> ประแจหกเหลี่ยมหัวทอร์คแบบพับเก็บ 8 ชิ้น | H97: 1 | I97: =IFERROR(VLOOKUP(E97,ProductMaster!B:G,6,FALSE),0) -> 549.53271 | J97: =ROUND(SUM(I97*7%),2) -> 38.47 | K97: =ROUND(SUM(H97*I97),2) -> 549.53 | M97: Transfer | N97: Cat | O97: 0 | P97: Tax Invoice | Q97: =IF(B97=B96,Q96+1,1) -> 1
A98: 45417 | B98: 505041 | C98: A115 | D98: 45242342211 | E98: =IFERROR(VLOOKUP(D98,ProductMaster!$A:$B,2,FALSE),"") -> 006037401 | F98: =IFERROR(VLOOKUP(D98,ProductMaster!$A:$C,3,FALSE),"") -> 48-22-6101 | G98: =IFERROR(VLOOKUP($D98,ProductMaster!$A:$O,4,FALSE),"") -> คีมปากแหลม 8" | H98: 1 | I98: =IFERROR(VLOOKUP(E98,ProductMaster!B:G,6,FALSE),0) -> 661.68224 | J98: =ROUND(SUM(I98*7%),2) -> 46.32 | K98: =ROUND(SUM(H98*I98),2) -> 661.68 | M98: Transfer | N98: Cat | O98: 0 | P98: Tax Invoice | Q98: =IF(B98=B97,Q97+1,1) -> 2
A99: 45417 | B99: 505041 | C99: A115 | D99: 45242356089 | E99: =IFERROR(VLOOKUP(D99,ProductMaster!$A:$B,2,FALSE),"") -> 006051101 | F99: =IFERROR(VLOOKUP(D99,ProductMaster!$A:$C,3,FALSE),"") -> 48-22-6102 | G99: =IFERROR(VLOOKUP($D99,ProductMaster!$A:$O,4,FALSE),"") -> คีมปากจิ้งจก | H99: 1 | I99: =IFERROR(VLOOKUP(E99,ProductMaster!B:G,6,FALSE),0) -> 792.52336 | J99: =ROUND(SUM(I99*7%),2) -> 55.48 | K99: =ROUND(SUM(H99*I99),2) -> 792.52 | M99: Transfer | N99: Cat | O99: 0 | P99: Tax Invoice | Q99: =IF(B99=B98,Q98+1,1) -> 3
A100: 45417 | B100: 505041 | C100: A115 | D100: 45242638796 | E100: =IFERROR(VLOOKUP(D100,ProductMaster!$A:$B,2,FALSE),"") -> 006143201 | F100: =IFERROR(VLOOKUP(D100,ProductMaster!$A:$C,3,FALSE),"") -> 48-22-0307 | G100: =IFERROR(VLOOKUP($D100,ProductMaster!$A:$O,4,FALSE),"") -> เลื่อยอเนกประสงค์แบบพับ | H100: 1 | I100: =IFERROR(VLOOKUP(E100,ProductMaster!B:G,6,FALSE),0) -> 829.90654 | J100: =ROUND(SUM(I100*7%),2) -> 58.09 | K100: =ROUND(SUM(H100*I100),2) -> 829.91 | M100: Transfer | N100: Cat | O100: 0 | P100: Tax Invoice | Q100: =IF(B100=B99,Q99+1,1) -> 4
...

Sheet ProductMaster
A1: UPC | B1: SKU | C1: Model Name | D1: Description | E1: ProductGroup | F1: Support From | G1: SellPrice (Exc. VAT) | H1: SellPrice (Inc. VAT) | I1: Barcode
A2: 45242502066 | B2: 008049487 | C2: 48894759 | D2: ชุดดอกเจาะเหล็กไทเทเนี่ยม Red Hex HSS-G Titanium (10 ดอก) | E2: Accessories | F2: TH | G2: =(ProductMaster_iPST_iPower[[#This Row],[SellPrice (Inc. VAT)]]*100)/107 -> 1119.6262 | H2: 1198 | I2: *45242502066*
A3: 4002395308866 | B3: 129303445 | C3: 4932307070 | D3: ดอกโรตารี่ SDS+ 8.0 x 50 x 110 มม. | E3: Accessories | F3: TH | G3: =(ProductMaster_iPST_iPower[[#This Row],[SellPrice (Inc. VAT)]]*100)/107 -> 194.39252 | H3: 208 | I3: *4002395308866*
A4: 4002395308873 | B4: 129303446 | C4: 4932307071 | D4: ดอกโรตารี่ SDS+ 8.0 x 100 x 160 มม. | E4: Accessories | F4: TH | G4: =(ProductMaster_iPST_iPower[[#This Row],[SellPrice (Inc. VAT)]]*100)/107 -> 213.08411 | H4: 228 | I4: *4002395308873*
A5: 4002395308897 | B5: 129303457 | C5: 4932307073 | D5: ดอกโรตารี่ SDS+ 10 x 100 x 160 มม. | E5: Accessories | F5: TH | G5: =(ProductMaster_iPST_iPower[[#This Row],[SellPrice (Inc. VAT)]]*100)/107 -> 241.1215 | H5: 258 | I5: *4002395308897*
A6: 4002395312276 | B6: 129303436 | C6: 4932344292 | D6: ดอกโรตารี่ SDS+ 6.5 x 50 x 110 มม. | E6: Accessories | F6: TH | G6: =(ProductMaster_iPST_iPower[[#This Row],[SellPrice (Inc. VAT)]]*100)/107 -> 185.04673 | H6: 198 | I6: *4002395312276*
A7: 4002395312269 | B7: 129303437 | C7: 4932344293 | D7: ดอกโรตารี่ SDS+ 6.5 x 100 x 160 มม. | E7: Accessories | F7: TH | G7: =(ProductMaster_iPST_iPower[[#This Row],[SellPrice (Inc. VAT)]]*100)/107 -> 203.73832 | H7: 218 | I7: *4002395312269*
A8: 4058546287405 | B8: 008052901 | C8: 4932471112 | D8: ชุดดอกสว่านอเนกประสงค์ (8 ชิ้น) | E8: Accessories | F8: TH | G8: =(ProductMaster_iPST_iPower[[#This Row],[SellPrice (Inc. VAT)]]*100)/107 -> 951.40187 | H8: 1018 | I8: *4058546287405*
A9: 4058546413262 | B9: 001998659 | C9: 49162517 | D9: ใบมีดตัดหญ้า | E9: Accessories | F9: TH | G9: =(ProductMaster_iPST_iPower[[#This Row],[SellPrice (Inc. VAT)]]*100)/107 -> 0 | H9: 0 | I9: *4058546413262*
A10: 4058546297633 | B10: 006101901 | C10: 4932471864 | D10: ชุดประแจบล็อก 1/2" 28 ชิ้น | E10: Accessories | F10: TH | G10: =(ProductMaster_iPST_iPower[[#This Row],[SellPrice (Inc. VAT)]]*100)/107 -> 5502.8037 | H10: 5888 | I10: *4058546297633*
A11: 4058546289584 | B11: 001999918 | C11: 4932471330 | D11: ใบมีดสำหรับก้านต่อตัดขอบสนาม | E11: Accessories | F11: TH | G11: =(ProductMaster_iPST_iPower[[#This Row],[SellPrice (Inc. VAT)]]*100)/107 -> 474.76636 | H11: 508 | I11: *4058546289584*
A12: 4058546404611 | B12: 001998668 | C12: 4932480176 | D12: โซ่เลื่อย 8" สำหรับ M18 FHS | E12: Accessories | F12: TH | G12: =(ProductMaster_iPST_iPower[[#This Row],[SellPrice (Inc. VAT)]]*100)/107 -> 801.86916 | H12: 858 | I12: *4058546404611*
A13: 4892210218001 | B13: 001528007 | C13: 4932480180 | D13: ตลับพร้อมเส้นเอ็นเล็มหญ้า 2 มม. x 7.6 ม. | E13: Accessories | F13: TH | G13: =(ProductMaster_iPST_iPower[[#This Row],[SellPrice (Inc. VAT)]]*100)/107 -> 801.86916 | H13: 858 | I13: *4892210218001*
A14: 4058546376123 | B14: 001568005 | C14: 4932479818 | D14: ใบมีดตัดหญ้า 21 นิ้ว สำหรับรถเข็นตัดหญ้าไร้สาย 21 นิ้ว ระบบแบตเตอรี่คู่ | E14: Accessories | F14: TH | G14: =(ProductMaster_iPST_iPower[[#This Row],[SellPrice (Inc. VAT)]]*100)/107 -> 755.14019 | H14: 808 | I14: *4058546376123*
A15: 45242081745 | B15: 129221183 | C15: 48-00-1301 | D15: ใบเลื่อยซอว์ซอลตัดแต่ง 9" Pruning 5 TPI (5 ใบ) | E15: Accessories | F15: TH | G15: =(ProductMaster_iPST_iPower[[#This Row],[SellPrice (Inc. VAT)]]*100)/107 -> 568.2243 | H15: 608 | I15: *45242081745*
A16: 45242081769 | B16: 129221184 | C16: 48-00-1303 | D16: ใบเลื่อยซอว์ซอลตัดแต่ง 12" Pruning 5 TPI (5 ใบ) | E16: Accessories | F16: TH | G16: =(ProductMaster_iPST_iPower[[#This Row],[SellPrice (Inc. VAT)]]*100)/107 -> 867.28972 | H16: 928 | I16: *45242081769*
A17: 45242081042 | B17: 129221193 | C17: 48-00-4184 | D17: ใบเลื่อยซอว์ซอลตัดเหล็ก 6" TORCH Thin Kerf Ice Hardened 18 TPI (5 ใบ) | E17: Accessories | F17: TH | G17: =(ProductMaster_iPST_iPower[[#This Row],[SellPrice (Inc. VAT)]]*100)/107 -> 418.69159 | H17: 448 | I17: *45242081042*
A18: 45242188666 | B18: 129224863 | C18: 48-00-4189 | D18: ใบเลื่อยซอว์ซอลตัดเหล็ก 12" TORCH Thin Kerf Ice Hardened 18 TPI (5 ใบ) | E18: Accessories | F18: TH | G18: =(ProductMaster_iPST_iPower[[#This Row],[SellPrice (Inc. VAT)]]*100)/107 -> 745.79439 | H18: 798 | I18: *45242188666*
A19: 45242081073 | B19: 129221197 | C19: 48-00-4712 | D19: ใบเลื่อยซอว์ซอลตัดเหล็ก 6" TORCH Ice Hardened 10 TPI (5 ใบ) | E19: Accessories | F19: TH | G19: =(ProductMaster_iPST_iPower[[#This Row],[SellPrice (Inc. VAT)]]*100)/107 -> 512.14953 | H19: 548 | I19: *45242081073*
A20: 45242081097 | B20: 129221199 | C20: 48-00-4782 | D20: ใบเลื่อยซอว์ซอลตัดเหล็ก 6" TORCH Ice Hardened 14 TPI (5 ใบ) | E20: Accessories | F20: TH | G20: =(ProductMaster_iPST_iPower[[#This Row],[SellPrice (Inc. VAT)]]*100)/107 -> 502.80374 | H20: 538 | I20: *45242081097*
A21: 45242082988 | B21: 129224935 | C21: 48-00-5021 | D21: ใบเลื่อยซอว์ซอลตัดไม้ 6" AX 5 TPI (5 ใบ) | E21: Accessories | F21: TH | G21: =(ProductMaster_iPST_iPower[[#This Row],[SellPrice (Inc. VAT)]]*100)/107 -> 652.33645 | H21: 698 | I21: *45242082988*
A22: 45242082995 | B22: 129221208 | C22: 48-00-5026 | D22: ใบเลื่อยซอว์ซอลตัดไม้ 9" AX 5 TPI (5 ใบ) | E22: Accessories | F22: TH | G22: =(ProductMaster_iPST_iPower[[#This Row],[SellPrice (Inc. VAT)]]*100)/107 -> 942.05607 | H22: 1008 | I22: *45242082995*
A23: 45242083022 | B23: 129221209 | C23: 48-00-5027 | D23: ใบเลื่อยซอว์ซอลตัดไม้ 12" AX 5 TPI (5 ใบ) | E23: Accessories | F23: TH | G23: =(ProductMaster_iPST_iPower[[#This Row],[SellPrice (Inc. VAT)]]*100)/107 -> 1269.1589 | H23: 1358 | I23: *45242083022*
A24: 45242082698 | B24: 129221211 | C24: 48-00-5035 | D24: ใบเลื่อยซอว์ซอลตัดไม้ 6" Thin Kerf 5 TPI (5 ใบ) | E24: Accessories | F24: TH | G24: =(ProductMaster_iPST_iPower[[#This Row],[SellPrice (Inc. VAT)]]*100)/107 -> 642.99065 | H24: 688 | I24: *45242082698*
A25: 45242082704 | B25: 129221212 | C25: 48-00-5036 | D25: ใบเลื่อยซอว์ซอลตัดไม้ 9" Thin Kerf 5 TPI (5 ใบ) | E25: Accessories | F25: TH | G25: =(ProductMaster_iPST_iPower[[#This Row],[SellPrice (Inc. VAT)]]*100)/107 -> 857.94393 | H25: 918 | I25: *45242082704*
... A98: 4892210191557 | B98: 001998279 | C98: FCHSC18ACCY01 | D98: โซ่เลื่อย สำหรับ M18 FCHSC | E98: Accessories | F98: TH | G98: =(ProductMaster_iPST_iPower[[#This Row],[SellPrice (Inc. VAT)]]*100)/107 -> 801.86916 | H98: 858 | I98: *4892210191557*
A99: 4058546348144 | B99: 006126701 | C99: 4932478621 | D99: ชุดประแจหกเหลี่ยม 9 ชิ้น | E99: Hand Tools | F99: TH | G99: =(ProductMaster_iPST_iPower[[#This Row],[SellPrice (Inc. VAT)]]*100)/107 -> 633.64486 | H99: 678 | I99: *4058546348144*
A100: 45242638796 | B100: 006143201 | C100: 48-22-0307 | D100: เลื่อยอเนกประสงค์แบบพับ | E100: Hand Tools | F100: TH | G100: =(ProductMaster_iPST_iPower[[#This Row],[SellPrice (Inc. VAT)]]*100)/107 -> 829.90654 | H100: 888 | I100: *45242638796*
A101: 4892210183637 | B101: 076002492 | C101: 48-22-0616 | D101: ตลับเมตรรุ่น COMPACT MAGNETIC 5 เมตร/16 ฟุต | E101: Hand Tools | F101: TH | G101: =(ProductMaster_iPST_iPower[[#This Row],[SellPrice (Inc. VAT)]]*100)/107 -> 633.64486 | H101: 678 | I101: *4892210183637*
A102: 4892210183644 | B102: 076002493 | C102: 48-22-0626 | D102: ตลับเมตรรุ่น COMPACT MAGNETIC 8 เมตร/26 ฟุต | E102: Hand Tools | F102: TH | G102: =(ProductMaster_iPST_iPower[[#This Row],[SellPrice (Inc. VAT)]]*100)/107 -> 783.17757 | H102: 838 | I102: *4892210183644*
A103: 45242573912 | B103: 006105507 | C103: 48-22-1505 | D103: มีดพับอเนกประสงค์ พร้อมช่องเก็บใบมีด รุ่น FASTBACK™ 6 IN 1 | E103: Hand tools | F103: TH | G103: =(ProductMaster_iPST_iPower[[#This Row],[SellPrice (Inc. VAT)]]*100)/107 -> 699.06542 | H103: 748 | I103: *45242573912*
A104: 45242534470 | B104: 006084001 | C104: 48-22-1520 | D104: มีดพับฮันเตอร์ | E104: Hand Tools | F104: TH | G104: =(ProductMaster_iPST_iPower[[#This Row],[SellPrice (Inc. VAT)]]*100)/107 -> 605.60748 | H104: 648 | I104: *45242534470*
A105: 45242534487 | B105: 006084101 | C105: 48-22-1525 | D105: มีดพับเล็บเหยี่ยว | E105: Hand Tools | F105: TH | G105: =(ProductMaster_iPST_iPower[[#This Row],[SellPrice (Inc. VAT)]]*100)/107 -> 614.95327 | H105: 658 | I105: *45242534487*
A106: 45242534494 | B106: 006084201 | C106: 48-22-1530 | D106: มีดพับฟันเลื่อยระบบสปริงเปิดปิด | E106: Hand Tools | F106: TH | G106: =(ProductMaster_iPST_iPower[[#This Row],[SellPrice (Inc. VAT)]]*100)/107 -> 727.1028 | H106: 778 | I106: *45242534494*
A107: 45242534500 | B107: 006084301 | C107: 48-22-1535 | D107: มีดพับฟันเลื่อยลายพรางระบบสปริงเปิด/ปิด | E107: Hand Tools | F107: TH | G107: =(ProductMaster_iPST_iPower[[#This Row],[SellPrice (Inc. VAT)]]*100)/107 -> 876.63551 | H107: 938 | I107: *45242534500*
A108: 45242551453 | B108: 006089001 | C108: 48-22-1540 | D108: มีดพับ รุ่น FASTBACK™ 5 IN 1 | E108: Hand Tools | F108: TH | G108: =(ProductMaster_iPST_iPower[[#This Row],[SellPrice (Inc. VAT)]]*100)/107 -> 951.40187 | H108: 1018 | I108: *45242551453*
A109: 45242534395 | B109: 006084404 | C109: 48-22-1906 | D109: มีดพับคอมแพ็คอเนกประสงค์ | E109: Hand Tools | F109: TH | G109: =(ProductMaster_iPST_iPower[[#This Row],[SellPrice (Inc. VAT)]]*100)/107 -> 446.72897 | H109: 478 | I109: *45242534395*
A110: 45242359158 | B110: 129305673 | C110: 48-22-1997 | D110: มีดพับ D2 Hardline 2.5" | E110: Hand Tools | F110: TH | G110: =(ProductMaster_iPST_iPower[[#This Row],[SellPrice (Inc. VAT)]]*100)/107 -> 1465.4206 | H110: 1568 | I110: *45242359158*
A111: 45242359172 | B111: 129305674 | C111: 48-22-1999 | D111: มีดพับ D2 Hardline 3.5" | E111: Hand Tools | F111: TH | G111: =(ProductMaster_iPST_iPower[[#This Row],[SellPrice (Inc. VAT)]]*100)/107 -> 1671.028 | H111: 1788 | I111: *45242359172*
... A211: 4892210190345 | B211: 001998090DG9 | C211: MXF CP203 | D211: แบตเตอรี่ MXF CP203 | E211: Power Tools | F211: TH | G211: =(ProductMaster_iPST_iPower[[#This Row],[SellPrice (Inc. VAT)]]*100)/107 -> 18867.29 | H211: 20188 | I211: *4892210190345*
B212: 018758010 | C212: M18 F2BPB-0 ASIA | D212: เครื่องเป่าใบไม้ไร้สายแบบสะพายหลัง 18 โวลต์ | E212: Power Tools | F212: TH | G212: =(ProductMaster_iPST_iPower[[#This Row],[SellPrice (Inc. VAT)]]*100)/107 -> 20456.075 | H212: 21888 | I212: #N/A
B213: 018813002 | C213: MXF TLIC-0 APJ | D213: MXF Compact Tower Light | E213: Power Tools | F213: TH | G213: =(ProductMaster_iPST_iPower[[#This Row],[SellPrice (Inc. VAT)]]*100)/107 -> 70923.364 | H213: 75888 | I213: #N/A
A214: 45242603312 | B214: 129306821 | C214: 49-90-2020 | D214: หัวดูดฝุ่นพรม | E214: Accessories | F214: PRD Storage | G214: =(ProductMaster_iPST_iPower[[#This Row],[SellPrice (Inc. VAT)]]*100)/107 -> 1297.1963 | H214: 1388 | I214: *45242603312*
A215: 45242610273 | B215: 129306823 | C215: 49-90-2022 | D215: หัวดูดเก็บฝุ่น | E215: Accessories | F215: PRD Storage | G215: =(ProductMaster_iPST_iPower[[#This Row],[SellPrice (Inc. VAT)]]*100)/107 -> 829.90654 | H215: 888 | I215: *45242610273*
A216: 45242610280 | B216: 129306824 | C216: 49-90-2023 | D216: หัวดูดฝุ่นร่อง 3 in 1 | E216: Accessories | F216: PRD Storage | G216: =(ProductMaster_iPST_iPower[[#This Row],[SellPrice (Inc. VAT)]]*100)/107 -> 456.07477 | H216: 488 | I216: *45242610280*
A217: 45242610273 | B217: 129306833 | C217: 49-90-2034 | D217: หัวดูดฝุ่นรักษาพื้นผิว | E217: Accessories | F217: PRD Storage | G217: =(ProductMaster_iPST_iPower[[#This Row],[SellPrice (Inc. VAT)]]*100)/107 -> 923.36449 | H217: 988 | I217: *45242610273*
A218: 45242610426 | B218: 129306835 | C218: 49-90-2037 | D218: หัวดูดฝุ่นที่แคบ | E218: Accessories | F218: PRD Storage | G218: =(ProductMaster_iPST_iPower[[#This Row],[SellPrice (Inc. VAT)]]*100)/107 -> 1390.6542 | H218: 1488 | I218: *45242610426*
B219: 018685005 | C219: M18 HCC125R-0C ASIA | D219: M18 เครื่องตัดสายไฟใต้ดิน 125มม.ไร้สาย | E219: Power Tools | F219: Hub Simple List | G219: =(ProductMaster_iPST_iPower[[#This Row],[SellPrice (Inc. VAT)]]*100)/107 -> 0 | H219: 0 | I219: #N/A
B220: 019600964 | C220: MXF PC50 | D220: MXF เครื่องตบดิน รุ่นแผ่นเรียบ | E220: Power Tools | F220: Hub Simple List | G220: =(ProductMaster_iPST_iPower[[#This Row],[SellPrice (Inc. VAT)]]*100)/107 -> 148493.46 | H220: 158888 | I220: #N/A
A221: 4892210199027 | B221: 018505015 | C221: FPFT18ACCY01 | D221: ลวดร้อยสายไฟ (30 เมตร ไม่นำไฟฟ้า) | E221: Accessories | F221: HPC TH List | G221: =(ProductMaster_iPST_iPower[[#This Row],[SellPrice (Inc. VAT)]]*100)/107 -> 5642.9907 | H221: 6038 | I221: *4892210199027*
A222: 4892210236258 | B222: 018718008 | C222: M12 FJS-0 ASIA | D222: M12 FUEL จิ๊กซอว์ไร้สาย | E222: Power Tools | F222: HPC TH List | G222: =(ProductMaster_iPST_iPower[[#This Row],[SellPrice (Inc. VAT)]]*100)/107 -> 6530.8411 | H222: 6988 | I222: *4892210236258*
A223: 4892210215000 | B223: 016052011 | C223: M18 BTP-0 | D223: ปั๊มน้ำอเนกประสงค์ไร้สาย 18 โวลต์ (เครื่องเปล่า) | E223: Power Tools | F223: HPC TH List | G223: =(ProductMaster_iPST_iPower[[#This Row],[SellPrice (Inc. VAT)]]*100)/107 -> 9241.1215 | H223: 9888 | I223: *4892210215000*
A224: 4892210238139 | B224: 001998938 | C224: M18 DBSC SA | D224: M18 แท่นชาร์จแบตเตอรี่ แบบซูเปอร์ชาร์จ 2 ช่อง | E224: Power Tools | F224: HPC TH List | G224: =(ProductMaster_iPST_iPower[[#This Row],[SellPrice (Inc. VAT)]]*100)/107 -> 10269.159 | H224: 10988 | I224: *4892210238139*
A225: 4892210236128 | B225: 001998977DG9 | C225: M18 FB6 ASIA | D225: M18 FORGE แบตเตอรี่ 6.0 แอมป์อาว | E225: Power Tools | F225: HPC TH List | G225: =(ProductMaster_iPST_iPower[[#This Row],[SellPrice (Inc. VAT)]]*100)/107 -> 7558.8785 | H225: 8088 | I225: *4892210236128*
A226: 4892210180537 | B226: 018287008 | C226: M18 FJS-0X | D226: จิ๊กซอว์ไร้สาย 18 โวลต์ (เครื่องเปล่า) | E226: Power Tools | F226: HPC TH List | G226: =(ProductMaster_iPST_iPower[[#This Row],[SellPrice (Inc. VAT)]]*100)/107 -> 9334.5794 | H226: 9988 | I226: *4892210180537*
A227: 4892210173058 | B227: 018230032 | C227: M18 ONEFHIWF34-0X | D227: บล็อกกระแทกไร้สาย 18 โวลต์ 3/4" (เครื่องเปล่า) | E227: Power Tools | F227: HPC TH List | G227: =(ProductMaster_iPST_iPower[[#This Row],[SellPrice (Inc. VAT)]]*100)/107 -> 10642.991 | H227: 11388 | I227: *4892210173058*
B228: 086252001 | C228: 48-22-8690 | D228: แท่นปากกาจับท่อ 6 นิ้ว แบบโซ่ล็อคพร้อมขาตั้ง | E228: Hand Tools | F228: HPC List | G228: =(ProductMaster_iPST_iPower[[#This Row],[SellPrice (Inc. VAT)]]*100)/107 -> 17932.71 | H228: 19188 | I228: #N/A
A229: 4892210132253 | B229: 000138153 | C229: C12 C | D229: แท่นชาร์จแบตเตอรี่ 12 โวลต์ | E229: Power Tools | F229: HPC List | G229: =(ProductMaster_iPST_iPower[[#This Row],[SellPrice (Inc. VAT)]]*100)/107 -> 1390.6542 | H229: 1488 | I229: *4892210132253*
A230: 4892210203458 | B230: 016710004 | C230: IR FL500 | D230: ไฟฉาย แบบชาร์จไฟได้ 500 ลูเมน | E230: Power Tools | F230: HPC List | G230: =(ProductMaster_iPST_iPower[[#This Row],[SellPrice (Inc. VAT)]]*100)/107 -> 2325.2336 | H230: 2488 | I230: *4892210203458*
B231: 016110174 | C231: IR HL450 ASIA | D231: ไฟฉายคาดหัว 450 ลูเมน | E231: Power Tools | F231: HPC List | G231: =(ProductMaster_iPST_iPower[[#This Row],[SellPrice (Inc. VAT)]]*100)/107 -> 2231.7757 | H231: 2388 | I231: #N/A
A232: 4892210203441 | B232: 016141004 | C232: IR PL250 | D232: ไฟฉายปากกา แบบชาร์จไฟได้ 250 ลูเมน | E232: Power Tools | F232: HPC List | G232: =(ProductMaster_iPST_iPower[[#This Row],[SellPrice (Inc. VAT)]]*100)/107 -> 2138.3178 | H232: 2288 | I232: *4892210203441*
A233: 4892210211262 | B233: 018331015 | C233: L4 FFL-301 ASIA | D233: ไฟส่องทำงาน แบบบานพับ | E233: Power Tools | F233: HPC List | G233: =(ProductMaster_iPST_iPower[[#This Row],[SellPrice (Inc. VAT)]]*100)/107 -> 2699.0654 | H233: 2888 | I233: *4892210211262*
A234: 4892210223265 | B234: 016163004 | C234: L4 HL2-301 ASIA | D234: ไฟฉายคาดหัว แอลอีดี | E234: Power Tools | F234: HPC List | G234: =(ProductMaster_iPST_iPower[[#This Row],[SellPrice (Inc. VAT)]]*100)/107 -> 2699.0654 | H234: 2888 | I234: *4892210223265*
A235: 4892210211019 | B235: 016137016 | C235: L4 TMLED-301 ASIA | D235: ไฟฉายโลหะหมุนปรับแสง แอลอีดี | E235: Power Tools | F235: HPC List | G235: =(ProductMaster_iPST_iPower[[#This Row],[SellPrice (Inc. VAT)]]*100)/107 -> 3259.8131 | H235: 3488 | I235: *4892210211019*
A236: 4892210201416 | B236: 016144005 | C236: M12 AF-0 ASIA | D236: พัดลมไร้สาย 12 โวลต์ (เครื่องเปล่า) | E236: Power Tools | F236: HPC List | G236: =(ProductMaster_iPST_iPower[[#This Row],[SellPrice (Inc. VAT)]]*100)/107 -> 3072.8972 | H236: 3288 | I236: *4892210201416*
A237: 4892210130266 | B237: 001998232 | C237: M12 B2 ASIA | D237: แบตเตอรี่ 12 โวลต์ 2.0 แอมป์อาว | E237: Power Tools | F237: HPC List | G237: =(ProductMaster_iPST_iPower[[#This Row],[SellPrice (Inc. VAT)]]*100)/107 -> 1110.2804 | H237: 1188 | I237: *4892210130266*
A238: 4892210130273 | B238: 001998233 | C238: M12 B4 ASIA | D238: แบตเตอรี่ 12 โวลต์ 4.0 แอมป์อาว | E238: Power Tools | F238: HPC List | G238: =(ProductMaster_iPST_iPower[[#This Row],[SellPrice (Inc. VAT)]]*100)/107 -> 1764.486 | H238: 1888 | I238: *4892210130273*
A239: 4892210201423 | B239: 016142004 | C239: M12 BBL-0 APJ | D239: เครื่องเป่าลมไร้สาย 12 โวลต์ (เครื่องเปล่า) | E239: Power Tools | F239: HPC List | G239: =(ProductMaster_iPST_iPower[[#This Row],[SellPrice (Inc. VAT)]]*100)/107 -> 3259.8131 | H239: 3488 | I239: *4892210201423*
A240: 4892210223715 | B240: 016723009 | C240: M12 BHCS7L-0 APJ | D240: M12 เครื่องพ่นยาไร้สาย | E240: Power Tools | F240: HPC List | G240: =(ProductMaster_iPST_iPower[[#This Row],[SellPrice (Inc. VAT)]]*100)/107 -> 6998.1308 | H240: 7488 | I240: *4892210223715*
A241: 4892210220929 | B241: 016088017 | C241: M12 BI-0 ASIA | D241: เครื่องเติมลมไร้สาย 12 โวลต์ (เครื่องเปล่า) | E241: Power Tools | F241: HPC List | G241: =(ProductMaster_iPST_iPower[[#This Row],[SellPrice (Inc. VAT)]]*100)/107 -> 3633.6449 | H241: 3888 | I241: *4892210220929*
A242: 019601194 | B242: 019601194 | C242: M12 BLPRS TH | D242: M12 กรรไกรตัดกิ่งไร้สาย | E242: Power Tools | F242: HPC List | G242: =(ProductMaster_iPST_iPower[[#This Row],[SellPrice (Inc. VAT)]]*100)/107 -> 7745.7944 | H242: 8288 | I242: *019601194*
A243: 4892210174987 | B243: 018252007 | C243: M12 BPRT-0C | D243: เครื่องยิงรีเวทไร้สาย 12 โวลต์ (เครื่องเปล่า) | E243: Power Tools | F243: HPC List | G243: =(ProductMaster_iPST_iPower[[#This Row],[SellPrice (Inc. VAT)]]*100)/107 -> 6811.215 | H243: 7288 | I243: *4892210174987*
A244: 4892210135186 | B244: 018109013 | C244: M12 BPS-0 | D244: เครื่องขัดไร้สาย 12 โวลต์ (เครื่องเปล่า) | E244: Power Tools | F244: HPC List | G244: =(ProductMaster_iPST_iPower[[#This Row],[SellPrice (Inc. VAT)]]*100)/107 -> 3166.3551 | H244: 3388 | I244: *4892210135186*
A245: 4892210159175 | B245: 018098036 | C245: M12 CH-0C | D245: สว่านโรตารี่ไร้สาย 12 โวลต์ ระบบ SDS+ (เครื่องเปล่า) | E245: Power Tools | F245: HPC List | G245: =(ProductMaster_iPST_iPower[[#This Row],[SellPrice (Inc. VAT)]]*100)/107 -> 6764.486 | H245: 7238 | I245: *4892210159175*
A246: 4892210135179 | B246: 018099014 | C246: M12 CHZ-0 | D246: เลื่อยอเนกประสงค์ไร้สาย 12 โวลต์ (เครื่องเปล่า) | E246: Power Tools | F246: HPC List | G246: =(ProductMaster_iPST_iPower[[#This Row],[SellPrice (Inc. VAT)]]*100)/107 -> 4661.6822 | H246: 4988 | I246: *4892210135179*
A247: 4892210198334 | B247: 006912604 | C247: M12 CLLP-0C ASIA | D247: เลเซอร์วัดระดับและวางแนวดิ่ง (เครื่องเปล่า) | E247: Power Tools | F247: HPC List | G247: =(ProductMaster_iPST_iPower[[#This Row],[SellPrice (Inc. VAT)]]*100)/107 -> 15783.178 | H247: 16888 | I247: *4892210198334*
A248: 4892210214065 | B248: 016149004 | C248: M12 CML-0 | D248: ไฟส่องเทียบสีไร้สาย 12 โวลต์ (เครื่องเปล่า) | E248: Power Tools | F248: HPC List | G248: =(ProductMaster_iPST_iPower[[#This Row],[SellPrice (Inc. VAT)]]*100)/107 -> 4007.4766 | H248: 4288 | I248: *4892210214065*
A249: 4892210227836 | B249: 018669012 | C249: M12 FBFL10-0 ASIA | D249: M12 เครื่องขัดกระดาษทรายสายพาน | E249: Power Tools | F249: HPC List | G249: =(ProductMaster_iPST_iPower[[#This Row],[SellPrice (Inc. VAT)]]*100)/107 -> 6811.215 | H249: 7288 | I249: *4892210227836*
B250: 018723006 | C250: M12 FCN18GS-0X0 ASIA | D250: M12 เครื่องยิงตะปูไร้สาย 18Ga | E250: Power Tools | F250: HPC List | G250: =(ProductMaster_iPST_iPower[[#This Row],[SellPrice (Inc. VAT)]]*100)/107 -> 9334.5794 | H250: 9988 | I250: #N/A
A251: 4892210182531 | B251: 018264007 | C251: M12 FCOT-0X | D251: เครื่องตัดไร้สาย 12 โวลต์ 3 นิ้ว (เครื่องเปล่า) | E251: Power Tools | F251: HPC List | G251: =(ProductMaster_iPST_iPower[[#This Row],[SellPrice (Inc. VAT)]]*100)/107 -> 5689.7196 | H251: 6088 | I251: *4892210182531*
A252: 4892210185983 | B252: 018365009 | C252: M12 FDDXKIT-0X ASIA | D252: สว่านไขควงไร้สาย 12 โวลต์ พร้อมชุดหัวงานติดตั้ง (เครื่องเปล่า) | E252: Power Tools | F252: HPC List | G252: =(ProductMaster_iPST_iPower[[#This Row],[SellPrice (Inc. VAT)]]*100)/107 -> 8026.1682 | H252: 8588 | I252: *4892210185983*
A253: 4892210187239 | B253: 018394009 | C253: M12 FDGA-0 | D253: เครื่องเจียรแกนหัวงอไร้สาย 12 โวลต์ (เครื่องเปล่า) | E253: Power Tools | F253: HPC List | G253: =(ProductMaster_iPST_iPower[[#This Row],[SellPrice (Inc. VAT)]]*100)/107 -> 5502.8037 | H253: 5888 | I253: *4892210187239*
A254: 4892210189578 | B254: 018393007 | C254: M12 FDGS-0 | D254: เครื่องเจียรแกนคอตรงไร้สาย 12 โวลต์ (เครื่องเปล่า) | E254: Power Tools | F254: HPC List | G254: =(ProductMaster_iPST_iPower[[#This Row],[SellPrice (Inc. VAT)]]*100)/107 -> 5315.8879 | H254: 5688 | I254: *4892210189578*
A255: 4892210199430 | B255: 018526006 | C255: M12 FHIR14-0 | D255: ประแจบล็อกด้ามฟรีไร้สาย 12 โวลต์ 1/4" (เครื่องเปล่า) | E255: Power Tools | F255: HPC List | G255: =(ProductMaster_iPST_iPower[[#This Row],[SellPrice (Inc. VAT)]]*100)/107 -> 5502.8037 | H255: 5888 | I255: *4892210199430*
A256: 4892210199447 | B256: 018527007 | C256: M12 FHIR38-0 | D256: ประแจบล็อกด้ามฟรีไร้สาย 12 โวลต์ 3/8" (เครื่องเปล่า) | E256: Power Tools | F256: HPC List | G256: =(ProductMaster_iPST_iPower[[#This Row],[SellPrice (Inc. VAT)]]*100)/107 -> 5783.1776 | H256: 6188 | I256: *4892210199447*
A257: 4892210195234 | B257: 018488007 | C257: M12 FHS-0X | D257: เลื่อยตัดกิ่งไร้สาย 12 โวลต์ (เครื่องเปล่า) | E257: Power Tools | F257: HPC List | G257: =(ProductMaster_iPST_iPower[[#This Row],[SellPrice (Inc. VAT)]]*100)/107 -> 6717.757 | H257: 7188 | I257: *4892210195234*
A258: 4892210215499 | B258: 018240006 | C258: M12 FHT20-0 ASIA | D258: เครื่องตัดแต่งพุ่มไม้ไร้สาย 12 โวลต์ (เครื่องเปล่า) | E258: Power Tools | F258: HPC List | G258: =(ProductMaster_iPST_iPower[[#This Row],[SellPrice (Inc. VAT)]]*100)/107 -> 4568.2243 | H258: 4888 | I258: *4892210215499*
A259: 4892210219831 | B259: 018620017 | C259: M12 FID2-0 | D259: ไขควงกระแทกไร้สาย 18 โวลต์ (เครื่องเปล่า) | E259: Power Tools | F259: HPC List | G259: =(ProductMaster_iPST_iPower[[#This Row],[SellPrice (Inc. VAT)]]*100)/107 -> 4231.7757 | H259: 4528 | I259: *4892210219831*
A260: 4892210163462 | B260: 018270007 | C260: M12 FIR12-0 | D260: ประแจบล็อกด้ามฟรีไร้สาย 12 โวลต์ 1/2" (เครื่องเปล่า) | E260: Power Tools | F260: HPC List | G260: =(ProductMaster_iPST_iPower[[#This Row],[SellPrice (Inc. VAT)]]*100)/107 -> 5970.0935 | H260: 6388 | I260: *4892210163462*
A261: 4892210163479 | B261: 018269009 | C261: M12 FIR38-0 | D261: ประแจบล็อกด้ามฟรีไร้สาย 12 โวลต์ 3/8" (เครื่องเปล่า) | E261: Power Tools | F261: HPC List | G261: =(ProductMaster_iPST_iPower[[#This Row],[SellPrice (Inc. VAT)]]*100)/107 -> 5783.1776 | H261: 6188 | I261: *4892210163479*
A262: 4892210174840 | B262: 018312019 | C262: M12 FIWF12-0C | D262: บล็อกกระแทกไร้สาย 12 โวลต์ 1/2" (เครื่องเปล่า) | E262: Power Tools | F262: HPC List | G262: =(ProductMaster_iPST_iPower[[#This Row],[SellPrice (Inc. VAT)]]*100)/107 -> 5596.2617 | H262: 5988 | I262: *4892210174840*
... A264: 4892210219978 | B264: 018622023 | C264: M12 FPD2-0 | D264: ไขควงกระแทกไร้สาย 12 โวลต์ (เครื่องเปล่า) | E264: Power Tools | F264: HPC List | G264: =(ProductMaster_iPST_iPower[[#This Row],[SellPrice (Inc. VAT)]]*100)/107 -> 4708.4112 | H264: 5038 | I264: *4892210219978*
B265: 018686009 | C265: M12 FPTR-0 ASIA | D265: M12 FUEL™ INSIDER™ ประแจบล็อกด้ามฟรีไร้สายแบบเปลี่ยนหัว | E265: Power Tools | F265: HPC List | G265: =(ProductMaster_iPST_iPower[[#This Row],[SellPrice (Inc. VAT)]]*100)/107 -> 8493.4579 | H265: 9088 | I265: #N/A
A266: 4892210182494 | B266: 018370003 | C266: M12 FQID-0 ASIA | D266: ไขควงกระแทกไร้สาย 12 โวลต์ ระบบไฮดรอลิก (เครื่องเปล่า) | E266: Power Tools | F266: HPC List | G266: =(ProductMaster_iPST_iPower[[#This Row],[SellPrice (Inc. VAT)]]*100)/107 -> 5970.0935 | H266: 6388 | I266: *4892210182494*
A267: 4892210190024 | B267: 018423012 | C267: M12 FRAIWF12-0 ASIA | D267: บล็อกกระแทกมุมฉากไร้สาย 12 โวลต์ 1/2" (เครื่องเปล่า) | E267: Power Tools | F267: HPC List | G267: =(ProductMaster_iPST_iPower[[#This Row],[SellPrice (Inc. VAT)]]*100)/107 -> 6343.9252 | H267: 6788 | I267: *4892210190024*
A268: 4892210195708 | B268: 016134009 | C268: M12 FVCL-0 ASIA | D268: เครื่องดูดฝุ่น แบบเปียก/แห้ง ไร้สาย 12 โวลต์ (เครื่องเปล่า) | E268: Power Tools | F268: HPC List | G268: =(ProductMaster_iPST_iPower[[#This Row],[SellPrice (Inc. VAT)]]*100)/107 -> 6998.1308 | H268: 7488 | I268: *4892210195708*
A269: 4892210194770 | B269: 018482021 | C269: M12 GG-0 ASIA | D269: เครื่องอัดจารบีไร้สาย 12 โวลต์ (เครื่องเปล่า) | E269: Power Tools | F269: HPC List | G269: =(ProductMaster_iPST_iPower[[#This Row],[SellPrice (Inc. VAT)]]*100)/107 -> 6063.5514 | H269: 6488 | I269: *4892210194770*
A270: 4892210220677 | B270: 001997033 | C270: M12 HB5 | D270: แบตเตอรี่ 12 โวลต์ 5.0 แอมป์อาว HIGH OUTPUT | E270: Power Tools | F270: HPC List | G270: =(ProductMaster_iPST_iPower[[#This Row],[SellPrice (Inc. VAT)]]*100)/107 -> 2325.2336 | H270: 2488 | I270: *4892210220677*
A271: 4892210193032 | B271: 016047007 | C271: M12 LL-0 APJ | D271: ไฟตะเกียง 12 โวลต์ พร้อมที่ชาร์จ USB (เครื่องเปล่า) | E271: Power Tools | F271: HPC List | G271: =(ProductMaster_iPST_iPower[[#This Row],[SellPrice (Inc. VAT)]]*100)/107 -> 2885.9813 | H271: 3088 | I271: *4892210193032*
A272: 4892210188496 | B272: 018302008 | C272: M12 ONEFTR12-0C | D272: ประแจปอนด์ดิจิทัลไร้สาย 12 โวลต์ 1/2" (เครื่องเปล่า) | E272: Power Tools | F272: HPC List | G272: =(ProductMaster_iPST_iPower[[#This Row],[SellPrice (Inc. VAT)]]*100)/107 -> 28400 | H272: 30388 | I272: *4892210188496*
...

Sheet OtherMaster
A1: ReceiveType | C1: User | E1: Remark
A2: Cash | C2: Mook | E2: Tax Invoice
A3: Transfer | C3: New | E3: No Tax Invoice
A4: Credit Card | C4: Namtarn
A5: Cash & Card | C5: Cat
A6: Transfer & Card
A7: Online (Kerry)
